Workbook
Name PCEntradasN1_Nível_1: TbPCEntradasN1[Nível 1]
Name PCEntradasN1_Nível_1: TbPCEntradasN1[Nível 1]
Name PCEntradasN2_Nível_1: TbPCEntradasN2[Nível 1]
Name PCEntradasN2_Nível_1: TbPCEntradasN2[Nível 1]
Name PCEntradasN2_Nível_2: TbPCEntradasN2[Nível 2]
Name PCEntradasN2_Nível_2: TbPCEntradasN2[Nível 2]
Name PCSaídasN1_Nível_1: TbPCSaídasN1[Nível 1]
Name PCSaídasN1_Nível_1: TbPCSaídasN1[Nível 1]
Name PCSaídasN2_Nível_1: TbPCSaídasN2[Nível 1]
Name PCSaídasN2_Nível_1: TbPCSaídasN2[Nível 1]
Name PCSaídasN2_Nível_2: TbPCSaídasN2[Nível 2]
Name PCSaídasN2_Nível_2: TbPCSaídasN2[Nível 2]
Name Slicer_Ano_Competência: #N/A
Name Slicer_Ano_Competência1: #N/A
Name Slicer_Ano_Previsto: #N/A
Name Slicer_Ano_Previsto1: #N/A
Name Slicer_Ano_Previsto2: #N/A
Name Slicer_Mês_Competência: #N/A
Name Slicer_Mês_Competência1: #N/A
Name Slicer_Mês_Previsto: #N/A
Name Slicer_Mês_Previsto1: #N/A

Sheet Início
B1: Educaçãoweb | N1: FLUXO DE CAIXA EMPRESARIAL
B3: Empresa
B4: LOJAS EDUCANDOWEB LTDA.
B7: Responsável
B8: Victor Von Doom

Sheet Matriz
B1: Educaçãoweb | N1: TÍTULO

Sheet PCEntradasN1
B1: Educaçãoweb | N1: PLANO DE CONTAS DE ENTRADA - Nível 1
B3: PLANO DE CONTAS DE ENTRADA NÍVEL 1
B4: Nível 1
B5: Empréstimos de curto prazo
B6: Financiamentos de longo prazo
B7: Receitas Financeiras
B8: Venda de ativos
B9: Vendas de mercadorias

Sheet PCEntradasN2
B1: Educaçãoweb | N1: PLANO DE CONTAS DE ENTRADA - Nível 2
B3: PLANO DE CONTAS DE ENTRADA NÍVEL 2
B4: Nível 1 | C4: Nível 2
B5: Empréstimos de curto prazo | C5: Empréstimos capital de giro
B6: Receitas Financeiras | C6: Juros sobre aplicações
B7: Venda de ativos | C7: Mobiliário próprio
B8: Vendas de mercadorias | C8: Eletrodomésticos
B9: Vendas de mercadorias | C9: Informática
B10: Vendas de mercadorias | C10: Livros
B11: Vendas de mercadorias | C11: Móveis
B12: Vendas de mercadorias | C12: Som e imagem
B13: Financiamentos de longo prazo | C13: Geral

Sheet PCSaídasN1
B1: Educaçãoweb | N1: PLANO DE CONTAS DE SAÍDA - Nível 1
B3: PLANO DE CONTAS DE SAÍDA NÍVEL 1
B4: Nível 1
B5: Compra de mercadorias
B6: Despesas administrativas
B7: Despesas comerciais
B8: Despesas financeiras
B9: Imposto de renda
B10: Impostos sobre as vendas

Sheet PCSaídasN2
B1: Educaçãoweb | N1: PLANO DE CONTAS DE SAÍDA - Nível 2
B3: PLANO DE CONTAS DE SAÍDA NÍVEL 2
B4: Nível 1 | C4: Nível 2
B5: Compra de mercadorias | C5: Eletrodomésticos
B6: Compra de mercadorias | C6: Informática
B7: Compra de mercadorias | C7: Livros
B8: Compra de mercadorias | C8: Som e imagem
B9: Compra de mercadorias | C9: Vestuário
B10: Despesas administrativas | C10: Comunicação - internet e telefonia
B11: Despesas administrativas | C11: Energia elétrica
B12: Despesas comerciais | C12: Encargos sobre os salários dos vendedores
B13: Despesas comerciais | C13: Salários dos vendedores
B14: Despesas financeiras | C14: Juros sobre empréstimos
B15: Imposto de renda | C15: IR sobre o lucro presumido
B16: Impostos sobre as vendas | C16: Geral

Sheet RegistroEntradas
B1: Educaçãoweb | H1: REGISTRO DAS ENTRADAS DE CAIXA
B3: Data do Caixa Realizado | C3: Data da Competência | D3: Data do Caixa Previsto | E3: Conta Nível 1 | F3: Conta Nível 2 | G3: Histórico | H3: Valor | I3: Mês Caixa | J3: Ano Caixa | K3: Mês Competência | L3: Ano Competência | M3: Mês Previsto | N3: Ano Previsto | O3: Conta Vencida | P3: Venda à Vista | Q3: Dias de Atraso
B4: 42994 | C4: 42957 | D4: 42972 | E4: Vendas de mercadorias | F4: Informática | G4: NF7238 | H4: 1133 | I4: =IF(TbRegistroEntradas[[#This Row],[Data do Caixa Realizado]]="",0,MONTH(TbRegistroEntradas[[#This Row],[Data do Caixa Realizado]])) -> 9 | J4: =IF(TbRegistroEntradas[[#This Row],[Data do Caixa Realizado]]="",0,YEAR(TbRegistroEntradas[[#This Row],[Data do Caixa Realizado]])) -> 2017 | K4: =IF(TbRegistroEntradas[[#This Row],[Data da Competência]]="",0,MONTH(TbRegistroEntradas[[#This Row],[Data da Competência]])) -> 8 | L4: =IF(TbRegistroEntradas[[#This Row],[Data da Competência]]="",0,YEAR(TbRegistroEntradas[[#This Row],[Data da Competência]])) -> 2017 | M4: =IF(TbRegistroEntradas[[#This Row],[Data do Caixa Previsto]]="",0,MONTH(TbRegistroEntradas[[#This Row],[Data do Caixa Previsto]])) -> 8 | N4: =IF(TbRegistroEntradas[[#This Row],[Data do Caixa Previsto]]="",0,YEAR(TbRegistroEntradas[[#This Row],[Data do Caixa Previsto]])) -> 2017 | O4: =IF(AND(TbRegistroEntradas[[#This Row],[Data do Caixa Previsto]]<TODAY(),TbRegistroEntradas[[#This Row],[Data do Caixa Realizado]]=""),"Vencida","Não Vencida") -> Não Vencida | P4: =IF(TbRegistroEntradas[[#This Row],[Data da Competência]]=TbRegistroEntradas[[#This Row],[Data do Caixa Previsto]],"Vista","Prazo") -> Prazo | Q4: =IF(TbRegistroEntradas[[#This Row],[Data do Caixa Realizado]]<>"", IF(TbRegistroEntradas[[#This Row],[Data do Caixa Realizado]]>TbRegistroEntradas[[#This Row],[Data do Caixa Previsto]], TbRegistroEntradas[[#This Row],[Data do Caixa Realizado]]-TbRegistroEntradas[[#This Row],[Data do Caixa Previsto]], 0 ), IF(TODAY()>TbRegistroEntradas[[#This Row],[Data do Caixa Previsto]], TODAY()-TbRegistroEntradas[[#This Row],[Data do Caixa Previsto]], 0 ) ) -> 22
B5: 42985 | C5: 42960 | D5: 42985 | E5: Vendas de mercadorias | F5: Móveis | G5: NF9147 | H5: 164 | I5: =IF(TbRegistroEntradas[[#This Row],[Data do Caixa Realizado]]="",0,MONTH(TbRegistroEntradas[[#This Row],[Data do Caixa Realizado]])) -> 9 | J5: =IF(TbRegistroEntradas[[#This Row],[Data do Caixa Realizado]]="",0,YEAR(TbRegistroEntradas[[#This Row],[Data do Caixa Realizado]])) -> 2017 | K5: =IF(TbRegistroEntradas[[#This Row],[Data da Competência]]="",0,MONTH(TbRegistroEntradas[[#This Row],[Data da Competência]])) -> 8 | L5: =IF(TbRegistroEntradas[[#This Row],[Data da Competência]]="",0,YEAR(TbRegistroEntradas[[#This Row],[Data da Competência]])) -> 2017 | M5: =IF(TbRegistroEntradas[[#This Row],[Data do Caixa Previsto]]="",0,MONTH(TbRegistroEntradas[[#This Row],[Data do Caixa Previsto]])) -> 9 | N5: =IF(TbRegistroEntradas[[#This Row],[Data do Caixa Previsto]]="",0,YEAR(TbRegistroEntradas[[#This Row],[Data do Caixa Previsto]])) -> 2017 | O5: =IF(AND(TbRegistroEntradas[[#This Row],[Data do Caixa Previsto]]<TODAY(),TbRegistroEntradas[[#This Row],[Data do Caixa Realizado]]=""),"Vencida","Não Vencida") -> Não Vencida | P5: =IF(TbRegistroEntradas[[#This Row],[Data da Competência]]=TbRegistroEntradas[[#This Row],[Data do Caixa Previsto]],"Vista","Prazo") -> Prazo | Q5: =IF(TbRegistroEntradas[[#This Row],[Data do Caixa Realizado]]<>"", IF(TbRegistroEntradas[[#This Row],[Data do Caixa Realizado]]>TbRegistroEntradas[[#This Row],[Data do Caixa Previsto]], TbRegistroEntradas[[#This Row],[Data do Caixa Realizado]]-TbRegistroEntradas[[#This Row],[Data do Caixa Previsto]], 0 ), IF(TODAY()>TbRegistroEntradas[[#This Row],[Data do Caixa Previsto]], TODAY()-TbRegistroEntradas[[#This Row],[Data do Caixa Previsto]], 0 ) ) -> 0
B6: 43007 | C6: 42964 | D6: 43001 | E6: Vendas de mercadorias | F6: Móveis | G6: NF8005 | H6: 2937 | I6: =IF(TbRegistroEntradas[[#This Row],[Data do Caixa Realizado]]="",0,MONTH(TbRegistroEntradas[[#This Row],[Data do Caixa Realizado]])) -> 9 | J6: =IF(TbRegistroEntradas[[#This Row],[Data do Caixa Realizado]]="",0,YEAR(TbRegistroEntradas[[#This Row],[Data do Caixa Realizado]])) -> 2017 | K6: =IF(TbRegistroEntradas[[#This Row],[Data da Competência]]="",0,MONTH(TbRegistroEntradas[[#This Row],[Data da Competência]])) -> 8 | L6: =IF(TbRegistroEntradas[[#This Row],[Data da Competência]]="",0,YEAR(TbRegistroEntradas[[#This Row],[Data da Competência]])) -> 2017 | M6: =IF(TbRegistroEntradas[[#This Row],[Data do Caixa Previsto]]="",0,MONTH(TbRegistroEntradas[[#This Row],[Data do Caixa Previsto]])) -> 9 | N6: =IF(TbRegistroEntradas[[#This Row],[Data do Caixa Previsto]]="",0,YEAR(TbRegistroEntradas[[#This Row],[Data do Caixa Previsto]])) -> 2017 | O6: =IF(AND(TbRegistroEntradas[[#This Row],[Data do Caixa Previsto]]<TODAY(),TbRegistroEntradas[[#This Row],[Data do Caixa Realizado]]=""),"Vencida","Não Vencida") -> Não Vencida | P6: =IF(TbRegistroEntradas[[#This Row],[Data da Competência]]=TbRegistroEntradas[[#This Row],[Data do Caixa Previsto]],"Vista","Prazo") -> Prazo | Q6: =IF(TbRegistroEntradas[[#This Row],[Data do Caixa Realizado]]<>"", IF(TbRegistroEntradas[[#This Row],[Data do Caixa Realizado]]>TbRegistroEntradas[[#This Row],[Data do Caixa Previsto]], TbRegistroEntradas[[#This Row],[Data do Caixa Realizado]]-TbRegistroEntradas[[#This Row],[Data do Caixa Previsto]], 0 ), IF(TODAY()>TbRegistroEntradas[[#This Row],[Data do Caixa Previsto]], TODAY()-TbRegistroEntradas[[#This Row],[Data do Caixa Previsto]], 0 ) ) -> 6
B7: 43020 | C7: 42969 | D7: 43020 | E7: Vendas de mercadorias | F7: Som e imagem | G7: NF5493 | H7: 807 | I7: =IF(TbRegistroEntradas[[#This Row],[Data do Caixa Realizado]]="",0,MONTH(TbRegistroEntradas[[#This Row],[Data do Caixa Realizado]])) -> 10 | J7: =IF(TbRegistroEntradas[[#This Row],[Data do Caixa Realizado]]="",0,YEAR(TbRegistroEntradas[[#This Row],[Data do Caixa Realizado]])) -> 2017 | K7: =IF(TbRegistroEntradas[[#This Row],[Data da Competência]]="",0,MONTH(TbRegistroEntradas[[#This Row],[Data da Competência]])) -> 8 | L7: =IF(TbRegistroEntradas[[#This Row],[Data da Competência]]="",0,YEAR(TbRegistroEntradas[[#This Row],[Data da Competência]])) -> 2017 | M7: =IF(TbRegistroEntradas[[#This Row],[Data do Caixa Previsto]]="",0,MONTH(TbRegistroEntradas[[#This Row],[Data do Caixa Previsto]])) -> 10 | N7: =IF(TbRegistroEntradas[[#This Row],[Data do Caixa Previsto]]="",0,YEAR(TbRegistroEntradas[[#This Row],[Data do Caixa Previsto]])) -> 2017 | O7: =IF(AND(TbRegistroEntradas[[#This Row],[Data do Caixa Previsto]]<TODAY(),TbRegistroEntradas[[#This Row],[Data do Caixa Realizado]]=""),"Vencida","Não Vencida") -> Não Vencida | P7: =IF(TbRegistroEntradas[[#This Row],[Data da Competência]]=TbRegistroEntradas[[#This Row],[Data do Caixa Previsto]],"Vista","Prazo") -> Prazo | Q7: =IF(TbRegistroEntradas[[#This Row],[Data do Caixa Realizado]]<>"", IF(TbRegistroEntradas[[#This Row],[Data do Caixa Realizado]]>TbRegistroEntradas[[#This Row],[Data do Caixa Previsto]], TbRegistroEntradas[[#This Row],[Data do Caixa Realizado]]-TbRegistroEntradas[[#This Row],[Data do Caixa Previsto]], 0 ), IF(TODAY()>TbRegistroEntradas[[#This Row],[Data do Caixa Previsto]], TODAY()-TbRegistroEntradas[[#This Row],[Data do Caixa Previsto]], 0 ) ) -> 0
B8: 43014 | C8: 42972 | D8: 43014 | E8: Vendas de mercadorias | F8: Informática | G8: NF7946 | H8: 2612 | I8: =IF(TbRegistroEntradas[[#This Row],[Data do Caixa Realizado]]="",0,MONTH(TbRegistroEntradas[[#This Row],[Data do Caixa Realizado]])) -> 10 | J8: =IF(TbRegistroEntradas[[#This Row],[Data do Caixa Realizado]]="",0,YEAR(TbRegistroEntradas[[#This Row],[Data do Caixa Realizado]])) -> 2017 | K8: =IF(TbRegistroEntradas[[#This Row],[Data da Competência]]="",0,MONTH(TbRegistroEntradas[[#This Row],[Data da Competência]])) -> 8 | L8: =IF(TbRegistroEntradas[[#This Row],[Data da Competência]]="",0,YEAR(TbRegistroEntradas[[#This Row],[Data da Competência]])) -> 2017 | M8: =IF(TbRegistroEntradas[[#This Row],[Data do Caixa Previsto]]="",0,MONTH(TbRegistroEntradas[[#This Row],[Data do Caixa Previsto]])) -> 10 | N8: =IF(TbRegistroEntradas[[#This Row],[Data do Caixa Previsto]]="",0,YEAR(TbRegistroEntradas[[#This Row],[Data do Caixa Previsto]])) -> 2017 | O8: =IF(AND(TbRegistroEntradas[[#This Row],[Data do Caixa Previsto]]<TODAY(),TbRegistroEntradas[[#This Row],[Data do Caixa Realizado]]=""),"Vencida","Não Vencida") -> Não Vencida | P8: =IF(TbRegistroEntradas[[#This Row],[Data da Competência]]=TbRegistroEntradas[[#This Row],[Data do Caixa Previsto]],"Vista","Prazo") -> Prazo | Q8: =IF(TbRegistroEntradas[[#This Row],[Data do Caixa Realizado]]<>"", IF(TbRegistroEntradas[[#This Row],[Data do Caixa Realizado]]>TbRegistroEntradas[[#This Row],[Data do Caixa Previsto]], TbRegistroEntradas[[#This Row],[Data do Caixa Realizado]]-TbRegistroEntradas[[#This Row],[Data do Caixa Previsto]], 0 ), IF(TODAY()>TbRegistroEntradas[[#This Row],[Data do Caixa Previsto]], TODAY()-TbRegistroEntradas[[#This Row],[Data do Caixa Previsto]], 0 ) ) -> 0
B9: 43054 | C9: 42974 | D9: 43030 | E9: Vendas de mercadorias | F9: Móveis | G9: NF8598 | H9: 2483 | I9: =IF(TbRegistroEntradas[[#This Row],[Data do Caixa Realizado]]="",0,MONTH(TbRegistroEntradas[[#This Row],[Data do Caixa Realizado]])) -> 11 | J9: =IF(TbRegistroEntradas[[#This Row],[Data do Caixa Realizado]]="",0,YEAR(TbRegistroEntradas[[#This Row],[Data do Caixa Realizado]])) -> 2017 | K9: =IF(TbRegistroEntradas[[#This Row],[Data da Competência]]="",0,MONTH(TbRegistroEntradas[[#This Row],[Data da Competência]])) -> 8 | L9: =IF(TbRegistroEntradas[[#This Row],[Data da Competência]]="",0,YEAR(TbRegistroEntradas[[#This Row],[Data da Competência]])) -> 2017 | M9: =IF(TbRegistroEntradas[[#This Row],[Data do Caixa Previsto]]="",0,MONTH(TbRegistroEntradas[[#This Row],[Data do Caixa Previsto]])) -> 10 | N9: =IF(TbRegistroEntradas[[#This Row],[Data do Caixa Previsto]]="",0,YEAR(TbRegistroEntradas[[#This Row],[Data do Caixa Previsto]])) -> 2017 | O9: =IF(AND(TbRegistroEntradas[[#This Row],[Data do Caixa Previsto]]<TODAY(),TbRegistroEntradas[[#This Row],[Data do Caixa Realizado]]=""),"Vencida","Não Vencida") -> Não Vencida | P9: =IF(TbRegistroEntradas[[#This Row],[Data da Competência]]=TbRegistroEntradas[[#This Row],[Data do Caixa Previsto]],"Vista","Prazo") -> Prazo | Q9: =IF(TbRegistroEntradas[[#This Row],[Data do Caixa Realizado]]<>"", IF(TbRegistroEntradas[[#This Row],[Data do Caixa Realizado]]>TbRegistroEntradas[[#This Row],[Data do Caixa Previsto]], TbRegistroEntradas[[#This Row],[Data do Caixa Realizado]]-TbRegistroEntradas[[#This Row],[Data do Caixa Previsto]], 0 ), IF(TODAY()>TbRegistroEntradas[[#This Row],[Data do Caixa Previsto]], TODAY()-TbRegistroEntradas[[#This Row],[Data do Caixa Previsto]], 0 ) ) -> 24
B10: 43087 | C10: 42979 | D10: 43009 | E10: Vendas de mercadorias | F10: Informática | G10: NF1535 | H10: 4387 | I10: =IF(TbRegistroEntradas[[#This Row],[Data do Caixa Realizado]]="",0,MONTH(TbRegistroEntradas[[#This Row],[Data do Caixa Realizado]])) -> 12 | J10: =IF(TbRegistroEntradas[[#This Row],[Data do Caixa Realizado]]="",0,YEAR(TbRegistroEntradas[[#This Row],[Data do Caixa Realizado]])) -> 2017 | K10: =IF(TbRegistroEntradas[[#This Row],[Data da Competência]]="",0,MONTH(TbRegistroEntradas[[#This Row],[Data da Competência]])) -> 9 | L10: =IF(TbRegistroEntradas[[#This Row],[Data da Competência]]="",0,YEAR(TbRegistroEntradas[[#This Row],[Data da Competência]])) -> 2017 | M10: =IF(TbRegistroEntradas[[#This Row],[Data do Caixa Previsto]]="",0,MONTH(TbRegistroEntradas[[#This Row],[Data do Caixa Previsto]])) -> 10 | N10: =IF(TbRegistroEntradas[[#This Row],[Data do Caixa Previsto]]="",0,YEAR(TbRegistroEntradas[[#This Row],[Data do Caixa Previsto]])) -> 2017 | O10: =IF(AND(TbRegistroEntradas[[#This Row],[Data do Caixa Previsto]]<TODAY(),TbRegistroEntradas[[#This Row],[Data do Caixa Realizado]]=""),"Vencida","Não Vencida") -> Não Vencida | P10: =IF(TbRegistroEntradas[[#This Row],[Data da Competência]]=TbRegistroEntradas[[#This Row],[Data do Caixa Previsto]],"Vista","Prazo") -> Prazo | Q10: =IF(TbRegistroEntradas[[#This Row],[Data do Caixa Realizado]]<>"", IF(TbRegistroEntradas[[#This Row],[Data do Caixa Realizado]]>TbRegistroEntradas[[#This Row],[Data do Caixa Previsto]], TbRegistroEntradas[[#This Row],[Data do Caixa Realizado]]-TbRegistroEntradas[[#This Row],[Data do Caixa Previsto]], 0 ), IF(TODAY()>TbRegistroEntradas[[#This Row],[Data do Caixa Previsto]], TODAY()-TbRegistroEntradas[[#This Row],[Data do Caixa Previsto]], 0 ) ) -> 78
B11: 43004 | C11: 42980 | D11: 43004 | E11: Vendas de mercadorias | F11: Móveis | G11: NF4333 | H11: 4268 | I11: =IF(TbRegistroEntradas[[#This Row],[Data do Caixa Realizado]]="",0,MONTH(TbRegistroEntradas[[#This Row],[Data do Caixa Realizado]])) -> 9 | J11: =IF(TbRegistroEntradas[[#This Row],[Data do Caixa Realizado]]="",0,YEAR(TbRegistroEntradas[[#This Row],[Data do Caixa Realizado]])) -> 2017 | K11: =IF(TbRegistroEntradas[[#This Row],[Data da Competência]]="",0,MONTH(TbRegistroEntradas[[#This Row],[Data da Competência]])) -> 9 | L11: =IF(TbRegistroEntradas[[#This Row],[Data da Competência]]="",0,YEAR(TbRegistroEntradas[[#This Row],[Data da Competência]])) -> 2017 | M11: =IF(TbRegistroEntradas[[#This Row],[Data do Caixa Previsto]]="",0,MONTH(TbRegistroEntradas[[#This Row],[Data do Caixa Previsto]])) -> 9 | N11: =IF(TbRegistroEntradas[[#This Row],[Data do Caixa Previsto]]="",0,YEAR(TbRegistroEntradas[[#This Row],[Data do Caixa Previsto]])) -> 2017 | O11: =IF(AND(TbRegistroEntradas[[#This Row],[Data do Caixa Previsto]]<TODAY(),TbRegistroEntradas[[#This Row],[Data do Caixa Realizado]]=""),"Vencida","Não Vencida") -> Não Vencida | P11: =IF(TbRegistroEntradas[[#This Row],[Data da Competência]]=TbRegistroEntradas[[#This Row],[Data do Caixa Previsto]],"Vista","Prazo") -> Prazo | Q11: =IF(TbRegistroEntradas[[#This Row],[Data do Caixa Realizado]]<>"", IF(TbRegistroEntradas[[#This Row],[Data do Caixa Realizado]]>TbRegistroEntradas[[#This Row],[Data do Caixa Previsto]], TbRegistroEntradas[[#This Row],[Data do Caixa Realizado]]-TbRegistroEntradas[[#This Row],[Data do Caixa Previsto]], 0 ), IF(TODAY()>TbRegistroEntradas[[#This Row],[Data do Caixa Previsto]], TODAY()-TbRegistroEntradas[[#This Row],[Data do Caixa Previsto]], 0 ) ) -> 0
B12: 43015 | C12: 42984 | D12: 43015 | E12: Vendas de mercadorias | F12: Móveis | G12: NF8091 | H12: 3761 | I12: =IF(TbRegistroEntradas[[#This Row],[Data do Caixa Realizado]]="",0,MONTH(TbRegistroEntradas[[#This Row],[Data do Caixa Realizado]])) -> 10 | J12: =IF(TbRegistroEntradas[[#This Row],[Data do Caixa Realizado]]="",0,YEAR(TbRegistroEntradas[[#This Row],[Data do Caixa Realizado]])) -> 2017 | K12: =IF(TbRegistroEntradas[[#This Row],[Data da Competência]]="",0,MONTH(TbRegistroEntradas[[#This Row],[Data da Competência]])) -> 9 | L12: =IF(TbRegistroEntradas[[#This Row],[Data da Competência]]="",0,YEAR(TbRegistroEntradas[[#This Row],[Data da Competência]])) -> 2017 | M12: =IF(TbRegistroEntradas[[#This Row],[Data do Caixa Previsto]]="",0,MONTH(TbRegistroEntradas[[#This Row],[Data do Caixa Previsto]])) -> 10 | N12: =IF(TbRegistroEntradas[[#This Row],[Data do Caixa Previsto]]="",0,YEAR(TbRegistroEntradas[[#This Row],[Data do Caixa Previsto]])) -> 2017 | O12: =IF(AND(TbRegistroEntradas[[#This Row],[Data do Caixa Previsto]]<TODAY(),TbRegistroEntradas[[#This Row],[Data do Caixa Realizado]]=""),"Vencida","Não Vencida") -> Não Vencida | P12: =IF(TbRegistroEntradas[[#This Row],[Data da Competência]]=TbRegistroEntradas[[#This Row],[Data do Caixa Previsto]],"Vista","Prazo") -> Prazo | Q12: =IF(TbRegistroEntradas[[#This Row],[Data do Caixa Realizado]]<>"", IF(TbRegistroEntradas[[#This Row],[Data do Caixa Realizado]]>TbRegistroEntradas[[#This Row],[Data do Caixa Previsto]], TbRegistroEntradas[[#This Row],[Data do Caixa Realizado]]-TbRegistroEntradas[[#This Row],[Data do Caixa Previsto]], 0 ), IF(TODAY()>TbRegistroEntradas[[#This Row],[Data do Caixa Previsto]], TODAY()-TbRegistroEntradas[[#This Row],[Data do Caixa Previsto]], 0 ) ) -> 0
C13: 42988 | D13: 43013 | E13: Vendas de mercadorias | F13: Móveis | G13: NF2421 | H13: 4983 | I13: =IF(TbRegistroEntradas[[#This Row],[Data do Caixa Realizado]]="",0,MONTH(TbRegistroEntradas[[#This Row],[Data do Caixa Realizado]])) -> 0 | J13: =IF(TbRegistroEntradas[[#This Row],[Data do Caixa Realizado]]="",0,YEAR(TbRegistroEntradas[[#This Row],[Data do Caixa Realizado]])) -> 0 | K13: =IF(TbRegistroEntradas[[#This Row],[Data da Competência]]="",0,MONTH(TbRegistroEntradas[[#This Row],[Data da Competência]])) -> 9 | L13: =IF(TbRegistroEntradas[[#This Row],[Data da Competência]]="",0,YEAR(TbRegistroEntradas[[#This Row],[Data da Competência]])) -> 2017 | M13: =IF(TbRegistroEntradas[[#This Row],[Data do Caixa Previsto]]="",0,MONTH(TbRegistroEntradas[[#This Row],[Data do Caixa Previsto]])) -> 10 | N13: =IF(TbRegistroEntradas[[#This Row],[Data do Caixa Previsto]]="",0,YEAR(TbRegistroEntradas[[#This Row],[Data do Caixa Previsto]])) -> 2017 | O13: =IF(AND(TbRegistroEntradas[[#This Row],[Data do Caixa Previsto]]<TODAY(),TbRegistroEntradas[[#This Row],[Data do Caixa Realizado]]=""),"Vencida","Não Vencida") -> Vencida | P13: =IF(TbRegistroEntradas[[#This Row],[Data da Competência]]=TbRegistroEntradas[[#This Row],[Data do Caixa Previsto]],"Vista","Prazo") -> Prazo | Q13: =IF(TbRegistroEntradas[[#This Row],[Data do Caixa Realizado]]<>"", IF(TbRegistroEntradas[[#This Row],[Data do Caixa Realizado]]>TbRegistroEntradas[[#This Row],[Data do Caixa Previsto]], TbRegistroEntradas[[#This Row],[Data do Caixa Realizado]]-TbRegistroEntradas[[#This Row],[Data do Caixa Previsto]], 0 ), IF(TODAY()>TbRegistroEntradas[[#This Row],[Data do Caixa Previsto]], TODAY()-TbRegistroEntradas[[#This Row],[Data do Caixa Previsto]], 0 ) ) -> 2340
B14: 42997 | C14: 42990 | D14: 42997 | E14: Vendas de mercadorias | F14: Eletrodomésticos | G14: NF9787 | H14: 2502 | I14: =IF(TbRegistroEntradas[[#This Row],[Data do Caixa Realizado]]="",0,MONTH(TbRegistroEntradas[[#This Row],[Data do Caixa Realizado]])) -> 9 | J14: =IF(TbRegistroEntradas[[#This Row],[Data do Caixa Realizado]]="",0,YEAR(TbRegistroEntradas[[#This Row],[Data do Caixa Realizado]])) -> 2017 | K14: =IF(TbRegistroEntradas[[#This Row],[Data da Competência]]="",0,MONTH(TbRegistroEntradas[[#This Row],[Data da Competência]])) -> 9 | L14: =IF(TbRegistroEntradas[[#This Row],[Data da Competência]]="",0,YEAR(TbRegistroEntradas[[#This Row],[Data da Competência]])) -> 2017 | M14: =IF(TbRegistroEntradas[[#This Row],[Data do Caixa Previsto]]="",0,MONTH(TbRegistroEntradas[[#This Row],[Data do Caixa Previsto]])) -> 9 | N14: =IF(TbRegistroEntradas[[#This Row],[Data do Caixa Previsto]]="",0,YEAR(TbRegistroEntradas[[#This Row],[Data do Caixa Previsto]])) -> 2017 | O14: =IF(AND(TbRegistroEntradas[[#This Row],[Data do Caixa Previsto]]<TODAY(),TbRegistroEntradas[[#This Row],[Data do Caixa Realizado]]=""),"Vencida","Não Vencida") -> Não Vencida | P14: =IF(TbRegistroEntradas[[#This Row],[Data da Competência]]=TbRegistroEntradas[[#This Row],[Data do Caixa Previsto]],"Vista","Prazo") -> Prazo | Q14: =IF(TbRegistroEntradas[[#This Row],[Data do Caixa Realizado]]<>"", IF(TbRegistroEntradas[[#This Row],[Data do Caixa Realizado]]>TbRegistroEntradas[[#This Row],[Data do Caixa Previsto]], TbRegistroEntradas[[#This Row],[Data do Caixa Realizado]]-TbRegistroEntradas[[#This Row],[Data do Caixa Previsto]], 0 ), IF(TODAY()>TbRegistroEntradas[[#This Row],[Data do Caixa Previsto]], TODAY()-TbRegistroEntradas[[#This Row],[Data do Caixa Previsto]], 0 ) ) -> 0
B15: 43002 | C15: 42994 | D15: 43002 | E15: Vendas de mercadorias | F15: Móveis | G15: NF8674 | H15: 2337 | I15: =IF(TbRegistroEntradas[[#This Row],[Data do Caixa Realizado]]="",0,MONTH(TbRegistroEntradas[[#This Row],[Data do Caixa Realizado]])) -> 9 | J15: =IF(TbRegistroEntradas[[#This Row],[Data do Caixa Realizado]]="",0,YEAR(TbRegistroEntradas[[#This Row],[Data do Caixa Realizado]])) -> 2017 | K15: =IF(TbRegistroEntradas[[#This Row],[Data da Competência]]="",0,MONTH(TbRegistroEntradas[[#This Row],[Data da Competência]])) -> 9 | L15: =IF(TbRegistroEntradas[[#This Row],[Data da Competência]]="",0,YEAR(TbRegistroEntradas[[#This Row],[Data da Competência]])) -> 2017 | M15: =IF(TbRegistroEntradas[[#This Row],[Data do Caixa Previsto]]="",0,MONTH(TbRegistroEntradas[[#This Row],[Data do Caixa Previsto]])) -> 9 | N15: =IF(TbRegistroEntradas[[#This Row],[Data do Caixa Previsto]]="",0,YEAR(TbRegistroEntradas[[#This Row],[Data do Caixa Previsto]])) -> 2017 | O15: =IF(AND(TbRegistroEntradas[[#This Row],[Data do Caixa Previsto]]<TODAY(),TbRegistroEntradas[[#This Row],[Data do Caixa Realizado]]=""),"Vencida","Não Vencida") -> Não Vencida | P15: =IF(TbRegistroEntradas[[#This Row],[Data da Competência]]=TbRegistroEntradas[[#This Row],[Data do Caixa Previsto]],"Vista","Prazo") -> Prazo | Q15: =IF(TbRegistroEntradas[[#This Row],[Data do Caixa Realizado]]<>"", IF(TbRegistroEntradas[[#This Row],[Data do Caixa Realizado]]>TbRegistroEntradas[[#This Row],[Data do Caixa Previsto]], TbRegistroEntradas[[#This Row],[Data do Caixa Realizado]]-TbRegistroEntradas[[#This Row],[Data do Caixa Previsto]], 0 ), IF(TODAY()>TbRegistroEntradas[[#This Row],[Data do Caixa Previsto]], TODAY()-TbRegistroEntradas[[#This Row],[Data do Caixa Previsto]], 0 ) ) -> 0
B16: 43001 | C16: 43001 | D16: 43001 | E16: Vendas de mercadorias | F16: Livros | G16: NF5880 | H16: 3125 | I16: =IF(TbRegistroEntradas[[#This Row],[Data do Caixa Realizado]]="",0,MONTH(TbRegistroEntradas[[#This Row],[Data do Caixa Realizado]])) -> 9 | J16: =IF(TbRegistroEntradas[[#This Row],[Data do Caixa Realizado]]="",0,YEAR(TbRegistroEntradas[[#This Row],[Data do Caixa Realizado]])) -> 2017 | K16: =IF(TbRegistroEntradas[[#This Row],[Data da Competência]]="",0,MONTH(TbRegistroEntradas[[#This Row],[Data da Competência]])) -> 9 | L16: =IF(TbRegistroEntradas[[#This Row],[Data da Competência]]="",0,YEAR(TbRegistroEntradas[[#This Row],[Data da Competência]])) -> 2017 | M16: =IF(TbRegistroEntradas[[#This Row],[Data do Caixa Previsto]]="",0,MONTH(TbRegistroEntradas[[#This Row],[Data do Caixa Previsto]])) -> 9 | N16: =IF(TbRegistroEntradas[[#This Row],[Data do Caixa Previsto]]="",0,YEAR(TbRegistroEntradas[[#This Row],[Data do Caixa Previsto]])) -> 2017 | O16: =IF(AND(TbRegistroEntradas[[#This Row],[Data do Caixa Previsto]]<TODAY(),TbRegistroEntradas[[#This Row],[Data do Caixa Realizado]]=""),"Vencida","Não Vencida") -> Não Vencida | P16: =IF(TbRegistroEntradas[[#This Row],[Data da Competência]]=TbRegistroEntradas[[#This Row],[Data do Caixa Previsto]],"Vista","Prazo") -> Vista | Q16: =IF(TbRegistroEntradas[[#This Row],[Data do Caixa Realizado]]<>"", IF(TbRegistroEntradas[[#This Row],[Data do Caixa Realizado]]>TbRegistroEntradas[[#This Row],[Data do Caixa Previsto]], TbRegistroEntradas[[#This Row],[Data do Caixa Realizado]]-TbRegistroEntradas[[#This Row],[Data do Caixa Previsto]], 0 ), IF(TODAY()>TbRegistroEntradas[[#This Row],[Data do Caixa Previsto]], TODAY()-TbRegistroEntradas[[#This Row],[Data do Caixa Previsto]], 0 ) ) -> 0
B17: 43056 | C17: 43004 | D17: 43056 | E17: Vendas de mercadorias | F17: Móveis | G17: NF2763 | H17: 1201 | I17: =IF(TbRegistroEntradas[[#This Row],[Data do Caixa Realizado]]="",0,MONTH(TbRegistroEntradas[[#This Row],[Data do Caixa Realizado]])) -> 11 | J17: =IF(TbRegistroEntradas[[#This Row],[Data do Caixa Realizado]]="",0,YEAR(TbRegistroEntradas[[#This Row],[Data do Caixa Realizado]])) -> 2017 | K17: =IF(TbRegistroEntradas[[#This Row],[Data da Competência]]="",0,MONTH(TbRegistroEntradas[[#This Row],[Data da Competência]])) -> 9 | L17: =IF(TbRegistroEntradas[[#This Row],[Data da Competência]]="",0,YEAR(TbRegistroEntradas[[#This Row],[Data da Competência]])) -> 2017 | M17: =IF(TbRegistroEntradas[[#This Row],[Data do Caixa Previsto]]="",0,MONTH(TbRegistroEntradas[[#This Row],[Data do Caixa Previsto]])) -> 11 | N17: =IF(TbRegistroEntradas[[#This Row],[Data do Caixa Previsto]]="",0,YEAR(TbRegistroEntradas[[#This Row],[Data do Caixa Previsto]])) -> 2017 | O17: =IF(AND(TbRegistroEntradas[[#This Row],[Data do Caixa Previsto]]<TODAY(),TbRegistroEntradas[[#This Row],[Data do Caixa Realizado]]=""),"Vencida","Não Vencida") -> Não Vencida | P17: =IF(TbRegistroEntradas[[#This Row],[Data da Competência]]=TbRegistroEntradas[[#This Row],[Data do Caixa Previsto]],"Vista","Prazo") -> Prazo | Q17: =IF(TbRegistroEntradas[[#This Row],[Data do Caixa Realizado]]<>"", IF(TbRegistroEntradas[[#This Row],[Data do Caixa Realizado]]>TbRegistroEntradas[[#This Row],[Data do Caixa Previsto]], TbRegistroEntradas[[#This Row],[Data do Caixa Realizado]]-TbRegistroEntradas[[#This Row],[Data do Caixa Previsto]], 0 ), IF(TODAY()>TbRegistroEntradas[[#This Row],[Data do Caixa Previsto]], TODAY()-TbRegistroEntradas[[#This Row],[Data do Caixa Previsto]], 0 ) ) -> 0
B18: 43018 | C18: 43005 | D18: 43018 | E18: Vendas de mercadorias | F18: Informática | G18: NF3303 | H18: 4380 | I18: =IF(TbRegistroEntradas[[#This Row],[Data do Caixa Realizado]]="",0,MONTH(TbRegistroEntradas[[#This Row],[Data do Caixa Realizado]])) -> 10 | J18: =IF(TbRegistroEntradas[[#This Row],[Data do Caixa Realizado]]="",0,YEAR(TbRegistroEntradas[[#This Row],[Data do Caixa Realizado]])) -> 2017 | K18: =IF(TbRegistroEntradas[[#This Row],[Data da Competência]]="",0,MONTH(TbRegistroEntradas[[#This Row],[Data da Competência]])) -> 9 | L18: =IF(TbRegistroEntradas[[#This Row],[Data da Competência]]="",0,YEAR(TbRegistroEntradas[[#This Row],[Data da Competência]])) -> 2017 | M18: =IF(TbRegistroEntradas[[#This Row],[Data do Caixa Previsto]]="",0,MONTH(TbRegistroEntradas[[#This Row],[Data do Caixa Previsto]])) -> 10 | N18: =IF(TbRegistroEntradas[[#This Row],[Data do Caixa Previsto]]="",0,YEAR(TbRegistroEntradas[[#This Row],[Data do Caixa Previsto]])) -> 2017 | O18: =IF(AND(TbRegistroEntradas[[#This Row],[Data do Caixa Previsto]]<TODAY(),TbRegistroEntradas[[#This Row],[Data do Caixa Realizado]]=""),"Vencida","Não Vencida") -> Não Vencida | P18: =IF(TbRegistroEntradas[[#This Row],[Data da Competência]]=TbRegistroEntradas[[#This Row],[Data do Caixa Previsto]],"Vista","Prazo") -> Prazo | Q18: =IF(TbRegistroEntradas[[#This Row],[Data do Caixa Realizado]]<>"", IF(TbRegistroEntradas[[#This Row],[Data do Caixa Realizado]]>TbRegistroEntradas[[#This Row],[Data do Caixa Previsto]], TbRegistroEntradas[[#This Row],[Data do Caixa Realizado]]-TbRegistroEntradas[[#This Row],[Data do Caixa Previsto]], 0 ), IF(TODAY()>TbRegistroEntradas[[#This Row],[Data do Caixa Previsto]], TODAY()-TbRegistroEntradas[[#This Row],[Data do Caixa Previsto]], 0 ) ) -> 0
B19: 43019 | C19: 43008 | D19: 43019 | E19: Vendas de mercadorias | F19: Livros | G19: NF3966 | H19: 919 | I19: =IF(TbRegistroEntradas[[#This Row],[Data do Caixa Realizado]]="",0,MONTH(TbRegistroEntradas[[#This Row],[Data do Caixa Realizado]])) -> 10 | J19: =IF(TbRegistroEntradas[[#This Row],[Data do Caixa Realizado]]="",0,YEAR(TbRegistroEntradas[[#This Row],[Data do Caixa Realizado]])) -> 2017 | K19: =IF(TbRegistroEntradas[[#This Row],[Data da Competência]]="",0,MONTH(TbRegistroEntradas[[#This Row],[Data da Competência]])) -> 9 | L19: =IF(TbRegistroEntradas[[#This Row],[Data da Competência]]="",0,YEAR(TbRegistroEntradas[[#This Row],[Data da Competência]])) -> 2017 | M19: =IF(TbRegistroEntradas[[#This Row],[Data do Caixa Previsto]]="",0,MONTH(TbRegistroEntradas[[#This Row],[Data do Caixa Previsto]])) -> 10 | N19: =IF(TbRegistroEntradas[[#This Row],[Data do Caixa Previsto]]="",0,YEAR(TbRegistroEntradas[[#This Row],[Data do Caixa Previsto]])) -> 2017 | O19: =IF(AND(TbRegistroEntradas[[#This Row],[Data do Caixa Previsto]]<TODAY(),TbRegistroEntradas[[#This Row],[Data do Caixa Realizado]]=""),"Vencida","Não Vencida") -> Não Vencida | P19: =IF(TbRegistroEntradas[[#This Row],[Data da Competência]]=TbRegistroEntradas[[#This Row],[Data do Caixa Previsto]],"Vista","Prazo") -> Prazo | Q19: =IF(TbRegistroEntradas[[#This Row],[Data do Caixa Realizado]]<>"", IF(TbRegistroEntradas[[#This Row],[Data do Caixa Realizado]]>TbRegistroEntradas[[#This Row],[Data do Caixa Previsto]], TbRegistroEntradas[[#This Row],[Data do Caixa Realizado]]-TbRegistroEntradas[[#This Row],[Data do Caixa Previsto]], 0 ), IF(TODAY()>TbRegistroEntradas[[#This Row],[Data do Caixa Previsto]], TODAY()-TbRegistroEntradas[[#This Row],[Data do Caixa Previsto]], 0 ) ) -> 0
B20: 43076 | C20: 43012 | D20: 43025 | E20: Vendas de mercadorias | F20: Som e imagem | G20: NF6107 | H20: 4590 | I20: =IF(TbRegistroEntradas[[#This Row],[Data do Caixa Realizado]]="",0,MONTH(TbRegistroEntradas[[#This Row],[Data do Caixa Realizado]])) -> 12 | J20: =IF(TbRegistroEntradas[[#This Row],[Data do Caixa Realizado]]="",0,YEAR(TbRegistroEntradas[[#This Row],[Data do Caixa Realizado]])) -> 2017 | K20: =IF(TbRegistroEntradas[[#This Row],[Data da Competência]]="",0,MONTH(TbRegistroEntradas[[#This Row],[Data da Competência]])) -> 10 | L20: =IF(TbRegistroEntradas[[#This Row],[Data da Competência]]="",0,YEAR(TbRegistroEntradas[[#This Row],[Data da Competência]])) -> 2017 | M20: =IF(TbRegistroEntradas[[#This Row],[Data do Caixa Previsto]]="",0,MONTH(TbRegistroEntradas[[#This Row],[Data do Caixa Previsto]])) -> 10 | N20: =IF(TbRegistroEntradas[[#This Row],[Data do Caixa Previsto]]="",0,YEAR(TbRegistroEntradas[[#This Row],[Data do Caixa Previsto]])) -> 2017 | O20: =IF(AND(TbRegistroEntradas[[#This Row],[Data do Caixa Previsto]]<TODAY(),TbRegistroEntradas[[#This Row],[Data do Caixa Realizado]]=""),"Vencida","Não Vencida") -> Não Vencida | P20: =IF(TbRegistroEntradas[[#This Row],[Data da Competência]]=TbRegistroEntradas[[#This Row],[Data do Caixa Previsto]],"Vista","Prazo") -> Prazo | Q20: =IF(TbRegistroEntradas[[#This Row],[Data do Caixa Realizado]]<>"", IF(TbRegistroEntradas[[#This Row],[Data do Caixa Realizado]]>TbRegistroEntradas[[#This Row],[Data do Caixa Previsto]], TbRegistroEntradas[[#This Row],[Data do Caixa Realizado]]-TbRegistroEntradas[[#This Row],[Data do Caixa Previsto]], 0 ), IF(TODAY()>TbRegistroEntradas[[#This Row],[Data do Caixa Previsto]], TODAY()-TbRegistroEntradas[[#This Row],[Data do Caixa Previsto]], 0 ) ) -> 51
B21: 43052 | C21: 43015 | D21: 43052 | E21: Vendas de mercadorias | F21: Eletrodomésticos | G21: NF4832 | H21: 1958 | I21: =IF(TbRegistroEntradas[[#This Row],[Data do Caixa Realizado]]="",0,MONTH(TbRegistroEntradas[[#This Row],[Data do Caixa Realizado]])) -> 11 | J21: =IF(TbRegistroEntradas[[#This Row],[Data do Caixa Realizado]]="",0,YEAR(TbRegistroEntradas[[#This Row],[Data do Caixa Realizado]])) -> 2017 | K21: =IF(TbRegistroEntradas[[#This Row],[Data da Competência]]="",0,MONTH(TbRegistroEntradas[[#This Row],[Data da Competência]])) -> 10 | L21: =IF(TbRegistroEntradas[[#This Row],[Data da Competência]]="",0,YEAR(TbRegistroEntradas[[#This Row],[Data da Competência]])) -> 2017 | M21: =IF(TbRegistroEntradas[[#This Row],[Data do Caixa Previsto]]="",0,MONTH(TbRegistroEntradas[[#This Row],[Data do Caixa Previsto]])) -> 11 | N21: =IF(TbRegistroEntradas[[#This Row],[Data do Caixa Previsto]]="",0,YEAR(TbRegistroEntradas[[#This Row],[Data do Caixa Previsto]])) -> 2017 | O21: =IF(AND(TbRegistroEntradas[[#This Row],[Data do Caixa Previsto]]<TODAY(),TbRegistroEntradas[[#This Row],[Data do Caixa Realizado]]=""),"Vencida","Não Vencida") -> Não Vencida | P21: =IF(TbRegistroEntradas[[#This Row],[Data da Competência]]=TbRegistroEntradas[[#This Row],[Data do Caixa Previsto]],"Vista","Prazo") -> Prazo | Q21: =IF(TbRegistroEntradas[[#This Row],[Data do Caixa Realizado]]<>"", IF(TbRegistroEntradas[[#This Row],[Data do Caixa Realizado]]>TbRegistroEntradas[[#This Row],[Data do Caixa Previsto]], TbRegistroEntradas[[#This Row],[Data do Caixa Realizado]]-TbRegistroEntradas[[#This Row],[Data do Caixa Previsto]], 0 ), IF(TODAY()>TbRegistroEntradas[[#This Row],[Data do Caixa Previsto]], TODAY()-TbRegistroEntradas[[#This Row],[Data do Caixa Previsto]], 0 ) ) -> 0
B22: 43043 | C22: 43017 | D22: 43043 | E22: Vendas de mercadorias | F22: Informática | G22: NF5012 | H22: 1171 | I22: =IF(TbRegistroEntradas[[#This Row],[Data do Caixa Realizado]]="",0,MONTH(TbRegistroEntradas[[#This Row],[Data do Caixa Realizado]])) -> 11 | J22: =IF(TbRegistroEntradas[[#This Row],[Data do Caixa Realizado]]="",0,YEAR(TbRegistroEntradas[[#This Row],[Data do Caixa Realizado]])) -> 2017 | K22: =IF(TbRegistroEntradas[[#This Row],[Data da Competência]]="",0,MONTH(TbRegistroEntradas[[#This Row],[Data da Competência]])) -> 10 | L22: =IF(TbRegistroEntradas[[#This Row],[Data da Competência]]="",0,YEAR(TbRegistroEntradas[[#This Row],[Data da Competência]])) -> 2017 | M22: =IF(TbRegistroEntradas[[#This Row],[Data do Caixa Previsto]]="",0,MONTH(TbRegistroEntradas[[#This Row],[Data do Caixa Previsto]])) -> 11 | N22: =IF(TbRegistroEntradas[[#This Row],[Data do Caixa Previsto]]="",0,YEAR(TbRegistroEntradas[[#This Row],[Data do Caixa Previsto]])) -> 2017 | O22: =IF(AND(TbRegistroEntradas[[#This Row],[Data do Caixa Previsto]]<TODAY(),TbRegistroEntradas[[#This Row],[Data do Caixa Realizado]]=""),"Vencida","Não Vencida") -> Não Vencida | P22: =IF(TbRegistroEntradas[[#This Row],[Data da Competência]]=TbRegistroEntradas[[#This Row],[Data do Caixa Previsto]],"Vista","Prazo") -> Prazo | Q22: =IF(TbRegistroEntradas[[#This Row],[Data do Caixa Realizado]]<>"", IF(TbRegistroEntradas[[#This Row],[Data do Caixa Realizado]]>TbRegistroEntradas[[#This Row],[Data do Caixa Previsto]], TbRegistroEntradas[[#This Row],[Data do Caixa Realizado]]-TbRegistroEntradas[[#This Row],[Data do Caixa Previsto]], 0 ), IF(TODAY()>TbRegistroEntradas[[#This Row],[Data do Caixa Previsto]], TODAY()-TbRegistroEntradas[[#This Row],[Data do Caixa Previsto]], 0 ) ) -> 0
B23: 43060 | C23: 43019 | D23: 43060 | E23: Vendas de mercadorias | F23: Móveis | G23: NF7669 | H23: 2587 | I23: =IF(TbRegistroEntradas[[#This Row],[Data do Caixa Realizado]]="",0,MONTH(TbRegistroEntradas[[#This Row],[Data do Caixa Realizado]])) -> 11 | J23: =IF(TbRegistroEntradas[[#This Row],[Data do Caixa Realizado]]="",0,YEAR(TbRegistroEntradas[[#This Row],[Data do Caixa Realizado]])) -> 2017 | K23: =IF(TbRegistroEntradas[[#This Row],[Data da Competência]]="",0,MONTH(TbRegistroEntradas[[#This Row],[Data da Competência]])) -> 10 | L23: =IF(TbRegistroEntradas[[#This Row],[Data da Competência]]="",0,YEAR(TbRegistroEntradas[[#This Row],[Data da Competência]])) -> 2017 | M23: =IF(TbRegistroEntradas[[#This Row],[Data do Caixa Previsto]]="",0,MONTH(TbRegistroEntradas[[#This Row],[Data do Caixa Previsto]])) -> 11 | N23: =IF(TbRegistroEntradas[[#This Row],[Data do Caixa Previsto]]="",0,YEAR(TbRegistroEntradas[[#This Row],[Data do Caixa Previsto]])) -> 2017 | O23: =IF(AND(TbRegistroEntradas[[#This Row],[Data do Caixa Previsto]]<TODAY(),TbRegistroEntradas[[#This Row],[Data do Caixa Realizado]]=""),"Vencida","Não Vencida") -> Não Vencida | P23: =IF(TbRegistroEntradas[[#This Row],[Data da Competência]]=TbRegistroEntradas[[#This Row],[Data do Caixa Previsto]],"Vista","Prazo") -> Prazo | Q23: =IF(TbRegistroEntradas[[#This Row],[Data do Caixa Realizado]]<>"", IF(TbRegistroEntradas[[#This Row],[Data do Caixa Realizado]]>TbRegistroEntradas[[#This Row],[Data do Caixa Previsto]], TbRegistroEntradas[[#This Row],[Data do Caixa Realizado]]-TbRegistroEntradas[[#This Row],[Data do Caixa Previsto]], 0 ), IF(TODAY()>TbRegistroEntradas[[#This Row],[Data do Caixa Previsto]], TODAY()-TbRegistroEntradas[[#This Row],[Data do Caixa Previsto]], 0 ) ) -> 0
C24: 43023 | D24: 43045 | E24: Vendas de mercadorias | F24: Móveis | G24: NF7663 | H24: 3425 | I24: =IF(TbRegistroEntradas[[#This Row],[Data do Caixa Realizado]]="",0,MONTH(TbRegistroEntradas[[#This Row],[Data do Caixa Realizado]])) -> 0 | J24: =IF(TbRegistroEntradas[[#This Row],[Data do Caixa Realizado]]="",0,YEAR(TbRegistroEntradas[[#This Row],[Data do Caixa Realizado]])) -> 0 | K24: =IF(TbRegistroEntradas[[#This Row],[Data da Competência]]="",0,MONTH(TbRegistroEntradas[[#This Row],[Data da Competência]])) -> 10 | L24: =IF(TbRegistroEntradas[[#This Row],[Data da Competência]]="",0,YEAR(TbRegistroEntradas[[#This Row],[Data da Competência]])) -> 2017 | M24: =IF(TbRegistroEntradas[[#This Row],[Data do Caixa Previsto]]="",0,MONTH(TbRegistroEntradas[[#This Row],[Data do Caixa Previsto]])) -> 11 | N24: =IF(TbRegistroEntradas[[#This Row],[Data do Caixa Previsto]]="",0,YEAR(TbRegistroEntradas[[#This Row],[Data do Caixa Previsto]])) -> 2017 | O24: =IF(AND(TbRegistroEntradas[[#This Row],[Data do Caixa Previsto]]<TODAY(),TbRegistroEntradas[[#This Row],[Data do Caixa Realizado]]=""),"Vencida","Não Vencida") -> Vencida | P24: =IF(TbRegistroEntradas[[#This Row],[Data da Competência]]=TbRegistroEntradas[[#This Row],[Data do Caixa Previsto]],"Vista","Prazo") -> Prazo | Q24: =IF(TbRegistroEntradas[[#This Row],[Data do Caixa Realizado]]<>"", IF(TbRegistroEntradas[[#This Row],[Data do Caixa Realizado]]>TbRegistroEntradas[[#This Row],[Data do Caixa Previsto]], TbRegistroEntradas[[#This Row],[Data do Caixa Realizado]]-TbRegistroEntradas[[#This Row],[Data do Caixa Previsto]], 0 ), IF(TODAY()>TbRegistroEntradas[[#This Row],[Data do Caixa Previsto]], TODAY()-TbRegistroEntradas[[#This Row],[Data do Caixa Previsto]], 0 ) ) -> 2308
B25: 43113 | C25: 43026 | D25: 43026 | E25: Vendas de mercadorias | F25: Som e imagem | G25: NF4063 | H25: 4454 | I25: =IF(TbRegistroEntradas[[#This Row],[Data do Caixa Realizado]]="",0,MONTH(TbRegistroEntradas[[#This Row],[Data do Caixa Realizado]])) -> 1 | J25: =IF(TbRegistroEntradas[[#This Row],[Data do Caixa Realizado]]="",0,YEAR(TbRegistroEntradas[[#This Row],[Data do Caixa Realizado]])) -> 2018 | K25: =IF(TbRegistroEntradas[[#This Row],[Data da Competência]]="",0,MONTH(TbRegistroEntradas[[#This Row],[Data da Competência]])) -> 10 | L25: =IF(TbRegistroEntradas[[#This Row],[Data da Competência]]="",0,YEAR(TbRegistroEntradas[[#This Row],[Data da Competência]])) -> 2017 | M25: =IF(TbRegistroEntradas[[#This Row],[Data do Caixa Previsto]]="",0,MONTH(TbRegistroEntradas[[#This Row],[Data do Caixa Previsto]])) -> 10 | N25: =IF(TbRegistroEntradas[[#This Row],[Data do Caixa Previsto]]="",0,YEAR(TbRegistroEntradas[[#This Row],[Data do Caixa Previsto]])) -> 2017 | O25: =IF(AND(TbRegistroEntradas[[#This Row],[Data do Caixa Previsto]]<TODAY(),TbRegistroEntradas[[#This Row],[Data do Caixa Realizado]]=""),"Vencida","Não Vencida") -> Não Vencida | P25: =IF(TbRegistroEntradas[[#This Row],[Data da Competência]]=TbRegistroEntradas[[#This Row],[Data do Caixa Previsto]],"Vista","Prazo") -> Vista | Q25: =IF(TbRegistroEntradas[[#This Row],[Data do Caixa Realizado]]<>"", IF(TbRegistroEntradas[[#This Row],[Data do Caixa Realizado]]>TbRegistroEntradas[[#This Row],[Data do Caixa Previsto]], TbRegistroEntradas[[#This Row],[Data do Caixa Realizado]]-TbRegistroEntradas[[#This Row],[Data do Caixa Previsto]], 0 ), IF(TODAY()>TbRegistroEntradas[[#This Row],[Data do Caixa Previsto]], TODAY()-TbRegistroEntradas[[#This Row],[Data do Caixa Previsto]], 0 ) ) -> 87
B26: 43030 | C26: 43030 | D26: 43030 | E26: Vendas de mercadorias | F26: Informática | G26: NF4290 | H26: 2134 | I26: =IF(TbRegistroEntradas[[#This Row],[Data do Caixa Realizado]]="",0,MONTH(TbRegistroEntradas[[#This Row],[Data do Caixa Realizado]])) -> 10 | J26: =IF(TbRegistroEntradas[[#This Row],[Data do Caixa Realizado]]="",0,YEAR(TbRegistroEntradas[[#This Row],[Data do Caixa Realizado]])) -> 2017 | K26: =IF(TbRegistroEntradas[[#This Row],[Data da Competência]]="",0,MONTH(TbRegistroEntradas[[#This Row],[Data da Competência]])) -> 10 | L26: =IF(TbRegistroEntradas[[#This Row],[Data da Competência]]="",0,YEAR(TbRegistroEntradas[[#This Row],[Data da Competência]])) -> 2017 | M26: =IF(TbRegistroEntradas[[#This Row],[Data do Caixa Previsto]]="",0,MONTH(TbRegistroEntradas[[#This Row],[Data do Caixa Previsto]])) -> 10 | N26: =IF(TbRegistroEntradas[[#This Row],[Data do Caixa Previsto]]="",0,YEAR(TbRegistroEntradas[[#This Row],[Data do Caixa Previsto]])) -> 2017 | O26: =IF(AND(TbRegistroEntradas[[#This Row],[Data do Caixa Previsto]]<TODAY(),TbRegistroEntradas[[#This Row],[Data do Caixa Realizado]]=""),"Vencida","Não Vencida") -> Não Vencida | P26: =IF(TbRegistroEntradas[[#This Row],[Data da Competência]]=TbRegistroEntradas[[#This Row],[Data do Caixa Previsto]],"Vista","Prazo") -> Vista | Q26: =IF(TbRegistroEntradas[[#This Row],[Data do Caixa Realizado]]<>"", IF(TbRegistroEntradas[[#This Row],[Data do Caixa Realizado]]>TbRegistroEntradas[[#This Row],[Data do Caixa Previsto]], TbRegistroEntradas[[#This Row],[Data do Caixa Realizado]]-TbRegistroEntradas[[#This Row],[Data do Caixa Previsto]], 0 ), IF(TODAY()>TbRegistroEntradas[[#This Row],[Data do Caixa Previsto]], TODAY()-TbRegistroEntradas[[#This Row],[Data do Caixa Previsto]], 0 ) ) -> 0
B27: 43032 | C27: 43032 | D27: 43032 | E27: Vendas de mercadorias | F27: Eletrodomésticos | G27: NF7319 | H27: 257 | I27: =IF(TbRegistroEntradas[[#This Row],[Data do Caixa Realizado]]="",0,MONTH(TbRegistroEntradas[[#This Row],[Data do Caixa Realizado]])) -> 10 | J27: =IF(TbRegistroEntradas[[#This Row],[Data do Caixa Realizado]]="",0,YEAR(TbRegistroEntradas[[#This Row],[Data do Caixa Realizado]])) -> 2017 | K27: =IF(TbRegistroEntradas[[#This Row],[Data da Competência]]="",0,MONTH(TbRegistroEntradas[[#This Row],[Data da Competência]])) -> 10 | L27: =IF(TbRegistroEntradas[[#This Row],[Data da Competência]]="",0,YEAR(TbRegistroEntradas[[#This Row],[Data da Competência]])) -> 2017 | M27: =IF(TbRegistroEntradas[[#This Row],[Data do Caixa Previsto]]="",0,MONTH(TbRegistroEntradas[[#This Row],[Data do Caixa Previsto]])) -> 10 | N27: =IF(TbRegistroEntradas[[#This Row],[Data do Caixa Previsto]]="",0,YEAR(TbRegistroEntradas[[#This Row],[Data do Caixa Previsto]])) -> 2017 | O27: =IF(AND(TbRegistroEntradas[[#This Row],[Data do Caixa Previsto]]<TODAY(),TbRegistroEntradas[[#This Row],[Data do Caixa Realizado]]=""),"Vencida","Não Vencida") -> Não Vencida | P27: =IF(TbRegistroEntradas[[#This Row],[Data da Competência]]=TbRegistroEntradas[[#This Row],[Data do Caixa Previsto]],"Vista","Prazo") -> Vista | Q27: =IF(TbRegistroEntradas[[#This Row],[Data do Caixa Realizado]]<>"", IF(TbRegistroEntradas[[#This Row],[Data do Caixa Realizado]]>TbRegistroEntradas[[#This Row],[Data do Caixa Previsto]], TbRegistroEntradas[[#This Row],[Data do Caixa Realizado]]-TbRegistroEntradas[[#This Row],[Data do Caixa Previsto]], 0 ), IF(TODAY()>TbRegistroEntradas[[#This Row],[Data do Caixa Previsto]], TODAY()-TbRegistroEntradas[[#This Row],[Data do Caixa Previsto]], 0 ) ) -> 0
B28: 43122 | C28: 43032 | D28: 43068 | E28: Vendas de mercadorias | F28: Livros | G28: NF7020 | H28: 2019 | I28: =IF(TbRegistroEntradas[[#This Row],[Data do Caixa Realizado]]="",0,MONTH(TbRegistroEntradas[[#This Row],[Data do Caixa Realizado]])) -> 1 | J28: =IF(TbRegistroEntradas[[#This Row],[Data do Caixa Realizado]]="",0,YEAR(TbRegistroEntradas[[#This Row],[Data do Caixa Realizado]])) -> 2018 | K28: =IF(TbRegistroEntradas[[#This Row],[Data da Competência]]="",0,MONTH(TbRegistroEntradas[[#This Row],[Data da Competência]])) -> 10 | L28: =IF(TbRegistroEntradas[[#This Row],[Data da Competência]]="",0,YEAR(TbRegistroEntradas[[#This Row],[Data da Competência]])) -> 2017 | M28: =IF(TbRegistroEntradas[[#This Row],[Data do Caixa Previsto]]="",0,MONTH(TbRegistroEntradas[[#This Row],[Data do Caixa Previsto]])) -> 11 | N28: =IF(TbRegistroEntradas[[#This Row],[Data do Caixa Previsto]]="",0,YEAR(TbRegistroEntradas[[#This Row],[Data do Caixa Previsto]])) -> 2017 | O28: =IF(AND(TbRegistroEntradas[[#This Row],[Data do Caixa Previsto]]<TODAY(),TbRegistroEntradas[[#This Row],[Data do Caixa Realizado]]=""),"Vencida","Não Vencida") -> Não Vencida | P28: =IF(TbRegistroEntradas[[#This Row],[Data da Competência]]=TbRegistroEntradas[[#This Row],[Data do Caixa Previsto]],"Vista","Prazo") -> Prazo | Q28: =IF(TbRegistroEntradas[[#This Row],[Data do Caixa Realizado]]<>"", IF(TbRegistroEntradas[[#This Row],[Data do Caixa Realizado]]>TbRegistroEntradas[[#This Row],[Data do Caixa Previsto]], TbRegistroEntradas[[#This Row],[Data do Caixa Realizado]]-TbRegistroEntradas[[#This Row],[Data do Caixa Previsto]], 0 ), IF(TODAY()>TbRegistroEntradas[[#This Row],[Data do Caixa Previsto]], TODAY()-TbRegistroEntradas[[#This Row],[Data do Caixa Previsto]], 0 ) ) -> 54
B29: 43034 | C29: 43034 | D29: 43034 | E29: Vendas de mercadorias | F29: Móveis | G29: NF7221 | H29: 3696 | I29: =IF(TbRegistroEntradas[[#This Row],[Data do Caixa Realizado]]="",0,MONTH(TbRegistroEntradas[[#This Row],[Data do Caixa Realizado]])) -> 10 | J29: =IF(TbRegistroEntradas[[#This Row],[Data do Caixa Realizado]]="",0,YEAR(TbRegistroEntradas[[#This Row],[Data do Caixa Realizado]])) -> 2017 | K29: =IF(TbRegistroEntradas[[#This Row],[Data da Competência]]="",0,MONTH(TbRegistroEntradas[[#This Row],[Data da Competência]])) -> 10 | L29: =IF(TbRegistroEntradas[[#This Row],[Data da Competência]]="",0,YEAR(TbRegistroEntradas[[#This Row],[Data da Competência]])) -> 2017 | M29: =IF(TbRegistroEntradas[[#This Row],[Data do Caixa Previsto]]="",0,MONTH(TbRegistroEntradas[[#This Row],[Data do Caixa Previsto]])) -> 10 | N29: =IF(TbRegistroEntradas[[#This Row],[Data do Caixa Previsto]]="",0,YEAR(TbRegistroEntradas[[#This Row],[Data do Caixa Previsto]])) -> 2017 | O29: =IF(AND(TbRegistroEntradas[[#This Row],[Data do Caixa Previsto]]<TODAY(),TbRegistroEntradas[[#This Row],[Data do Caixa Realizado]]=""),"Vencida","Não Vencida") -> Não Vencida | P29: =IF(TbRegistroEntradas[[#This Row],[Data da Competência]]=TbRegistroEntradas[[#This Row],[Data do Caixa Previsto]],"Vista","Prazo") -> Vista | Q29: =IF(TbRegistroEntradas[[#This Row],[Data do Caixa Realizado]]<>"", IF(TbRegistroEntradas[[#This Row],[Data do Caixa Realizado]]>TbRegistroEntradas[[#This Row],[Data do Caixa Previsto]], TbRegistroEntradas[[#This Row],[Data do Caixa Realizado]]-TbRegistroEntradas[[#This Row],[Data do Caixa Previsto]], 0 ), IF(TODAY()>TbRegistroEntradas[[#This Row],[Data do Caixa Previsto]], TODAY()-TbRegistroEntradas[[#This Row],[Data do Caixa Previsto]], 0 ) ) -> 0
B30: 43052 | C30: 43038 | D30: 43052 | E30: Vendas de mercadorias | F30: Livros | G30: NF5004 | H30: 4446 | I30: =IF(TbRegistroEntradas[[#This Row],[Data do Caixa Realizado]]="",0,MONTH(TbRegistroEntradas[[#This Row],[Data do Caixa Realizado]])) -> 11 | J30: =IF(TbRegistroEntradas[[#This Row],[Data do Caixa Realizado]]="",0,YEAR(TbRegistroEntradas[[#This Row],[Data do Caixa Realizado]])) -> 2017 | K30: =IF(TbRegistroEntradas[[#This Row],[Data da Competência]]="",0,MONTH(TbRegistroEntradas[[#This Row],[Data da Competência]])) -> 10 | L30: =IF(TbRegistroEntradas[[#This Row],[Data da Competência]]="",0,YEAR(TbRegistroEntradas[[#This Row],[Data da Competência]])) -> 2017 | M30: =IF(TbRegistroEntradas[[#This Row],[Data do Caixa Previsto]]="",0,MONTH(TbRegistroEntradas[[#This Row],[Data do Caixa Previsto]])) -> 11 | N30: =IF(TbRegistroEntradas[[#This Row],[Data do Caixa Previsto]]="",0,YEAR(TbRegistroEntradas[[#This Row],[Data do Caixa Previsto]])) -> 2017 | O30: =IF(AND(TbRegistroEntradas[[#This Row],[Data do Caixa Previsto]]<TODAY(),TbRegistroEntradas[[#This Row],[Data do Caixa Realizado]]=""),"Vencida","Não Vencida") -> Não Vencida | P30: =IF(TbRegistroEntradas[[#This Row],[Data da Competência]]=TbRegistroEntradas[[#This Row],[Data do Caixa Previsto]],"Vista","Prazo") -> Prazo | Q30: =IF(TbRegistroEntradas[[#This Row],[Data do Caixa Realizado]]<>"", IF(TbRegistroEntradas[[#This Row],[Data do Caixa Realizado]]>TbRegistroEntradas[[#This Row],[Data do Caixa Previsto]], TbRegistroEntradas[[#This Row],[Data do Caixa Realizado]]-TbRegistroEntradas[[#This Row],[Data do Caixa Previsto]], 0 ), IF(TODAY()>TbRegistroEntradas[[#This Row],[Data do Caixa Previsto]], TODAY()-TbRegistroEntradas[[#This Row],[Data do Caixa Previsto]], 0 ) ) -> 0
C31: 43040 | D31: 43057 | E31: Vendas de mercadorias | F31: Livros | G31: NF8690 | H31: 1445 | I31: =IF(TbRegistroEntradas[[#This Row],[Data do Caixa Realizado]]="",0,MONTH(TbRegistroEntradas[[#This Row],[Data do Caixa Realizado]])) -> 0 | J31: =IF(TbRegistroEntradas[[#This Row],[Data do Caixa Realizado]]="",0,YEAR(TbRegistroEntradas[[#This Row],[Data do Caixa Realizado]])) -> 0 | K31: =IF(TbRegistroEntradas[[#This Row],[Data da Competência]]="",0,MONTH(TbRegistroEntradas[[#This Row],[Data da Competência]])) -> 11 | L31: =IF(TbRegistroEntradas[[#This Row],[Data da Competência]]="",0,YEAR(TbRegistroEntradas[[#This Row],[Data da Competência]])) -> 2017 | M31: =IF(TbRegistroEntradas[[#This Row],[Data do Caixa Previsto]]="",0,MONTH(TbRegistroEntradas[[#This Row],[Data do Caixa Previsto]])) -> 11 | N31: =IF(TbRegistroEntradas[[#This Row],[Data do Caixa Previsto]]="",0,YEAR(TbRegistroEntradas[[#This Row],[Data do Caixa Previsto]])) -> 2017 | O31: =IF(AND(TbRegistroEntradas[[#This Row],[Data do Caixa Previsto]]<TODAY(),TbRegistroEntradas[[#This Row],[Data do Caixa Realizado]]=""),"Vencida","Não Vencida") -> Vencida | P31: =IF(TbRegistroEntradas[[#This Row],[Data da Competência]]=TbRegistroEntradas[[#This Row],[Data do Caixa Previsto]],"Vista","Prazo") -> Prazo | Q31: =IF(TbRegistroEntradas[[#This Row],[Data do Caixa Realizado]]<>"", IF(TbRegistroEntradas[[#This Row],[Data do Caixa Realizado]]>TbRegistroEntradas[[#This Row],[Data do Caixa Previsto]], TbRegistroEntradas[[#This Row],[Data do Caixa Realizado]]-TbRegistroEntradas[[#This Row],[Data do Caixa Previsto]], 0 ), IF(TODAY()>TbRegistroEntradas[[#This Row],[Data do Caixa Previsto]], TODAY()-TbRegistroEntradas[[#This Row],[Data do Caixa Previsto]], 0 ) ) -> 2296
B32: 43117 | C32: 43043 | D32: 43068 | E32: Vendas de mercadorias | F32: Informática | G32: NF3424 | H32: 3559 | I32: =IF(TbRegistroEntradas[[#This Row],[Data do Caixa Realizado]]="",0,MONTH(TbRegistroEntradas[[#This Row],[Data do Caixa Realizado]])) -> 1 | J32: =IF(TbRegistroEntradas[[#This Row],[Data do Caixa Realizado]]="",0,YEAR(TbRegistroEntradas[[#This Row],[Data do Caixa Realizado]])) -> 2018 | K32: =IF(TbRegistroEntradas[[#This Row],[Data da Competência]]="",0,MONTH(TbRegistroEntradas[[#This Row],[Data da Competência]])) -> 11 | L32: =IF(TbRegistroEntradas[[#This Row],[Data da Competência]]="",0,YEAR(TbRegistroEntradas[[#This Row],[Data da Competência]])) -> 2017 | M32: =IF(TbRegistroEntradas[[#This Row],[Data do Caixa Previsto]]="",0,MONTH(TbRegistroEntradas[[#This Row],[Data do Caixa Previsto]])) -> 11 | N32: =IF(TbRegistroEntradas[[#This Row],[Data do Caixa Previsto]]="",0,YEAR(TbRegistroEntradas[[#This Row],[Data do Caixa Previsto]])) -> 2017 | O32: =IF(AND(TbRegistroEntradas[[#This Row],[Data do Caixa Previsto]]<TODAY(),TbRegistroEntradas[[#This Row],[Data do Caixa Realizado]]=""),"Vencida","Não Vencida") -> Não Vencida | P32: =IF(TbRegistroEntradas[[#This Row],[Data da Competência]]=TbRegistroEntradas[[#This Row],[Data do Caixa Previsto]],"Vista","Prazo") -> Prazo | Q32: =IF(TbRegistroEntradas[[#This Row],[Data do Caixa Realizado]]<>"", IF(TbRegistroEntradas[[#This Row],[Data do Caixa Realizado]]>TbRegistroEntradas[[#This Row],[Data do Caixa Previsto]], TbRegistroEntradas[[#This Row],[Data do Caixa Realizado]]-TbRegistroEntradas[[#This Row],[Data do Caixa Previsto]], 0 ), IF(TODAY()>TbRegistroEntradas[[#This Row],[Data do Caixa Previsto]], TODAY()-TbRegistroEntradas[[#This Row],[Data do Caixa Previsto]], 0 ) ) -> 49
B33: 43047 | C33: 43047 | D33: 43047 | E33: Vendas de mercadorias | F33: Móveis | G33: NF5808 | H33: 547 | I33: =IF(TbRegistroEntradas[[#This Row],[Data do Caixa Realizado]]="",0,MONTH(TbRegistroEntradas[[#This Row],[Data do Caixa Realizado]])) -> 11 | J33: =IF(TbRegistroEntradas[[#This Row],[Data do Caixa Realizado]]="",0,YEAR(TbRegistroEntradas[[#This Row],[Data do Caixa Realizado]])) -> 2017 | K33: =IF(TbRegistroEntradas[[#This Row],[Data da Competência]]="",0,MONTH(TbRegistroEntradas[[#This Row],[Data da Competência]])) -> 11 | L33: =IF(TbRegistroEntradas[[#This Row],[Data da Competência]]="",0,YEAR(TbRegistroEntradas[[#This Row],[Data da Competência]])) -> 2017 | M33: =IF(TbRegistroEntradas[[#This Row],[Data do Caixa Previsto]]="",0,MONTH(TbRegistroEntradas[[#This Row],[Data do Caixa Previsto]])) -> 11 | N33: =IF(TbRegistroEntradas[[#This Row],[Data do Caixa Previsto]]="",0,YEAR(TbRegistroEntradas[[#This Row],[Data do Caixa Previsto]])) -> 2017 | O33: =IF(AND(TbRegistroEntradas[[#This Row],[Data do Caixa Previsto]]<TODAY(),TbRegistroEntradas[[#This Row],[Data do Caixa Realizado]]=""),"Vencida","Não Vencida") -> Não Vencida | P33: =IF(TbRegistroEntradas[[#This Row],[Data da Competência]]=TbRegistroEntradas[[#This Row],[Data do Caixa Previsto]],"Vista","Prazo") -> Vista | Q33: =IF(TbRegistroEntradas[[#This Row],[Data do Caixa Realizado]]<>"", IF(TbRegistroEntradas[[#This Row],[Data do Caixa Realizado]]>TbRegistroEntradas[[#This Row],[Data do Caixa Previsto]], TbRegistroEntradas[[#This Row],[Data do Caixa Realizado]]-TbRegistroEntradas[[#This Row],[Data do Caixa Previsto]], 0 ), IF(TODAY()>TbRegistroEntradas[[#This Row],[Data do Caixa Previsto]], TODAY()-TbRegistroEntradas[[#This Row],[Data do Caixa Previsto]], 0 ) ) -> 0
B34: 43077 | C34: 43051 | D34: 43051 | E34: Vendas de mercadorias | F34: Móveis | G34: NF2852 | H34: 1221 | I34: =IF(TbRegistroEntradas[[#This Row],[Data do Caixa Realizado]]="",0,MONTH(TbRegistroEntradas[[#This Row],[Data do Caixa Realizado]])) -> 12 | J34: =IF(TbRegistroEntradas[[#This Row],[Data do Caixa Realizado]]="",0,YEAR(TbRegistroEntradas[[#This Row],[Data do Caixa Realizado]])) -> 2017 | K34: =IF(TbRegistroEntradas[[#This Row],[Data da Competência]]="",0,MONTH(TbRegistroEntradas[[#This Row],[Data da Competência]])) -> 11 | L34: =IF(TbRegistroEntradas[[#This Row],[Data da Competência]]="",0,YEAR(TbRegistroEntradas[[#This Row],[Data da Competência]])) -> 2017 | M34: =IF(TbRegistroEntradas[[#This Row],[Data do Caixa Previsto]]="",0,MONTH(TbRegistroEntradas[[#This Row],[Data do Caixa Previsto]])) -> 11 | N34: =IF(TbRegistroEntradas[[#This Row],[Data do Caixa Previsto]]="",0,YEAR(TbRegistroEntradas[[#This Row],[Data do Caixa Previsto]])) -> 2017 | O34: =IF(AND(TbRegistroEntradas[[#This Row],[Data do Caixa Previsto]]<TODAY(),TbRegistroEntradas[[#This Row],[Data do Caixa Realizado]]=""),"Vencida","Não Vencida") -> Não Vencida | P34: =IF(TbRegistroEntradas[[#This Row],[Data da Competência]]=TbRegistroEntradas[[#This Row],[Data do Caixa Previsto]],"Vista","Prazo") -> Vista | Q34: =IF(TbRegistroEntradas[[#This Row],[Data do Caixa Realizado]]<>"", IF(TbRegistroEntradas[[#This Row],[Data do Caixa Realizado]]>TbRegistroEntradas[[#This Row],[Data do Caixa Previsto]], TbRegistroEntradas[[#This Row],[Data do Caixa Realizado]]-TbRegistroEntradas[[#This Row],[Data do Caixa Previsto]], 0 ), IF(TODAY()>TbRegistroEntradas[[#This Row],[Data do Caixa Previsto]], TODAY()-TbRegistroEntradas[[#This Row],[Data do Caixa Previsto]], 0 ) ) -> 26
B35: 43101 | C35: 43053 | D35: 43101 | E35: Vendas de mercadorias | F35: Livros | G35: NF2347 | H35: 4108 | I35: =IF(TbRegistroEntradas[[#This Row],[Data do Caixa Realizado]]="",0,MONTH(TbRegistroEntradas[[#This Row],[Data do Caixa Realizado]])) -> 1 | J35: =IF(TbRegistroEntradas[[#This Row],[Data do Caixa Realizado]]="",0,YEAR(TbRegistroEntradas[[#This Row],[Data do Caixa Realizado]])) -> 2018 | K35: =IF(TbRegistroEntradas[[#This Row],[Data da Competência]]="",0,MONTH(TbRegistroEntradas[[#This Row],[Data da Competência]])) -> 11 | L35: =IF(TbRegistroEntradas[[#This Row],[Data da Competência]]="",0,YEAR(TbRegistroEntradas[[#This Row],[Data da Competência]])) -> 2017 | M35: =IF(TbRegistroEntradas[[#This Row],[Data do Caixa Previsto]]="",0,MONTH(TbRegistroEntradas[[#This Row],[Data do Caixa Previsto]])) -> 1 | N35: =IF(TbRegistroEntradas[[#This Row],[Data do Caixa Previsto]]="",0,YEAR(TbRegistroEntradas[[#This Row],[Data do Caixa Previsto]])) -> 2018 | O35: =IF(AND(TbRegistroEntradas[[#This Row],[Data do Caixa Previsto]]<TODAY(),TbRegistroEntradas[[#This Row],[Data do Caixa Realizado]]=""),"Vencida","Não Vencida") -> Não Vencida | P35: =IF(TbRegistroEntradas[[#This Row],[Data da Competência]]=TbRegistroEntradas[[#This Row],[Data do Caixa Previsto]],"Vista","Prazo") -> Prazo | Q35: =IF(TbRegistroEntradas[[#This Row],[Data do Caixa Realizado]]<>"", IF(TbRegistroEntradas[[#This Row],[Data do Caixa Realizado]]>TbRegistroEntradas[[#This Row],[Data do Caixa Previsto]], TbRegistroEntradas[[#This Row],[Data do Caixa Realizado]]-TbRegistroEntradas[[#This Row],[Data do Caixa Previsto]], 0 ), IF(TODAY()>TbRegistroEntradas[[#This Row],[Data do Caixa Previsto]], TODAY()-TbRegistroEntradas[[#This Row],[Data do Caixa Previsto]], 0 ) ) -> 0
B36: 43055 | C36: 43055 | D36: 43055 | E36: Vendas de mercadorias | F36: Móveis | G36: NF7848 | H36: 3714 | I36: =IF(TbRegistroEntradas[[#This Row],[Data do Caixa Realizado]]="",0,MONTH(TbRegistroEntradas[[#This Row],[Data do Caixa Realizado]])) -> 11 | J36: =IF(TbRegistroEntradas[[#This Row],[Data do Caixa Realizado]]="",0,YEAR(TbRegistroEntradas[[#This Row],[Data do Caixa Realizado]])) -> 2017 | K36: =IF(TbRegistroEntradas[[#This Row],[Data da Competência]]="",0,MONTH(TbRegistroEntradas[[#This Row],[Data da Competência]])) -> 11 | L36: =IF(TbRegistroEntradas[[#This Row],[Data da Competência]]="",0,YEAR(TbRegistroEntradas[[#This Row],[Data da Competência]])) -> 2017 | M36: =IF(TbRegistroEntradas[[#This Row],[Data do Caixa Previsto]]="",0,MONTH(TbRegistroEntradas[[#This Row],[Data do Caixa Previsto]])) -> 11 | N36: =IF(TbRegistroEntradas[[#This Row],[Data do Caixa Previsto]]="",0,YEAR(TbRegistroEntradas[[#This Row],[Data do Caixa Previsto]])) -> 2017 | O36: =IF(AND(TbRegistroEntradas[[#This Row],[Data do Caixa Previsto]]<TODAY(),TbRegistroEntradas[[#This Row],[Data do Caixa Realizado]]=""),"Vencida","Não Vencida") -> Não Vencida | P36: =IF(TbRegistroEntradas[[#This Row],[Data da Competência]]=TbRegistroEntradas[[#This Row],[Data do Caixa Previsto]],"Vista","Prazo") -> Vista | Q36: =IF(TbRegistroEntradas[[#This Row],[Data do Caixa Realizado]]<>"", IF(TbRegistroEntradas[[#This Row],[Data do Caixa Realizado]]>TbRegistroEntradas[[#This Row],[Data do Caixa Previsto]], TbRegistroEntradas[[#This Row],[Data do Caixa Realizado]]-TbRegistroEntradas[[#This Row],[Data do Caixa Previsto]], 0 ), IF(TODAY()>TbRegistroEntradas[[#This Row],[Data do Caixa Previsto]], TODAY()-TbRegistroEntradas[[#This Row],[Data do Caixa Previsto]], 0 ) ) -> 0
C37: 43057 | D37: 43101 | E37: Vendas de mercadorias | F37: Eletrodomésticos | G37: NF4449 | H37: 4843 | I37: =IF(TbRegistroEntradas[[#This Row],[Data do Caixa Realizado]]="",0,MONTH(TbRegistroEntradas[[#This Row],[Data do Caixa Realizado]])) -> 0 | J37: =IF(TbRegistroEntradas[[#This Row],[Data do Caixa Realizado]]="",0,YEAR(TbRegistroEntradas[[#This Row],[Data do Caixa Realizado]])) -> 0 | K37: =IF(TbRegistroEntradas[[#This Row],[Data da Competência]]="",0,MONTH(TbRegistroEntradas[[#This Row],[Data da Competência]])) -> 11 | L37: =IF(TbRegistroEntradas[[#This Row],[Data da Competência]]="",0,YEAR(TbRegistroEntradas[[#This Row],[Data da Competência]])) -> 2017 | M37: =IF(TbRegistroEntradas[[#This Row],[Data do Caixa Previsto]]="",0,MONTH(TbRegistroEntradas[[#This Row],[Data do Caixa Previsto]])) -> 1 | N37: =IF(TbRegistroEntradas[[#This Row],[Data do Caixa Previsto]]="",0,YEAR(TbRegistroEntradas[[#This Row],[Data do Caixa Previsto]])) -> 2018 | O37: =IF(AND(TbRegistroEntradas[[#This Row],[Data do Caixa Previsto]]<TODAY(),TbRegistroEntradas[[#This Row],[Data do Caixa Realizado]]=""),"Vencida","Não Vencida") -> Vencida | P37: =IF(TbRegistroEntradas[[#This Row],[Data da Competência]]=TbRegistroEntradas[[#This Row],[Data do Caixa Previsto]],"Vista","Prazo") -> Prazo | Q37: =IF(TbRegistroEntradas[[#This Row],[Data do Caixa Realizado]]<>"", IF(TbRegistroEntradas[[#This Row],[Data do Caixa Realizado]]>TbRegistroEntradas[[#This Row],[Data do Caixa Previsto]], TbRegistroEntradas[[#This Row],[Data do Caixa Realizado]]-TbRegistroEntradas[[#This Row],[Data do Caixa Previsto]], 0 ), IF(TODAY()>TbRegistroEntradas[[#This Row],[Data do Caixa Previsto]], TODAY()-TbRegistroEntradas[[#This Row],[Data do Caixa Previsto]], 0 ) ) -> 2252
B38: 43090 | C38: 43058 | D38: 43090 | E38: Vendas de mercadorias | F38: Som e imagem | G38: NF7540 | H38: 4831 | I38: =IF(TbRegistroEntradas[[#This Row],[Data do Caixa Realizado]]="",0,MONTH(TbRegistroEntradas[[#This Row],[Data do Caixa Realizado]])) -> 12 | J38: =IF(TbRegistroEntradas[[#This Row],[Data do Caixa Realizado]]="",0,YEAR(TbRegistroEntradas[[#This Row],[Data do Caixa Realizado]])) -> 2017 | K38: =IF(TbRegistroEntradas[[#This Row],[Data da Competência]]="",0,MONTH(TbRegistroEntradas[[#This Row],[Data da Competência]])) -> 11 | L38: =IF(TbRegistroEntradas[[#This Row],[Data da Competência]]="",0,YEAR(TbRegistroEntradas[[#This Row],[Data da Competência]])) -> 2017 | M38: =IF(TbRegistroEntradas[[#This Row],[Data do Caixa Previsto]]="",0,MONTH(TbRegistroEntradas[[#This Row],[Data do Caixa Previsto]])) -> 12 | N38: =IF(TbRegistroEntradas[[#This Row],[Data do Caixa Previsto]]="",0,YEAR(TbRegistroEntradas[[#This Row],[Data do Caixa Previsto]])) -> 2017 | O38: =IF(AND(TbRegistroEntradas[[#This Row],[Data do Caixa Previsto]]<TODAY(),TbRegistroEntradas[[#This Row],[Data do Caixa Realizado]]=""),"Vencida","Não Vencida") -> Não Vencida | P38: =IF(TbRegistroEntradas[[#This Row],[Data da Competência]]=TbRegistroEntradas[[#This Row],[Data do Caixa Previsto]],"Vista","Prazo") -> Prazo | Q38: =IF(TbRegistroEntradas[[#This Row],[Data do Caixa Realizado]]<>"", IF(TbRegistroEntradas[[#This Row],[Data do Caixa Realizado]]>TbRegistroEntradas[[#This Row],[Data do Caixa Previsto]], TbRegistroEntradas[[#This Row],[Data do Caixa Realizado]]-TbRegistroEntradas[[#This Row],[Data do Caixa Previsto]], 0 ), IF(TODAY()>TbRegistroEntradas[[#This Row],[Data do Caixa Previsto]], TODAY()-TbRegistroEntradas[[#This Row],[Data do Caixa Previsto]], 0 ) ) -> 0
B39: 43059 | C39: 43059 | D39: 43059 | E39: Vendas de mercadorias | F39: Móveis | G39: NF7741 | H39: 2072 | I39: =IF(TbRegistroEntradas[[#This Row],[Data do Caixa Realizado]]="",0,MONTH(TbRegistroEntradas[[#This Row],[Data do Caixa Realizado]])) -> 11 | J39: =IF(TbRegistroEntradas[[#This Row],[Data do Caixa Realizado]]="",0,YEAR(TbRegistroEntradas[[#This Row],[Data do Caixa Realizado]])) -> 2017 | K39: =IF(TbRegistroEntradas[[#This Row],[Data da Competência]]="",0,MONTH(TbRegistroEntradas[[#This Row],[Data da Competência]])) -> 11 | L39: =IF(TbRegistroEntradas[[#This Row],[Data da Competência]]="",0,YEAR(TbRegistroEntradas[[#This Row],[Data da Competência]])) -> 2017 | M39: =IF(TbRegistroEntradas[[#This Row],[Data do Caixa Previsto]]="",0,MONTH(TbRegistroEntradas[[#This Row],[Data do Caixa Previsto]])) -> 11 | N39: =IF(TbRegistroEntradas[[#This Row],[Data do Caixa Previsto]]="",0,YEAR(TbRegistroEntradas[[#This Row],[Data do Caixa Previsto]])) -> 2017 | O39: =IF(AND(TbRegistroEntradas[[#This Row],[Data do Caixa Previsto]]<TODAY(),TbRegistroEntradas[[#This Row],[Data do Caixa Realizado]]=""),"Vencida","Não Vencida") -> Não Vencida | P39: =IF(TbRegistroEntradas[[#This Row],[Data da Competência]]=TbRegistroEntradas[[#This Row],[Data do Caixa Previsto]],"Vista","Prazo") -> Vista | Q39: =IF(TbRegistroEntradas[[#This Row],[Data do Caixa Realizado]]<>"", IF(TbRegistroEntradas[[#This Row],[Data do Caixa Realizado]]>TbRegistroEntradas[[#This Row],[Data do Caixa Previsto]], TbRegistroEntradas[[#This Row],[Data do Caixa Realizado]]-TbRegistroEntradas[[#This Row],[Data do Caixa Previsto]], 0 ), IF(TODAY()>TbRegistroEntradas[[#This Row],[Data do Caixa Previsto]], TODAY()-TbRegistroEntradas[[#This Row],[Data do Caixa Previsto]], 0 ) ) -> 0
B40: 43122 | C40: 43063 | D40: 43122 | E40: Vendas de mercadorias | F40: Informática | G40: NF6190 | H40: 3992 | I40: =IF(TbRegistroEntradas[[#This Row],[Data do Caixa Realizado]]="",0,MONTH(TbRegistroEntradas[[#This Row],[Data do Caixa Realizado]])) -> 1 | J40: =IF(TbRegistroEntradas[[#This Row],[Data do Caixa Realizado]]="",0,YEAR(TbRegistroEntradas[[#This Row],[Data do Caixa Realizado]])) -> 2018 | K40: =IF(TbRegistroEntradas[[#This Row],[Data da Competência]]="",0,MONTH(TbRegistroEntradas[[#This Row],[Data da Competência]])) -> 11 | L40: =IF(TbRegistroEntradas[[#This Row],[Data da Competência]]="",0,YEAR(TbRegistroEntradas[[#This Row],[Data da Competência]])) -> 2017 | M40: =IF(TbRegistroEntradas[[#This Row],[Data do Caixa Previsto]]="",0,MONTH(TbRegistroEntradas[[#This Row],[Data do Caixa Previsto]])) -> 1 | N40: =IF(TbRegistroEntradas[[#This Row],[Data do Caixa Previsto]]="",0,YEAR(TbRegistroEntradas[[#This Row],[Data do Caixa Previsto]])) -> 2018 | O40: =IF(AND(TbRegistroEntradas[[#This Row],[Data do Caixa Previsto]]<TODAY(),TbRegistroEntradas[[#This Row],[Data do Caixa Realizado]]=""),"Vencida","Não Vencida") -> Não Vencida | P40: =IF(TbRegistroEntradas[[#This Row],[Data da Competência]]=TbRegistroEntradas[[#This Row],[Data do Caixa Previsto]],"Vista","Prazo") -> Prazo | Q40: =IF(TbRegistroEntradas[[#This Row],[Data do Caixa Realizado]]<>"", IF(TbRegistroEntradas[[#This Row],[Data do Caixa Realizado]]>TbRegistroEntradas[[#This Row],[Data do Caixa Previsto]], TbRegistroEntradas[[#This Row],[Data do Caixa Realizado]]-TbRegistroEntradas[[#This Row],[Data do Caixa Previsto]], 0 ), IF(TODAY()>TbRegistroEntradas[[#This Row],[Data do Caixa Previsto]], TODAY()-TbRegistroEntradas[[#This Row],[Data do Caixa Previsto]], 0 ) ) -> 0
B41: 43114 | C41: 43068 | D41: 43068 | E41: Vendas de mercadorias | F41: Eletrodomésticos | G41: NF4129 | H41: 1284 | I41: =IF(TbRegistroEntradas[[#This Row],[Data do Caixa Realizado]]="",0,MONTH(TbRegistroEntradas[[#This Row],[Data do Caixa Realizado]])) -> 1 | J41: =IF(TbRegistroEntradas[[#This Row],[Data do Caixa Realizado]]="",0,YEAR(TbRegistroEntradas[[#This Row],[Data do Caixa Realizado]])) -> 2018 | K41: =IF(TbRegistroEntradas[[#This Row],[Data da Competência]]="",0,MONTH(TbRegistroEntradas[[#This Row],[Data da Competência]])) -> 11 | L41: =IF(TbRegistroEntradas[[#This Row],[Data da Competência]]="",0,YEAR(TbRegistroEntradas[[#This Row],[Data da Competência]])) -> 2017 | M41: =IF(TbRegistroEntradas[[#This Row],[Data do Caixa Previsto]]="",0,MONTH(TbRegistroEntradas[[#This Row],[Data do Caixa Previsto]])) -> 11 | N41: =IF(TbRegistroEntradas[[#This Row],[Data do Caixa Previsto]]="",0,YEAR(TbRegistroEntradas[[#This Row],[Data do Caixa Previsto]])) -> 2017 | O41: =IF(AND(TbRegistroEntradas[[#This Row],[Data do Caixa Previsto]]<TODAY(),TbRegistroEntradas[[#This Row],[Data do Caixa Realizado]]=""),"Vencida","Não Vencida") -> Não Vencida | P41: =IF(TbRegistroEntradas[[#This Row],[Data da Competência]]=TbRegistroEntradas[[#This Row],[Data do Caixa Previsto]],"Vista","Prazo") -> Vista | Q41: =IF(TbRegistroEntradas[[#This Row],[Data do Caixa Realizado]]<>"", IF(TbRegistroEntradas[[#This Row],[Data do Caixa Realizado]]>TbRegistroEntradas[[#This Row],[Data do Caixa Previsto]], TbRegistroEntradas[[#This Row],[Data do Caixa Realizado]]-TbRegistroEntradas[[#This Row],[Data do Caixa Previsto]], 0 ), IF(TODAY()>TbRegistroEntradas[[#This Row],[Data do Caixa Previsto]], TODAY()-TbRegistroEntradas[[#This Row],[Data do Caixa Previsto]], 0 ) ) -> 46
B42: 43073 | C42: 43073 | D42: 43073 | E42: Vendas de mercadorias | F42: Informática | G42: NF6811 | H42: 4073 | I42: =IF(TbRegistroEntradas[[#This Row],[Data do Caixa Realizado]]="",0,MONTH(TbRegistroEntradas[[#This Row],[Data do Caixa Realizado]])) -> 12 | J42: =IF(TbRegistroEntradas[[#This Row],[Data do Caixa Realizado]]="",0,YEAR(TbRegistroEntradas[[#This Row],[Data do Caixa Realizado]])) -> 2017 | K42: =IF(TbRegistroEntradas[[#This Row],[Data da Competência]]="",0,MONTH(TbRegistroEntradas[[#This Row],[Data da Competência]])) -> 12 | L42: =IF(TbRegistroEntradas[[#This Row],[Data da Competência]]="",0,YEAR(TbRegistroEntradas[[#This Row],[Data da Competência]])) -> 2017 | M42: =IF(TbRegistroEntradas[[#This Row],[Data do Caixa Previsto]]="",0,MONTH(TbRegistroEntradas[[#This Row],[Data do Caixa Previsto]])) -> 12 | N42: =IF(TbRegistroEntradas[[#This Row],[Data do Caixa Previsto]]="",0,YEAR(TbRegistroEntradas[[#This Row],[Data do Caixa Previsto]])) -> 2017 | O42: =IF(AND(TbRegistroEntradas[[#This Row],[Data do Caixa Previsto]]<TODAY(),TbRegistroEntradas[[#This Row],[Data do Caixa Realizado]]=""),"Vencida","Não Vencida") -> Não Vencida | P42: =IF(TbRegistroEntradas[[#This Row],[Data da Competência]]=TbRegistroEntradas[[#This Row],[Data do Caixa Previsto]],"Vista","Prazo") -> Vista | Q42: =IF(TbRegistroEntradas[[#This Row],[Data do Caixa Realizado]]<>"", IF(TbRegistroEntradas[[#This Row],[Data do Caixa Realizado]]>TbRegistroEntradas[[#This Row],[Data do Caixa Previsto]], TbRegistroEntradas[[#This Row],[Data do Caixa Realizado]]-TbRegistroEntradas[[#This Row],[Data do Caixa Previsto]], 0 ), IF(TODAY()>TbRegistroEntradas[[#This Row],[Data do Caixa Previsto]], TODAY()-TbRegistroEntradas[[#This Row],[Data do Caixa Previsto]], 0 ) ) -> 0
B43: 43073 | C43: 43073 | D43: 43073 | E43: Vendas de mercadorias | F43: Eletrodomésticos | G43: NF1550 | H43: 3008 | I43: =IF(TbRegistroEntradas[[#This Row],[Data do Caixa Realizado]]="",0,MONTH(TbRegistroEntradas[[#This Row],[Data do Caixa Realizado]])) -> 12 | J43: =IF(TbRegistroEntradas[[#This Row],[Data do Caixa Realizado]]="",0,YEAR(TbRegistroEntradas[[#This Row],[Data do Caixa Realizado]])) -> 2017 | K43: =IF(TbRegistroEntradas[[#This Row],[Data da Competência]]="",0,MONTH(TbRegistroEntradas[[#This Row],[Data da Competência]])) -> 12 | L43: =IF(TbRegistroEntradas[[#This Row],[Data da Competência]]="",0,YEAR(TbRegistroEntradas[[#This Row],[Data da Competência]])) -> 2017 | M43: =IF(TbRegistroEntradas[[#This Row],[Data do Caixa Previsto]]="",0,MONTH(TbRegistroEntradas[[#This Row],[Data do Caixa Previsto]])) -> 12 | N43: =IF(TbRegistroEntradas[[#This Row],[Data do Caixa Previsto]]="",0,YEAR(TbRegistroEntradas[[#This Row],[Data do Caixa Previsto]])) -> 2017 | O43: =IF(AND(TbRegistroEntradas[[#This Row],[Data do Caixa Previsto]]<TODAY(),TbRegistroEntradas[[#This Row],[Data do Caixa Realizado]]=""),"Vencida","Não Vencida") -> Não Vencida | P43: =IF(TbRegistroEntradas[[#This Row],[Data da Competência]]=TbRegistroEntradas[[#This Row],[Data do Caixa Previsto]],"Vista","Prazo") -> Vista | Q43: =IF(TbRegistroEntradas[[#This Row],[Data do Caixa Realizado]]<>"", IF(TbRegistroEntradas[[#This Row],[Data do Caixa Realizado]]>TbRegistroEntradas[[#This Row],[Data do Caixa Previsto]], TbRegistroEntradas[[#This Row],[Data do Caixa Realizado]]-TbRegistroEntradas[[#This Row],[Data do Caixa Previsto]], 0 ), IF(TODAY()>TbRegistroEntradas[[#This Row],[Data do Caixa Previsto]], TODAY()-TbRegistroEntradas[[#This Row],[Data do Caixa Previsto]], 0 ) ) -> 0
B44: 43103 | C44: 43080 | D44: 43080 | E44: Vendas de mercadorias | F44: Eletrodomésticos | G44: NF7213 | H44: 1267 | I44: =IF(TbRegistroEntradas[[#This Row],[Data do Caixa Realizado]]="",0,MONTH(TbRegistroEntradas[[#This Row],[Data do Caixa Realizado]])) -> 1 | J44: =IF(TbRegistroEntradas[[#This Row],[Data do Caixa Realizado]]="",0,YEAR(TbRegistroEntradas[[#This Row],[Data do Caixa Realizado]])) -> 2018 | K44: =IF(TbRegistroEntradas[[#This Row],[Data da Competência]]="",0,MONTH(TbRegistroEntradas[[#This Row],[Data da Competência]])) -> 12 | L44: =IF(TbRegistroEntradas[[#This Row],[Data da Competência]]="",0,YEAR(TbRegistroEntradas[[#This Row],[Data da Competência]])) -> 2017 | M44: =IF(TbRegistroEntradas[[#This Row],[Data do Caixa Previsto]]="",0,MONTH(TbRegistroEntradas[[#This Row],[Data do Caixa Previsto]])) -> 12 | N44: =IF(TbRegistroEntradas[[#This Row],[Data do Caixa Previsto]]="",0,YEAR(TbRegistroEntradas[[#This Row],[Data do Caixa Previsto]])) -> 2017 | O44: =IF(AND(TbRegistroEntradas[[#This Row],[Data do Caixa Previsto]]<TODAY(),TbRegistroEntradas[[#This Row],[Data do Caixa Realizado]]=""),"Vencida","Não Vencida") -> Não Vencida | P44: =IF(TbRegistroEntradas[[#This Row],[Data da Competência]]=TbRegistroEntradas[[#This Row],[Data do Caixa Previsto]],"Vista","Prazo") -> Vista | Q44: =IF(TbRegistroEntradas[[#This Row],[Data do Caixa Realizado]]<>"", IF(TbRegistroEntradas[[#This Row],[Data do Caixa Realizado]]>TbRegistroEntradas[[#This Row],[Data do Caixa Previsto]], TbRegistroEntradas[[#This Row],[Data do Caixa Realizado]]-TbRegistroEntradas[[#This Row],[Data do Caixa Previsto]], 0 ), IF(TODAY()>TbRegistroEntradas[[#This Row],[Data do Caixa Previsto]], TODAY()-TbRegistroEntradas[[#This Row],[Data do Caixa Previsto]], 0 ) ) -> 23
B45: 43103 | C45: 43082 | D45: 43103 | E45: Vendas de mercadorias | F45: Eletrodomésticos | G45: NF8396 | H45: 284 | I45: =IF(TbRegistroEntradas[[#This Row],[Data do Caixa Realizado]]="",0,MONTH(TbRegistroEntradas[[#This Row],[Data do Caixa Realizado]])) -> 1 | J45: =IF(TbRegistroEntradas[[#This Row],[Data do Caixa Realizado]]="",0,YEAR(TbRegistroEntradas[[#This Row],[Data do Caixa Realizado]])) -> 2018 | K45: =IF(TbRegistroEntradas[[#This Row],[Data da Competência]]="",0,MONTH(TbRegistroEntradas[[#This Row],[Data da Competência]])) -> 12 | L45: =IF(TbRegistroEntradas[[#This Row],[Data da Competência]]="",0,YEAR(TbRegistroEntradas[[#This Row],[Data da Competência]])) -> 2017 | M45: =IF(TbRegistroEntradas[[#This Row],[Data do Caixa Previsto]]="",0,MONTH(TbRegistroEntradas[[#This Row],[Data do Caixa Previsto]])) -> 1 | N45: =IF(TbRegistroEntradas[[#This Row],[Data do Caixa Previsto]]="",0,YEAR(TbRegistroEntradas[[#This Row],[Data do Caixa Previsto]])) -> 2018 | O45: =IF(AND(TbRegistroEntradas[[#This Row],[Data do Caixa Previsto]]<TODAY(),TbRegistroEntradas[[#This Row],[Data do Caixa Realizado]]=""),"Vencida","Não Vencida") -> Não Vencida | P45: =IF(TbRegistroEntradas[[#This Row],[Data da Competência]]=TbRegistroEntradas[[#This Row],[Data do Caixa Previsto]],"Vista","Prazo") -> Prazo | Q45: =IF(TbRegistroEntradas[[#This Row],[Data do Caixa Realizado]]<>"", IF(TbRegistroEntradas[[#This Row],[Data do Caixa Realizado]]>TbRegistroEntradas[[#This Row],[Data do Caixa Previsto]], TbRegistroEntradas[[#This Row],[Data do Caixa Realizado]]-TbRegistroEntradas[[#This Row],[Data do Caixa Previsto]], 0 ), IF(TODAY()>TbRegistroEntradas[[#This Row],[Data do Caixa Previsto]], TODAY()-TbRegistroEntradas[[#This Row],[Data do Caixa Previsto]], 0 ) ) -> 0
B46: 43086 | C46: 43083 | D46: 43086 | E46: Vendas de mercadorias | F46: Móveis | G46: NF2432 | H46: 2046 | I46: =IF(TbRegistroEntradas[[#This Row],[Data do Caixa Realizado]]="",0,MONTH(TbRegistroEntradas[[#This Row],[Data do Caixa Realizado]])) -> 12 | J46: =IF(TbRegistroEntradas[[#This Row],[Data do Caixa Realizado]]="",0,YEAR(TbRegistroEntradas[[#This Row],[Data do Caixa Realizado]])) -> 2017 | K46: =IF(TbRegistroEntradas[[#This Row],[Data da Competência]]="",0,MONTH(TbRegistroEntradas[[#This Row],[Data da Competência]])) -> 12 | L46: =IF(TbRegistroEntradas[[#This Row],[Data da Competência]]="",0,YEAR(TbRegistroEntradas[[#This Row],[Data da Competência]])) -> 2017 | M46: =IF(TbRegistroEntradas[[#This Row],[Data do Caixa Previsto]]="",0,MONTH(TbRegistroEntradas[[#This Row],[Data do Caixa Previsto]])) -> 12 | N46: =IF(TbRegistroEntradas[[#This Row],[Data do Caixa Previsto]]="",0,YEAR(TbRegistroEntradas[[#This Row],[Data do Caixa Previsto]])) -> 2017 | O46: =IF(AND(TbRegistroEntradas[[#This Row],[Data do Caixa Previsto]]<TODAY(),TbRegistroEntradas[[#This Row],[Data do Caixa Realizado]]=""),"Vencida","Não Vencida") -> Não Vencida | P46: =IF(TbRegistroEntradas[[#This Row],[Data da Competência]]=TbRegistroEntradas[[#This Row],[Data do Caixa Previsto]],"Vista","Prazo") -> Prazo | Q46: =IF(TbRegistroEntradas[[#This Row],[Data do Caixa Realizado]]<>"", IF(TbRegistroEntradas[[#This Row],[Data do Caixa Realizado]]>TbRegistroEntradas[[#This Row],[Data do Caixa Previsto]], TbRegistroEntradas[[#This Row],[Data do Caixa Realizado]]-TbRegistroEntradas[[#This Row],[Data do Caixa Previsto]], 0 ), IF(TODAY()>TbRegistroEntradas[[#This Row],[Data do Caixa Previsto]], TODAY()-TbRegistroEntradas[[#This Row],[Data do Caixa Previsto]], 0 ) ) -> 0
B47: 43122 | C47: 43085 | D47: 43122 | E47: Vendas de mercadorias | F47: Informática | G47: NF4722 | H47: 3880 | I47: =IF(TbRegistroEntradas[[#This Row],[Data do Caixa Realizado]]="",0,MONTH(TbRegistroEntradas[[#This Row],[Data do Caixa Realizado]])) -> 1 | J47: =IF(TbRegistroEntradas[[#This Row],[Data do Caixa Realizado]]="",0,YEAR(TbRegistroEntradas[[#This Row],[Data do Caixa Realizado]])) -> 2018 | K47: =IF(TbRegistroEntradas[[#This Row],[Data da Competência]]="",0,MONTH(TbRegistroEntradas[[#This Row],[Data da Competência]])) -> 12 | L47: =IF(TbRegistroEntradas[[#This Row],[Data da Competência]]="",0,YEAR(TbRegistroEntradas[[#This Row],[Data da Competência]])) -> 2017 | M47: =IF(TbRegistroEntradas[[#This Row],[Data do Caixa Previsto]]="",0,MONTH(TbRegistroEntradas[[#This Row],[Data do Caixa Previsto]])) -> 1 | N47: =IF(TbRegistroEntradas[[#This Row],[Data do Caixa Previsto]]="",0,YEAR(TbRegistroEntradas[[#This Row],[Data do Caixa Previsto]])) -> 2018 | O47: =IF(AND(TbRegistroEntradas[[#This Row],[Data do Caixa Previsto]]<TODAY(),TbRegistroEntradas[[#This Row],[Data do Caixa Realizado]]=""),"Vencida","Não Vencida") -> Não Vencida | P47: =IF(TbRegistroEntradas[[#This Row],[Data da Competência]]=TbRegistroEntradas[[#This Row],[Data do Caixa Previsto]],"Vista","Prazo") -> Prazo | Q47: =IF(TbRegistroEntradas[[#This Row],[Data do Caixa Realizado]]<>"", IF(TbRegistroEntradas[[#This Row],[Data do Caixa Realizado]]>TbRegistroEntradas[[#This Row],[Data do Caixa Previsto]], TbRegistroEntradas[[#This Row],[Data do Caixa Realizado]]-TbRegistroEntradas[[#This Row],[Data do Caixa Previsto]], 0 ), IF(TODAY()>TbRegistroEntradas[[#This Row],[Data do Caixa Previsto]], TODAY()-TbRegistroEntradas[[#This Row],[Data do Caixa Previsto]], 0 ) ) -> 0
B48: 43123 | C48: 43086 | D48: 43123 | E48: Vendas de mercadorias | F48: Informática | G48: NF8944 | H48: 3149 | I48: =IF(TbRegistroEntradas[[#This Row],[Data do Caixa Realizado]]="",0,MONTH(TbRegistroEntradas[[#This Row],[Data do Caixa Realizado]])) -> 1 | J48: =IF(TbRegistroEntradas[[#This Row],[Data do Caixa Realizado]]="",0,YEAR(TbRegistroEntradas[[#This Row],[Data do Caixa Realizado]])) -> 2018 | K48: =IF(TbRegistroEntradas[[#This Row],[Data da Competência]]="",0,MONTH(TbRegistroEntradas[[#This Row],[Data da Competência]])) -> 12 | L48: =IF(TbRegistroEntradas[[#This Row],[Data da Competência]]="",0,YEAR(TbRegistroEntradas[[#This Row],[Data da Competência]])) -> 2017 | M48: =IF(TbRegistroEntradas[[#This Row],[Data do Caixa Previsto]]="",0,MONTH(TbRegistroEntradas[[#This Row],[Data do Caixa Previsto]])) -> 1 | N48: =IF(TbRegistroEntradas[[#This Row],[Data do Caixa Previsto]]="",0,YEAR(TbRegistroEntradas[[#This Row],[Data do Caixa Previsto]])) -> 2018 | O48: =IF(AND(TbRegistroEntradas[[#This Row],[Data do Caixa Previsto]]<TODAY(),TbRegistroEntradas[[#This Row],[Data do Caixa Realizado]]=""),"Vencida","Não Vencida") -> Não Vencida | P48: =IF(TbRegistroEntradas[[#This Row],[Data da Competência]]=TbRegistroEntradas[[#This Row],[Data do Caixa Previsto]],"Vista","Prazo") -> Prazo | Q48: =IF(TbRegistroEntradas[[#This Row],[Data do Caixa Realizado]]<>"", IF(TbRegistroEntradas[[#This Row],[Data do Caixa Realizado]]>TbRegistroEntradas[[#This Row],[Data do Caixa Previsto]], TbRegistroEntradas[[#This Row],[Data do Caixa Realizado]]-TbRegistroEntradas[[#This Row],[Data do Caixa Previsto]], 0 ), IF(TODAY()>TbRegistroEntradas[[#This Row],[Data do Caixa Previsto]], TODAY()-TbRegistroEntradas[[#This Row],[Data do Caixa Previsto]], 0 ) ) -> 0
B49: 43125 | C49: 43088 | D49: 43125 | E49: Vendas de mercadorias | F49: Móveis | G49: NF2816 | H49: 668 | I49: =IF(TbRegistroEntradas[[#This Row],[Data do Caixa Realizado]]="",0,MONTH(TbRegistroEntradas[[#This Row],[Data do Caixa Realizado]])) -> 1 | J49: =IF(TbRegistroEntradas[[#This Row],[Data do Caixa Realizado]]="",0,YEAR(TbRegistroEntradas[[#This Row],[Data do Caixa Realizado]])) -> 2018 | K49: =IF(TbRegistroEntradas[[#This Row],[Data da Competência]]="",0,MONTH(TbRegistroEntradas[[#This Row],[Data da Competência]])) -> 12 | L49: =IF(TbRegistroEntradas[[#This Row],[Data da Competência]]="",0,YEAR(TbRegistroEntradas[[#This Row],[Data da Competência]])) -> 2017 | M49: =IF(TbRegistroEntradas[[#This Row],[Data do Caixa Previsto]]="",0,MONTH(TbRegistroEntradas[[#This Row],[Data do Caixa Previsto]])) -> 1 | N49: =IF(TbRegistroEntradas[[#This Row],[Data do Caixa Previsto]]="",0,YEAR(TbRegistroEntradas[[#This Row],[Data do Caixa Previsto]])) -> 2018 | O49: =IF(AND(TbRegistroEntradas[[#This Row],[Data do Caixa Previsto]]<TODAY(),TbRegistroEntradas[[#This Row],[Data do Caixa Realizado]]=""),"Vencida","Não Vencida") -> Não Vencida | P49: =IF(TbRegistroEntradas[[#This Row],[Data da Competência]]=TbRegistroEntradas[[#This Row],[Data do Caixa Previsto]],"Vista","Prazo") -> Prazo | Q49: =IF(TbRegistroEntradas[[#This Row],[Data do Caixa Realizado]]<>"", IF(TbRegistroEntradas[[#This Row],[Data do Caixa Realizado]]>TbRegistroEntradas[[#This Row],[Data do Caixa Previsto]], TbRegistroEntradas[[#This Row],[Data do Caixa Realizado]]-TbRegistroEntradas[[#This Row],[Data do Caixa Previsto]], 0 ), IF(TODAY()>TbRegistroEntradas[[#This Row],[Data do Caixa Previsto]], TODAY()-TbRegistroEntradas[[#This Row],[Data do Caixa Previsto]], 0 ) ) -> 0
... B54: 43144 | C54: 43100 | D54: 43144 | E54: Vendas de mercadorias | F54: Som e imagem | G54: NF2196 | H54: 2687 | I54: =IF(TbRegistroEntradas[[#This Row],[Data do Caixa Realizado]]="",0,MONTH(TbRegistroEntradas[[#This Row],[Data do Caixa Realizado]])) -> 2 | J54: =IF(TbRegistroEntradas[[#This Row],[Data do Caixa Realizado]]="",0,YEAR(TbRegistroEntradas[[#This Row],[Data do Caixa Realizado]])) -> 2018 | K54: =IF(TbRegistroEntradas[[#This Row],[Data da Competência]]="",0,MONTH(TbRegistroEntradas[[#This Row],[Data da Competência]])) -> 12 | L54: =IF(TbRegistroEntradas[[#This Row],[Data da Competência]]="",0,YEAR(TbRegistroEntradas[[#This Row],[Data da Competência]])) -> 2017 | M54: =IF(TbRegistroEntradas[[#This Row],[Data do Caixa Previsto]]="",0,MONTH(TbRegistroEntradas[[#This Row],[Data do Caixa Previsto]])) -> 2 | N54: =IF(TbRegistroEntradas[[#This Row],[Data do Caixa Previsto]]="",0,YEAR(TbRegistroEntradas[[#This Row],[Data do Caixa Previsto]])) -> 2018 | O54: =IF(AND(TbRegistroEntradas[[#This Row],[Data do Caixa Previsto]]<TODAY(),TbRegistroEntradas[[#This Row],[Data do Caixa Realizado]]=""),"Vencida","Não Vencida") -> Não Vencida | P54: =IF(TbRegistroEntradas[[#This Row],[Data da Competência]]=TbRegistroEntradas[[#This Row],[Data do Caixa Previsto]],"Vista","Prazo") -> Prazo | Q54: =IF(TbRegistroEntradas[[#This Row],[Data do Caixa Realizado]]<>"", IF(TbRegistroEntradas[[#This Row],[Data do Caixa Realizado]]>TbRegistroEntradas[[#This Row],[Data do Caixa Previsto]], TbRegistroEntradas[[#This Row],[Data do Caixa Realizado]]-TbRegistroEntradas[[#This Row],[Data do Caixa Previsto]], 0 ), IF(TODAY()>TbRegistroEntradas[[#This Row],[Data do Caixa Previsto]], TODAY()-TbRegistroEntradas[[#This Row],[Data do Caixa Previsto]], 0 ) ) -> 0
C55: 43103 | D55: 43159 | E55: Vendas de mercadorias | F55: Móveis | G55: NF1631 | H55: 1561 | I55: =IF(TbRegistroEntradas[[#This Row],[Data do Caixa Realizado]]="",0,MONTH(TbRegistroEntradas[[#This Row],[Data do Caixa Realizado]])) -> 0 | J55: =IF(TbRegistroEntradas[[#This Row],[Data do Caixa Realizado]]="",0,YEAR(TbRegistroEntradas[[#This Row],[Data do Caixa Realizado]])) -> 0 | K55: =IF(TbRegistroEntradas[[#This Row],[Data da Competência]]="",0,MONTH(TbRegistroEntradas[[#This Row],[Data da Competência]])) -> 1 | L55: =IF(TbRegistroEntradas[[#This Row],[Data da Competência]]="",0,YEAR(TbRegistroEntradas[[#This Row],[Data da Competência]])) -> 2018 | M55: =IF(TbRegistroEntradas[[#This Row],[Data do Caixa Previsto]]="",0,MONTH(TbRegistroEntradas[[#This Row],[Data do Caixa Previsto]])) -> 2 | N55: =IF(TbRegistroEntradas[[#This Row],[Data do Caixa Previsto]]="",0,YEAR(TbRegistroEntradas[[#This Row],[Data do Caixa Previsto]])) -> 2018 | O55: =IF(AND(TbRegistroEntradas[[#This Row],[Data do Caixa Previsto]]<TODAY(),TbRegistroEntradas[[#This Row],[Data do Caixa Realizado]]=""),"Vencida","Não Vencida") -> Vencida | P55: =IF(TbRegistroEntradas[[#This Row],[Data da Competência]]=TbRegistroEntradas[[#This Row],[Data do Caixa Previsto]],"Vista","Prazo") -> Prazo | Q55: =IF(TbRegistroEntradas[[#This Row],[Data do Caixa Realizado]]<>"", IF(TbRegistroEntradas[[#This Row],[Data do Caixa Realizado]]>TbRegistroEntradas[[#This Row],[Data do Caixa Previsto]], TbRegistroEntradas[[#This Row],[Data do Caixa Realizado]]-TbRegistroEntradas[[#This Row],[Data do Caixa Previsto]], 0 ), IF(TODAY()>TbRegistroEntradas[[#This Row],[Data do Caixa Previsto]], TODAY()-TbRegistroEntradas[[#This Row],[Data do Caixa Previsto]], 0 ) ) -> 2194
B56: 43155 | C56: 43109 | D56: 43113 | E56: Vendas de mercadorias | F56: Móveis | G56: NF9340 | H56: 1573 | I56: =IF(TbRegistroEntradas[[#This Row],[Data do Caixa Realizado]]="",0,MONTH(TbRegistroEntradas[[#This Row],[Data do Caixa Realizado]])) -> 2 | J56: =IF(TbRegistroEntradas[[#This Row],[Data do Caixa Realizado]]="",0,YEAR(TbRegistroEntradas[[#This Row],[Data do Caixa Realizado]])) -> 2018 | K56: =IF(TbRegistroEntradas[[#This Row],[Data da Competência]]="",0,MONTH(TbRegistroEntradas[[#This Row],[Data da Competência]])) -> 1 | L56: =IF(TbRegistroEntradas[[#This Row],[Data da Competência]]="",0,YEAR(TbRegistroEntradas[[#This Row],[Data da Competência]])) -> 2018 | M56: =IF(TbRegistroEntradas[[#This Row],[Data do Caixa Previsto]]="",0,MONTH(TbRegistroEntradas[[#This Row],[Data do Caixa Previsto]])) -> 1 | N56: =IF(TbRegistroEntradas[[#This Row],[Data do Caixa Previsto]]="",0,YEAR(TbRegistroEntradas[[#This Row],[Data do Caixa Previsto]])) -> 2018 | O56: =IF(AND(TbRegistroEntradas[[#This Row],[Data do Caixa Previsto]]<TODAY(),TbRegistroEntradas[[#This Row],[Data do Caixa Realizado]]=""),"Vencida","Não Vencida") -> Não Vencida | P56: =IF(TbRegistroEntradas[[#This Row],[Data da Competência]]=TbRegistroEntradas[[#This Row],[Data do Caixa Previsto]],"Vista","Prazo") -> Prazo | Q56: =IF(TbRegistroEntradas[[#This Row],[Data do Caixa Realizado]]<>"", IF(TbRegistroEntradas[[#This Row],[Data do Caixa Realizado]]>TbRegistroEntradas[[#This Row],[Data do Caixa Previsto]], TbRegistroEntradas[[#This Row],[Data do Caixa Realizado]]-TbRegistroEntradas[[#This Row],[Data do Caixa Previsto]], 0 ), IF(TODAY()>TbRegistroEntradas[[#This Row],[Data do Caixa Previsto]], TODAY()-TbRegistroEntradas[[#This Row],[Data do Caixa Previsto]], 0 ) ) -> 42
B57: 43117 | C57: 43117 | D57: 43117 | E57: Vendas de mercadorias | F57: Móveis | G57: NF6851 | H57: 1364 | I57: =IF(TbRegistroEntradas[[#This Row],[Data do Caixa Realizado]]="",0,MONTH(TbRegistroEntradas[[#This Row],[Data do Caixa Realizado]])) -> 1 | J57: =IF(TbRegistroEntradas[[#This Row],[Data do Caixa Realizado]]="",0,YEAR(TbRegistroEntradas[[#This Row],[Data do Caixa Realizado]])) -> 2018 | K57: =IF(TbRegistroEntradas[[#This Row],[Data da Competência]]="",0,MONTH(TbRegistroEntradas[[#This Row],[Data da Competência]])) -> 1 | L57: =IF(TbRegistroEntradas[[#This Row],[Data da Competência]]="",0,YEAR(TbRegistroEntradas[[#This Row],[Data da Competência]])) -> 2018 | M57: =IF(TbRegistroEntradas[[#This Row],[Data do Caixa Previsto]]="",0,MONTH(TbRegistroEntradas[[#This Row],[Data do Caixa Previsto]])) -> 1 | N57: =IF(TbRegistroEntradas[[#This Row],[Data do Caixa Previsto]]="",0,YEAR(TbRegistroEntradas[[#This Row],[Data do Caixa Previsto]])) -> 2018 | O57: =IF(AND(TbRegistroEntradas[[#This Row],[Data do Caixa Previsto]]<TODAY(),TbRegistroEntradas[[#This Row],[Data do Caixa Realizado]]=""),"Vencida","Não Vencida") -> Não Vencida | P57: =IF(TbRegistroEntradas[[#This Row],[Data da Competência]]=TbRegistroEntradas[[#This Row],[Data do Caixa Previsto]],"Vista","Prazo") -> Vista | Q57: =IF(TbRegistroEntradas[[#This Row],[Data do Caixa Realizado]]<>"", IF(TbRegistroEntradas[[#This Row],[Data do Caixa Realizado]]>TbRegistroEntradas[[#This Row],[Data do Caixa Previsto]], TbRegistroEntradas[[#This Row],[Data do Caixa Realizado]]-TbRegistroEntradas[[#This Row],[Data do Caixa Previsto]], 0 ), IF(TODAY()>TbRegistroEntradas[[#This Row],[Data do Caixa Previsto]], TODAY()-TbRegistroEntradas[[#This Row],[Data do Caixa Previsto]], 0 ) ) -> 0
B58: 43166 | C58: 43121 | D58: 43166 | E58: Vendas de mercadorias | F58: Som e imagem | G58: NF3336 | H58: 783 | I58: =IF(TbRegistroEntradas[[#This Row],[Data do Caixa Realizado]]="",0,MONTH(TbRegistroEntradas[[#This Row],[Data do Caixa Realizado]])) -> 3 | J58: =IF(TbRegistroEntradas[[#This Row],[Data do Caixa Realizado]]="",0,YEAR(TbRegistroEntradas[[#This Row],[Data do Caixa Realizado]])) -> 2018 | K58: =IF(TbRegistroEntradas[[#This Row],[Data da Competência]]="",0,MONTH(TbRegistroEntradas[[#This Row],[Data da Competência]])) -> 1 | L58: =IF(TbRegistroEntradas[[#This Row],[Data da Competência]]="",0,YEAR(TbRegistroEntradas[[#This Row],[Data da Competência]])) -> 2018 | M58: =IF(TbRegistroEntradas[[#This Row],[Data do Caixa Previsto]]="",0,MONTH(TbRegistroEntradas[[#This Row],[Data do Caixa Previsto]])) -> 3 | N58: =IF(TbRegistroEntradas[[#This Row],[Data do Caixa Previsto]]="",0,YEAR(TbRegistroEntradas[[#This Row],[Data do Caixa Previsto]])) -> 2018 | O58: =IF(AND(TbRegistroEntradas[[#This Row],[Data do Caixa Previsto]]<TODAY(),TbRegistroEntradas[[#This Row],[Data do Caixa Realizado]]=""),"Vencida","Não Vencida") -> Não Vencida | P58: =IF(TbRegistroEntradas[[#This Row],[Data da Competência]]=TbRegistroEntradas[[#This Row],[Data do Caixa Previsto]],"Vista","Prazo") -> Prazo | Q58: =IF(TbRegistroEntradas[[#This Row],[Data do Caixa Realizado]]<>"", IF(TbRegistroEntradas[[#This Row],[Data do Caixa Realizado]]>TbRegistroEntradas[[#This Row],[Data do Caixa Previsto]], TbRegistroEntradas[[#This Row],[Data do Caixa Realizado]]-TbRegistroEntradas[[#This Row],[Data do Caixa Previsto]], 0 ), IF(TODAY()>TbRegistroEntradas[[#This Row],[Data do Caixa Previsto]], TODAY()-TbRegistroEntradas[[#This Row],[Data do Caixa Previsto]], 0 ) ) -> 0
B59: 43145 | C59: 43122 | D59: 43145 | E59: Vendas de mercadorias | F59: Som e imagem | G59: NF7526 | H59: 3928 | I59: =IF(TbRegistroEntradas[[#This Row],[Data do Caixa Realizado]]="",0,MONTH(TbRegistroEntradas[[#This Row],[Data do Caixa Realizado]])) -> 2 | J59: =IF(TbRegistroEntradas[[#This Row],[Data do Caixa Realizado]]="",0,YEAR(TbRegistroEntradas[[#This Row],[Data do Caixa Realizado]])) -> 2018 | K59: =IF(TbRegistroEntradas[[#This Row],[Data da Competência]]="",0,MONTH(TbRegistroEntradas[[#This Row],[Data da Competência]])) -> 1 | L59: =IF(TbRegistroEntradas[[#This Row],[Data da Competência]]="",0,YEAR(TbRegistroEntradas[[#This Row],[Data da Competência]])) -> 2018 | M59: =IF(TbRegistroEntradas[[#This Row],[Data do Caixa Previsto]]="",0,MONTH(TbRegistroEntradas[[#This Row],[Data do Caixa Previsto]])) -> 2 | N59: =IF(TbRegistroEntradas[[#This Row],[Data do Caixa Previsto]]="",0,YEAR(TbRegistroEntradas[[#This Row],[Data do Caixa Previsto]])) -> 2018 | O59: =IF(AND(TbRegistroEntradas[[#This Row],[Data do Caixa Previsto]]<TODAY(),TbRegistroEntradas[[#This Row],[Data do Caixa Realizado]]=""),"Vencida","Não Vencida") -> Não Vencida | P59: =IF(TbRegistroEntradas[[#This Row],[Data da Competência]]=TbRegistroEntradas[[#This Row],[Data do Caixa Previsto]],"Vista","Prazo") -> Prazo | Q59: =IF(TbRegistroEntradas[[#This Row],[Data do Caixa Realizado]]<>"", IF(TbRegistroEntradas[[#This Row],[Data do Caixa Realizado]]>TbRegistroEntradas[[#This Row],[Data do Caixa Previsto]], TbRegistroEntradas[[#This Row],[Data do Caixa Realizado]]-TbRegistroEntradas[[#This Row],[Data do Caixa Previsto]], 0 ), IF(TODAY()>TbRegistroEntradas[[#This Row],[Data do Caixa Previsto]], TODAY()-TbRegistroEntradas[[#This Row],[Data do Caixa Previsto]], 0 ) ) -> 0
B60: 43142 | C60: 43124 | D60: 43142 | E60: Vendas de mercadorias | F60: Informática | G60: NF3023 | H60: 3843 | I60: =IF(TbRegistroEntradas[[#This Row],[Data do Caixa Realizado]]="",0,MONTH(TbRegistroEntradas[[#This Row],[Data do Caixa Realizado]])) -> 2 | J60: =IF(TbRegistroEntradas[[#This Row],[Data do Caixa Realizado]]="",0,YEAR(TbRegistroEntradas[[#This Row],[Data do Caixa Realizado]])) -> 2018 | K60: =IF(TbRegistroEntradas[[#This Row],[Data da Competência]]="",0,MONTH(TbRegistroEntradas[[#This Row],[Data da Competência]])) -> 1 | L60: =IF(TbRegistroEntradas[[#This Row],[Data da Competência]]="",0,YEAR(TbRegistroEntradas[[#This Row],[Data da Competência]])) -> 2018 | M60: =IF(TbRegistroEntradas[[#This Row],[Data do Caixa Previsto]]="",0,MONTH(TbRegistroEntradas[[#This Row],[Data do Caixa Previsto]])) -> 2 | N60: =IF(TbRegistroEntradas[[#This Row],[Data do Caixa Previsto]]="",0,YEAR(TbRegistroEntradas[[#This Row],[Data do Caixa Previsto]])) -> 2018 | O60: =IF(AND(TbRegistroEntradas[[#This Row],[Data do Caixa Previsto]]<TODAY(),TbRegistroEntradas[[#This Row],[Data do Caixa Realizado]]=""),"Vencida","Não Vencida") -> Não Vencida | P60: =IF(TbRegistroEntradas[[#This Row],[Data da Competência]]=TbRegistroEntradas[[#This Row],[Data do Caixa Previsto]],"Vista","Prazo") -> Prazo | Q60: =IF(TbRegistroEntradas[[#This Row],[Data do Caixa Realizado]]<>"", IF(TbRegistroEntradas[[#This Row],[Data do Caixa Realizado]]>TbRegistroEntradas[[#This Row],[Data do Caixa Previsto]], TbRegistroEntradas[[#This Row],[Data do Caixa Realizado]]-TbRegistroEntradas[[#This Row],[Data do Caixa Previsto]], 0 ), IF(TODAY()>TbRegistroEntradas[[#This Row],[Data do Caixa Previsto]], TODAY()-TbRegistroEntradas[[#This Row],[Data do Caixa Previsto]], 0 ) ) -> 0
B61: 43206 | C61: 43125 | D61: 43129 | E61: Vendas de mercadorias | F61: Eletrodomésticos | G61: NF7934 | H61: 1864 | I61: =IF(TbRegistroEntradas[[#This Row],[Data do Caixa Realizado]]="",0,MONTH(TbRegistroEntradas[[#This Row],[Data do Caixa Realizado]])) -> 4 | J61: =IF(TbRegistroEntradas[[#This Row],[Data do Caixa Realizado]]="",0,YEAR(TbRegistroEntradas[[#This Row],[Data do Caixa Realizado]])) -> 2018 | K61: =IF(TbRegistroEntradas[[#This Row],[Data da Competência]]="",0,MONTH(TbRegistroEntradas[[#This Row],[Data da Competência]])) -> 1 | L61: =IF(TbRegistroEntradas[[#This Row],[Data da Competência]]="",0,YEAR(TbRegistroEntradas[[#This Row],[Data da Competência]])) -> 2018 | M61: =IF(TbRegistroEntradas[[#This Row],[Data do Caixa Previsto]]="",0,MONTH(TbRegistroEntradas[[#This Row],[Data do Caixa Previsto]])) -> 1 | N61: =IF(TbRegistroEntradas[[#This Row],[Data do Caixa Previsto]]="",0,YEAR(TbRegistroEntradas[[#This Row],[Data do Caixa Previsto]])) -> 2018 | O61: =IF(AND(TbRegistroEntradas[[#This Row],[Data do Caixa Previsto]]<TODAY(),TbRegistroEntradas[[#This Row],[Data do Caixa Realizado]]=""),"Vencida","Não Vencida") -> Não Vencida | P61: =IF(TbRegistroEntradas[[#This Row],[Data da Competência]]=TbRegistroEntradas[[#This Row],[Data do Caixa Previsto]],"Vista","Prazo") -> Prazo | Q61: =IF(TbRegistroEntradas[[#This Row],[Data do Caixa Realizado]]<>"", IF(TbRegistroEntradas[[#This Row],[Data do Caixa Realizado]]>TbRegistroEntradas[[#This Row],[Data do Caixa Previsto]], TbRegistroEntradas[[#This Row],[Data do Caixa Realizado]]-TbRegistroEntradas[[#This Row],[Data do Caixa Previsto]], 0 ), IF(TODAY()>TbRegistroEntradas[[#This Row],[Data do Caixa Previsto]], TODAY()-TbRegistroEntradas[[#This Row],[Data do Caixa Previsto]], 0 ) ) -> 77
B62: 43137 | C62: 43128 | D62: 43128 | E62: Vendas de mercadorias | F62: Móveis | G62: NF7720 | H62: 1184 | I62: =IF(TbRegistroEntradas[[#This Row],[Data do Caixa Realizado]]="",0,MONTH(TbRegistroEntradas[[#This Row],[Data do Caixa Realizado]])) -> 2 | J62: =IF(TbRegistroEntradas[[#This Row],[Data do Caixa Realizado]]="",0,YEAR(TbRegistroEntradas[[#This Row],[Data do Caixa Realizado]])) -> 2018 | K62: =IF(TbRegistroEntradas[[#This Row],[Data da Competência]]="",0,MONTH(TbRegistroEntradas[[#This Row],[Data da Competência]])) -> 1 | L62: =IF(TbRegistroEntradas[[#This Row],[Data da Competência]]="",0,YEAR(TbRegistroEntradas[[#This Row],[Data da Competência]])) -> 2018 | M62: =IF(TbRegistroEntradas[[#This Row],[Data do Caixa Previsto]]="",0,MONTH(TbRegistroEntradas[[#This Row],[Data do Caixa Previsto]])) -> 1 | N62: =IF(TbRegistroEntradas[[#This Row],[Data do Caixa Previsto]]="",0,YEAR(TbRegistroEntradas[[#This Row],[Data do Caixa Previsto]])) -> 2018 | O62: =IF(AND(TbRegistroEntradas[[#This Row],[Data do Caixa Previsto]]<TODAY(),TbRegistroEntradas[[#This Row],[Data do Caixa Realizado]]=""),"Vencida","Não Vencida") -> Não Vencida | P62: =IF(TbRegistroEntradas[[#This Row],[Data da Competência]]=TbRegistroEntradas[[#This Row],[Data do Caixa Previsto]],"Vista","Prazo") -> Vista | Q62: =IF(TbRegistroEntradas[[#This Row],[Data do Caixa Realizado]]<>"", IF(TbRegistroEntradas[[#This Row],[Data do Caixa Realizado]]>TbRegistroEntradas[[#This Row],[Data do Caixa Previsto]], TbRegistroEntradas[[#This Row],[Data do Caixa Realizado]]-TbRegistroEntradas[[#This Row],[Data do Caixa Previsto]], 0 ), IF(TODAY()>TbRegistroEntradas[[#This Row],[Data do Caixa Previsto]], TODAY()-TbRegistroEntradas[[#This Row],[Data do Caixa Previsto]], 0 ) ) -> 9
B63: 43161 | C63: 43129 | D63: 43161 | E63: Vendas de mercadorias | F63: Móveis | G63: NF2719 | H63: 4055 | I63: =IF(TbRegistroEntradas[[#This Row],[Data do Caixa Realizado]]="",0,MONTH(TbRegistroEntradas[[#This Row],[Data do Caixa Realizado]])) -> 3 | J63: =IF(TbRegistroEntradas[[#This Row],[Data do Caixa Realizado]]="",0,YEAR(TbRegistroEntradas[[#This Row],[Data do Caixa Realizado]])) -> 2018 | K63: =IF(TbRegistroEntradas[[#This Row],[Data da Competência]]="",0,MONTH(TbRegistroEntradas[[#This Row],[Data da Competência]])) -> 1 | L63: =IF(TbRegistroEntradas[[#This Row],[Data da Competência]]="",0,YEAR(TbRegistroEntradas[[#This Row],[Data da Competência]])) -> 2018 | M63: =IF(TbRegistroEntradas[[#This Row],[Data do Caixa Previsto]]="",0,MONTH(TbRegistroEntradas[[#This Row],[Data do Caixa Previsto]])) -> 3 | N63: =IF(TbRegistroEntradas[[#This Row],[Data do Caixa Previsto]]="",0,YEAR(TbRegistroEntradas[[#This Row],[Data do Caixa Previsto]])) -> 2018 | O63: =IF(AND(TbRegistroEntradas[[#This Row],[Data do Caixa Previsto]]<TODAY(),TbRegistroEntradas[[#This Row],[Data do Caixa Realizado]]=""),"Vencida","Não Vencida") -> Não Vencida | P63: =IF(TbRegistroEntradas[[#This Row],[Data da Competência]]=TbRegistroEntradas[[#This Row],[Data do Caixa Previsto]],"Vista","Prazo") -> Prazo | Q63: =IF(TbRegistroEntradas[[#This Row],[Data do Caixa Realizado]]<>"", IF(TbRegistroEntradas[[#This Row],[Data do Caixa Realizado]]>TbRegistroEntradas[[#This Row],[Data do Caixa Previsto]], TbRegistroEntradas[[#This Row],[Data do Caixa Realizado]]-TbRegistroEntradas[[#This Row],[Data do Caixa Previsto]], 0 ), IF(TODAY()>TbRegistroEntradas[[#This Row],[Data do Caixa Previsto]], TODAY()-TbRegistroEntradas[[#This Row],[Data do Caixa Previsto]], 0 ) ) -> 0
B64: 43178 | C64: 43130 | D64: 43178 | E64: Vendas de mercadorias | F64: Móveis | G64: NF3036 | H64: 427 | I64: =IF(TbRegistroEntradas[[#This Row],[Data do Caixa Realizado]]="",0,MONTH(TbRegistroEntradas[[#This Row],[Data do Caixa Realizado]])) -> 3 | J64: =IF(TbRegistroEntradas[[#This Row],[Data do Caixa Realizado]]="",0,YEAR(TbRegistroEntradas[[#This Row],[Data do Caixa Realizado]])) -> 2018 | K64: =IF(TbRegistroEntradas[[#This Row],[Data da Competência]]="",0,MONTH(TbRegistroEntradas[[#This Row],[Data da Competência]])) -> 1 | L64: =IF(TbRegistroEntradas[[#This Row],[Data da Competência]]="",0,YEAR(TbRegistroEntradas[[#This Row],[Data da Competência]])) -> 2018 | M64: =IF(TbRegistroEntradas[[#This Row],[Data do Caixa Previsto]]="",0,MONTH(TbRegistroEntradas[[#This Row],[Data do Caixa Previsto]])) -> 3 | N64: =IF(TbRegistroEntradas[[#This Row],[Data do Caixa Previsto]]="",0,YEAR(TbRegistroEntradas[[#This Row],[Data do Caixa Previsto]])) -> 2018 | O64: =IF(AND(TbRegistroEntradas[[#This Row],[Data do Caixa Previsto]]<TODAY(),TbRegistroEntradas[[#This Row],[Data do Caixa Realizado]]=""),"Vencida","Não Vencida") -> Não Vencida | P64: =IF(TbRegistroEntradas[[#This Row],[Data da Competência]]=TbRegistroEntradas[[#This Row],[Data do Caixa Previsto]],"Vista","Prazo") -> Prazo | Q64: =IF(TbRegistroEntradas[[#This Row],[Data do Caixa Realizado]]<>"", IF(TbRegistroEntradas[[#This Row],[Data do Caixa Realizado]]>TbRegistroEntradas[[#This Row],[Data do Caixa Previsto]], TbRegistroEntradas[[#This Row],[Data do Caixa Realizado]]-TbRegistroEntradas[[#This Row],[Data do Caixa Previsto]], 0 ), IF(TODAY()>TbRegistroEntradas[[#This Row],[Data do Caixa Previsto]], TODAY()-TbRegistroEntradas[[#This Row],[Data do Caixa Previsto]], 0 ) ) -> 0
B65: 43138 | C65: 43133 | D65: 43138 | E65: Vendas de mercadorias | F65: Livros | G65: NF4604 | H65: 460 | I65: =IF(TbRegistroEntradas[[#This Row],[Data do Caixa Realizado]]="",0,MONTH(TbRegistroEntradas[[#This Row],[Data do Caixa Realizado]])) -> 2 | J65: =IF(TbRegistroEntradas[[#This Row],[Data do Caixa Realizado]]="",0,YEAR(TbRegistroEntradas[[#This Row],[Data do Caixa Realizado]])) -> 2018 | K65: =IF(TbRegistroEntradas[[#This Row],[Data da Competência]]="",0,MONTH(TbRegistroEntradas[[#This Row],[Data da Competência]])) -> 2 | L65: =IF(TbRegistroEntradas[[#This Row],[Data da Competência]]="",0,YEAR(TbRegistroEntradas[[#This Row],[Data da Competência]])) -> 2018 | M65: =IF(TbRegistroEntradas[[#This Row],[Data do Caixa Previsto]]="",0,MONTH(TbRegistroEntradas[[#This Row],[Data do Caixa Previsto]])) -> 2 | N65: =IF(TbRegistroEntradas[[#This Row],[Data do Caixa Previsto]]="",0,YEAR(TbRegistroEntradas[[#This Row],[Data do Caixa Previsto]])) -> 2018 | O65: =IF(AND(TbRegistroEntradas[[#This Row],[Data do Caixa Previsto]]<TODAY(),TbRegistroEntradas[[#This Row],[Data do Caixa Realizado]]=""),"Vencida","Não Vencida") -> Não Vencida | P65: =IF(TbRegistroEntradas[[#This Row],[Data da Competência]]=TbRegistroEntradas[[#This Row],[Data do Caixa Previsto]],"Vista","Prazo") -> Prazo | Q65: =IF(TbRegistroEntradas[[#This Row],[Data do Caixa Realizado]]<>"", IF(TbRegistroEntradas[[#This Row],[Data do Caixa Realizado]]>TbRegistroEntradas[[#This Row],[Data do Caixa Previsto]], TbRegistroEntradas[[#This Row],[Data do Caixa Realizado]]-TbRegistroEntradas[[#This Row],[Data do Caixa Previsto]], 0 ), IF(TODAY()>TbRegistroEntradas[[#This Row],[Data do Caixa Previsto]], TODAY()-TbRegistroEntradas[[#This Row],[Data do Caixa Previsto]], 0 ) ) -> 0
C66: 43136 | D66: 43190 | E66: Vendas de mercadorias | F66: Som e imagem | G66: NF2493 | H66: 964 | I66: =IF(TbRegistroEntradas[[#This Row],[Data do Caixa Realizado]]="",0,MONTH(TbRegistroEntradas[[#This Row],[Data do Caixa Realizado]])) -> 0 | J66: =IF(TbRegistroEntradas[[#This Row],[Data do Caixa Realizado]]="",0,YEAR(TbRegistroEntradas[[#This Row],[Data do Caixa Realizado]])) -> 0 | K66: =IF(TbRegistroEntradas[[#This Row],[Data da Competência]]="",0,MONTH(TbRegistroEntradas[[#This Row],[Data da Competência]])) -> 2 | L66: =IF(TbRegistroEntradas[[#This Row],[Data da Competência]]="",0,YEAR(TbRegistroEntradas[[#This Row],[Data da Competência]])) -> 2018 | M66: =IF(TbRegistroEntradas[[#This Row],[Data do Caixa Previsto]]="",0,MONTH(TbRegistroEntradas[[#This Row],[Data do Caixa Previsto]])) -> 3 | N66: =IF(TbRegistroEntradas[[#This Row],[Data do Caixa Previsto]]="",0,YEAR(TbRegistroEntradas[[#This Row],[Data do Caixa Previsto]])) -> 2018 | O66: =IF(AND(TbRegistroEntradas[[#This Row],[Data do Caixa Previsto]]<TODAY(),TbRegistroEntradas[[#This Row],[Data do Caixa Realizado]]=""),"Vencida","Não Vencida") -> Vencida | P66: =IF(TbRegistroEntradas[[#This Row],[Data da Competência]]=TbRegistroEntradas[[#This Row],[Data do Caixa Previsto]],"Vista","Prazo") -> Prazo | Q66: =IF(TbRegistroEntradas[[#This Row],[Data do Caixa Realizado]]<>"", IF(TbRegistroEntradas[[#This Row],[Data do Caixa Realizado]]>TbRegistroEntradas[[#This Row],[Data do Caixa Previsto]], TbRegistroEntradas[[#This Row],[Data do Caixa Realizado]]-TbRegistroEntradas[[#This Row],[Data do Caixa Previsto]], 0 ), IF(TODAY()>TbRegistroEntradas[[#This Row],[Data do Caixa Previsto]], TODAY()-TbRegistroEntradas[[#This Row],[Data do Caixa Previsto]], 0 ) ) -> 2163
B67: 43145 | C67: 43140 | D67: 43145 | E67: Vendas de mercadorias | F67: Móveis | G67: NF5788 | H67: 3412 | I67: =IF(TbRegistroEntradas[[#This Row],[Data do Caixa Realizado]]="",0,MONTH(TbRegistroEntradas[[#This Row],[Data do Caixa Realizado]])) -> 2 | J67: =IF(TbRegistroEntradas[[#This Row],[Data do Caixa Realizado]]="",0,YEAR(TbRegistroEntradas[[#This Row],[Data do Caixa Realizado]])) -> 2018 | K67: =IF(TbRegistroEntradas[[#This Row],[Data da Competência]]="",0,MONTH(TbRegistroEntradas[[#This Row],[Data da Competência]])) -> 2 | L67: =IF(TbRegistroEntradas[[#This Row],[Data da Competência]]="",0,YEAR(TbRegistroEntradas[[#This Row],[Data da Competência]])) -> 2018 | M67: =IF(TbRegistroEntradas[[#This Row],[Data do Caixa Previsto]]="",0,MONTH(TbRegistroEntradas[[#This Row],[Data do Caixa Previsto]])) -> 2 | N67: =IF(TbRegistroEntradas[[#This Row],[Data do Caixa Previsto]]="",0,YEAR(TbRegistroEntradas[[#This Row],[Data do Caixa Previsto]])) -> 2018 | O67: =IF(AND(TbRegistroEntradas[[#This Row],[Data do Caixa Previsto]]<TODAY(),TbRegistroEntradas[[#This Row],[Data do Caixa Realizado]]=""),"Vencida","Não Vencida") -> Não Vencida | P67: =IF(TbRegistroEntradas[[#This Row],[Data da Competência]]=TbRegistroEntradas[[#This Row],[Data do Caixa Previsto]],"Vista","Prazo") -> Prazo | Q67: =IF(TbRegistroEntradas[[#This Row],[Data do Caixa Realizado]]<>"", IF(TbRegistroEntradas[[#This Row],[Data do Caixa Realizado]]>TbRegistroEntradas[[#This Row],[Data do Caixa Previsto]], TbRegistroEntradas[[#This Row],[Data do Caixa Realizado]]-TbRegistroEntradas[[#This Row],[Data do Caixa Previsto]], 0 ), IF(TODAY()>TbRegistroEntradas[[#This Row],[Data do Caixa Previsto]], TODAY()-TbRegistroEntradas[[#This Row],[Data do Caixa Previsto]], 0 ) ) -> 0
B68: 43146 | C68: 43142 | D68: 43146 | E68: Vendas de mercadorias | F68: Informática | G68: NF9580 | H68: 3095 | I68: =IF(TbRegistroEntradas[[#This Row],[Data do Caixa Realizado]]="",0,MONTH(TbRegistroEntradas[[#This Row],[Data do Caixa Realizado]])) -> 2 | J68: =IF(TbRegistroEntradas[[#This Row],[Data do Caixa Realizado]]="",0,YEAR(TbRegistroEntradas[[#This Row],[Data do Caixa Realizado]])) -> 2018 | K68: =IF(TbRegistroEntradas[[#This Row],[Data da Competência]]="",0,MONTH(TbRegistroEntradas[[#This Row],[Data da Competência]])) -> 2 | L68: =IF(TbRegistroEntradas[[#This Row],[Data da Competência]]="",0,YEAR(TbRegistroEntradas[[#This Row],[Data da Competência]])) -> 2018 | M68: =IF(TbRegistroEntradas[[#This Row],[Data do Caixa Previsto]]="",0,MONTH(TbRegistroEntradas[[#This Row],[Data do Caixa Previsto]])) -> 2 | N68: =IF(TbRegistroEntradas[[#This Row],[Data do Caixa Previsto]]="",0,YEAR(TbRegistroEntradas[[#This Row],[Data do Caixa Previsto]])) -> 2018 | O68: =IF(AND(TbRegistroEntradas[[#This Row],[Data do Caixa Previsto]]<TODAY(),TbRegistroEntradas[[#This Row],[Data do Caixa Realizado]]=""),"Vencida","Não Vencida") -> Não Vencida | P68: =IF(TbRegistroEntradas[[#This Row],[Data da Competência]]=TbRegistroEntradas[[#This Row],[Data do Caixa Previsto]],"Vista","Prazo") -> Prazo | Q68: =IF(TbRegistroEntradas[[#This Row],[Data do Caixa Realizado]]<>"", IF(TbRegistroEntradas[[#This Row],[Data do Caixa Realizado]]>TbRegistroEntradas[[#This Row],[Data do Caixa Previsto]], TbRegistroEntradas[[#This Row],[Data do Caixa Realizado]]-TbRegistroEntradas[[#This Row],[Data do Caixa Previsto]], 0 ), IF(TODAY()>TbRegistroEntradas[[#This Row],[Data do Caixa Previsto]], TODAY()-TbRegistroEntradas[[#This Row],[Data do Caixa Previsto]], 0 ) ) -> 0
B69: 43193 | C69: 43148 | D69: 43193 | E69: Vendas de mercadorias | F69: Livros | G69: NF4061 | H69: 1532 | I69: =IF(TbRegistroEntradas[[#This Row],[Data do Caixa Realizado]]="",0,MONTH(TbRegistroEntradas[[#This Row],[Data do Caixa Realizado]])) -> 4 | J69: =IF(TbRegistroEntradas[[#This Row],[Data do Caixa Realizado]]="",0,YEAR(TbRegistroEntradas[[#This Row],[Data do Caixa Realizado]])) -> 2018 | K69: =IF(TbRegistroEntradas[[#This Row],[Data da Competência]]="",0,MONTH(TbRegistroEntradas[[#This Row],[Data da Competência]])) -> 2 | L69: =IF(TbRegistroEntradas[[#This Row],[Data da Competência]]="",0,YEAR(TbRegistroEntradas[[#This Row],[Data da Competência]])) -> 2018 | M69: =IF(TbRegistroEntradas[[#This Row],[Data do Caixa Previsto]]="",0,MONTH(TbRegistroEntradas[[#This Row],[Data do Caixa Previsto]])) -> 4 | N69: =IF(TbRegistroEntradas[[#This Row],[Data do Caixa Previsto]]="",0,YEAR(TbRegistroEntradas[[#This Row],[Data do Caixa Previsto]])) -> 2018 | O69: =IF(AND(TbRegistroEntradas[[#This Row],[Data do Caixa Previsto]]<TODAY(),TbRegistroEntradas[[#This Row],[Data do Caixa Realizado]]=""),"Vencida","Não Vencida") -> Não Vencida | P69: =IF(TbRegistroEntradas[[#This Row],[Data da Competência]]=TbRegistroEntradas[[#This Row],[Data do Caixa Previsto]],"Vista","Prazo") -> Prazo | Q69: =IF(TbRegistroEntradas[[#This Row],[Data do Caixa Realizado]]<>"", IF(TbRegistroEntradas[[#This Row],[Data do Caixa Realizado]]>TbRegistroEntradas[[#This Row],[Data do Caixa Previsto]], TbRegistroEntradas[[#This Row],[Data do Caixa Realizado]]-TbRegistroEntradas[[#This Row],[Data do Caixa Previsto]], 0 ), IF(TODAY()>TbRegistroEntradas[[#This Row],[Data do Caixa Previsto]], TODAY()-TbRegistroEntradas[[#This Row],[Data do Caixa Previsto]], 0 ) ) -> 0
B70: 43193 | C70: 43151 | D70: 43193 | E70: Vendas de mercadorias | F70: Livros | G70: NF6503 | H70: 3726 | I70: =IF(TbRegistroEntradas[[#This Row],[Data do Caixa Realizado]]="",0,MONTH(TbRegistroEntradas[[#This Row],[Data do Caixa Realizado]])) -> 4 | J70: =IF(TbRegistroEntradas[[#This Row],[Data do Caixa Realizado]]="",0,YEAR(TbRegistroEntradas[[#This Row],[Data do Caixa Realizado]])) -> 2018 | K70: =IF(TbRegistroEntradas[[#This Row],[Data da Competência]]="",0,MONTH(TbRegistroEntradas[[#This Row],[Data da Competência]])) -> 2 | L70: =IF(TbRegistroEntradas[[#This Row],[Data da Competência]]="",0,YEAR(TbRegistroEntradas[[#This Row],[Data da Competência]])) -> 2018 | M70: =IF(TbRegistroEntradas[[#This Row],[Data do Caixa Previsto]]="",0,MONTH(TbRegistroEntradas[[#This Row],[Data do Caixa Previsto]])) -> 4 | N70: =IF(TbRegistroEntradas[[#This Row],[Data do Caixa Previsto]]="",0,YEAR(TbRegistroEntradas[[#This Row],[Data do Caixa Previsto]])) -> 2018 | O70: =IF(AND(TbRegistroEntradas[[#This Row],[Data do Caixa Previsto]]<TODAY(),TbRegistroEntradas[[#This Row],[Data do Caixa Realizado]]=""),"Vencida","Não Vencida") -> Não Vencida | P70: =IF(TbRegistroEntradas[[#This Row],[Data da Competência]]=TbRegistroEntradas[[#This Row],[Data do Caixa Previsto]],"Vista","Prazo") -> Prazo | Q70: =IF(TbRegistroEntradas[[#This Row],[Data do Caixa Realizado]]<>"", IF(TbRegistroEntradas[[#This Row],[Data do Caixa Realizado]]>TbRegistroEntradas[[#This Row],[Data do Caixa Previsto]], TbRegistroEntradas[[#This Row],[Data do Caixa Realizado]]-TbRegistroEntradas[[#This Row],[Data do Caixa Previsto]], 0 ), IF(TODAY()>TbRegistroEntradas[[#This Row],[Data do Caixa Previsto]], TODAY()-TbRegistroEntradas[[#This Row],[Data do Caixa Previsto]], 0 ) ) -> 0
B71: 43154 | C71: 43154 | D71: 43154 | E71: Vendas de mercadorias | F71: Móveis | G71: NF6701 | H71: 4322 | I71: =IF(TbRegistroEntradas[[#This Row],[Data do Caixa Realizado]]="",0,MONTH(TbRegistroEntradas[[#This Row],[Data do Caixa Realizado]])) -> 2 | J71: =IF(TbRegistroEntradas[[#This Row],[Data do Caixa Realizado]]="",0,YEAR(TbRegistroEntradas[[#This Row],[Data do Caixa Realizado]])) -> 2018 | K71: =IF(TbRegistroEntradas[[#This Row],[Data da Competência]]="",0,MONTH(TbRegistroEntradas[[#This Row],[Data da Competência]])) -> 2 | L71: =IF(TbRegistroEntradas[[#This Row],[Data da Competência]]="",0,YEAR(TbRegistroEntradas[[#This Row],[Data da Competência]])) -> 2018 | M71: =IF(TbRegistroEntradas[[#This Row],[Data do Caixa Previsto]]="",0,MONTH(TbRegistroEntradas[[#This Row],[Data do Caixa Previsto]])) -> 2 | N71: =IF(TbRegistroEntradas[[#This Row],[Data do Caixa Previsto]]="",0,YEAR(TbRegistroEntradas[[#This Row],[Data do Caixa Previsto]])) -> 2018 | O71: =IF(AND(TbRegistroEntradas[[#This Row],[Data do Caixa Previsto]]<TODAY(),TbRegistroEntradas[[#This Row],[Data do Caixa Realizado]]=""),"Vencida","Não Vencida") -> Não Vencida | P71: =IF(TbRegistroEntradas[[#This Row],[Data da Competência]]=TbRegistroEntradas[[#This Row],[Data do Caixa Previsto]],"Vista","Prazo") -> Vista | Q71: =IF(TbRegistroEntradas[[#This Row],[Data do Caixa Realizado]]<>"", IF(TbRegistroEntradas[[#This Row],[Data do Caixa Realizado]]>TbRegistroEntradas[[#This Row],[Data do Caixa Previsto]], TbRegistroEntradas[[#This Row],[Data do Caixa Realizado]]-TbRegistroEntradas[[#This Row],[Data do Caixa Previsto]], 0 ), IF(TODAY()>TbRegistroEntradas[[#This Row],[Data do Caixa Previsto]], TODAY()-TbRegistroEntradas[[#This Row],[Data do Caixa Previsto]], 0 ) ) -> 0
C72: 43156 | D72: 43205 | E72: Vendas de mercadorias | F72: Informática | G72: NF8891 | H72: 3998 | I72: =IF(TbRegistroEntradas[[#This Row],[Data do Caixa Realizado]]="",0,MONTH(TbRegistroEntradas[[#This Row],[Data do Caixa Realizado]])) -> 0 | J72: =IF(TbRegistroEntradas[[#This Row],[Data do Caixa Realizado]]="",0,YEAR(TbRegistroEntradas[[#This Row],[Data do Caixa Realizado]])) -> 0 | K72: =IF(TbRegistroEntradas[[#This Row],[Data da Competência]]="",0,MONTH(TbRegistroEntradas[[#This Row],[Data da Competência]])) -> 2 | L72: =IF(TbRegistroEntradas[[#This Row],[Data da Competência]]="",0,YEAR(TbRegistroEntradas[[#This Row],[Data da Competência]])) -> 2018 | M72: =IF(TbRegistroEntradas[[#This Row],[Data do Caixa Previsto]]="",0,MONTH(TbRegistroEntradas[[#This Row],[Data do Caixa Previsto]])) -> 4 | N72: =IF(TbRegistroEntradas[[#This Row],[Data do Caixa Previsto]]="",0,YEAR(TbRegistroEntradas[[#This Row],[Data do Caixa Previsto]])) -> 2018 | O72: =IF(AND(TbRegistroEntradas[[#This Row],[Data do Caixa Previsto]]<TODAY(),TbRegistroEntradas[[#This Row],[Data do Caixa Realizado]]=""),"Vencida","Não Vencida") -> Vencida | P72: =IF(TbRegistroEntradas[[#This Row],[Data da Competência]]=TbRegistroEntradas[[#This Row],[Data do Caixa Previsto]],"Vista","Prazo") -> Prazo | Q72: =IF(TbRegistroEntradas[[#This Row],[Data do Caixa Realizado]]<>"", IF(TbRegistroEntradas[[#This Row],[Data do Caixa Realizado]]>TbRegistroEntradas[[#This Row],[Data do Caixa Previsto]], TbRegistroEntradas[[#This Row],[Data do Caixa Realizado]]-TbRegistroEntradas[[#This Row],[Data do Caixa Previsto]], 0 ), IF(TODAY()>TbRegistroEntradas[[#This Row],[Data do Caixa Previsto]], TODAY()-TbRegistroEntradas[[#This Row],[Data do Caixa Previsto]], 0 ) ) -> 2148
B73: 43246 | C73: 43158 | D73: 43188 | E73: Vendas de mercadorias | F73: Informática | G73: NF2640 | H73: 3252 | I73: =IF(TbRegistroEntradas[[#This Row],[Data do Caixa Realizado]]="",0,MONTH(TbRegistroEntradas[[#This Row],[Data do Caixa Realizado]])) -> 5 | J73: =IF(TbRegistroEntradas[[#This Row],[Data do Caixa Realizado]]="",0,YEAR(TbRegistroEntradas[[#This Row],[Data do Caixa Realizado]])) -> 2018 | K73: =IF(TbRegistroEntradas[[#This Row],[Data da Competência]]="",0,MONTH(TbRegistroEntradas[[#This Row],[Data da Competência]])) -> 2 | L73: =IF(TbRegistroEntradas[[#This Row],[Data da Competência]]="",0,YEAR(TbRegistroEntradas[[#This Row],[Data da Competência]])) -> 2018 | M73: =IF(TbRegistroEntradas[[#This Row],[Data do Caixa Previsto]]="",0,MONTH(TbRegistroEntradas[[#This Row],[Data do Caixa Previsto]])) -> 3 | N73: =IF(TbRegistroEntradas[[#This Row],[Data do Caixa Previsto]]="",0,YEAR(TbRegistroEntradas[[#This Row],[Data do Caixa Previsto]])) -> 2018 | O73: =IF(AND(TbRegistroEntradas[[#This Row],[Data do Caixa Previsto]]<TODAY(),TbRegistroEntradas[[#This Row],[Data do Caixa Realizado]]=""),"Vencida","Não Vencida") -> Não Vencida | P73: =IF(TbRegistroEntradas[[#This Row],[Data da Competência]]=TbRegistroEntradas[[#This Row],[Data do Caixa Previsto]],"Vista","Prazo") -> Prazo | Q73: =IF(TbRegistroEntradas[[#This Row],[Data do Caixa Realizado]]<>"", IF(TbRegistroEntradas[[#This Row],[Data do Caixa Realizado]]>TbRegistroEntradas[[#This Row],[Data do Caixa Previsto]], TbRegistroEntradas[[#This Row],[Data do Caixa Realizado]]-TbRegistroEntradas[[#This Row],[Data do Caixa Previsto]], 0 ), IF(TODAY()>TbRegistroEntradas[[#This Row],[Data do Caixa Previsto]], TODAY()-TbRegistroEntradas[[#This Row],[Data do Caixa Previsto]], 0 ) ) -> 58
B74: 43169 | C74: 43160 | D74: 43169 | E74: Vendas de mercadorias | F74: Livros | G74: NF8852 | H74: 3701 | I74: =IF(TbRegistroEntradas[[#This Row],[Data do Caixa Realizado]]="",0,MONTH(TbRegistroEntradas[[#This Row],[Data do Caixa Realizado]])) -> 3 | J74: =IF(TbRegistroEntradas[[#This Row],[Data do Caixa Realizado]]="",0,YEAR(TbRegistroEntradas[[#This Row],[Data do Caixa Realizado]])) -> 2018 | K74: =IF(TbRegistroEntradas[[#This Row],[Data da Competência]]="",0,MONTH(TbRegistroEntradas[[#This Row],[Data da Competência]])) -> 3 | L74: =IF(TbRegistroEntradas[[#This Row],[Data da Competência]]="",0,YEAR(TbRegistroEntradas[[#This Row],[Data da Competência]])) -> 2018 | M74: =IF(TbRegistroEntradas[[#This Row],[Data do Caixa Previsto]]="",0,MONTH(TbRegistroEntradas[[#This Row],[Data do Caixa Previsto]])) -> 3 | N74: =IF(TbRegistroEntradas[[#This Row],[Data do Caixa Previsto]]="",0,YEAR(TbRegistroEntradas[[#This Row],[Data do Caixa Previsto]])) -> 2018 | O74: =IF(AND(TbRegistroEntradas[[#This Row],[Data do Caixa Previsto]]<TODAY(),TbRegistroEntradas[[#This Row],[Data do Caixa Realizado]]=""),"Vencida","Não Vencida") -> Não Vencida | P74: =IF(TbRegistroEntradas[[#This Row],[Data da Competência]]=TbRegistroEntradas[[#This Row],[Data do Caixa Previsto]],"Vista","Prazo") -> Prazo | Q74: =IF(TbRegistroEntradas[[#This Row],[Data do Caixa Realizado]]<>"", IF(TbRegistroEntradas[[#This Row],[Data do Caixa Realizado]]>TbRegistroEntradas[[#This Row],[Data do Caixa Previsto]], TbRegistroEntradas[[#This Row],[Data do Caixa Realizado]]-TbRegistroEntradas[[#This Row],[Data do Caixa Previsto]], 0 ), IF(TODAY()>TbRegistroEntradas[[#This Row],[Data do Caixa Previsto]], TODAY()-TbRegistroEntradas[[#This Row],[Data do Caixa Previsto]], 0 ) ) -> 0
C75: 43162 | D75: 43202 | E75: Vendas de mercadorias | F75: Som e imagem | G75: NF7869 | H75: 1977 | I75: =IF(TbRegistroEntradas[[#This Row],[Data do Caixa Realizado]]="",0,MONTH(TbRegistroEntradas[[#This Row],[Data do Caixa Realizado]])) -> 0 | J75: =IF(TbRegistroEntradas[[#This Row],[Data do Caixa Realizado]]="",0,YEAR(TbRegistroEntradas[[#This Row],[Data do Caixa Realizado]])) -> 0 | K75: =IF(TbRegistroEntradas[[#This Row],[Data da Competência]]="",0,MONTH(TbRegistroEntradas[[#This Row],[Data da Competência]])) -> 3 | L75: =IF(TbRegistroEntradas[[#This Row],[Data da Competência]]="",0,YEAR(TbRegistroEntradas[[#This Row],[Data da Competência]])) -> 2018 | M75: =IF(TbRegistroEntradas[[#This Row],[Data do Caixa Previsto]]="",0,MONTH(TbRegistroEntradas[[#This Row],[Data do Caixa Previsto]])) -> 4 | N75: =IF(TbRegistroEntradas[[#This Row],[Data do Caixa Previsto]]="",0,YEAR(TbRegistroEntradas[[#This Row],[Data do Caixa Previsto]])) -> 2018 | O75: =IF(AND(TbRegistroEntradas[[#This Row],[Data do Caixa Previsto]]<TODAY(),TbRegistroEntradas[[#This Row],[Data do Caixa Realizado]]=""),"Vencida","Não Vencida") -> Vencida | P75: =IF(TbRegistroEntradas[[#This Row],[Data da Competência]]=TbRegistroEntradas[[#This Row],[Data do Caixa Previsto]],"Vista","Prazo") -> Prazo | Q75: =IF(TbRegistroEntradas[[#This Row],[Data do Caixa Realizado]]<>"", IF(TbRegistroEntradas[[#This Row],[Data do Caixa Realizado]]>TbRegistroEntradas[[#This Row],[Data do Caixa Previsto]], TbRegistroEntradas[[#This Row],[Data do Caixa Realizado]]-TbRegistroEntradas[[#This Row],[Data do Caixa Previsto]], 0 ), IF(TODAY()>TbRegistroEntradas[[#This Row],[Data do Caixa Previsto]], TODAY()-TbRegistroEntradas[[#This Row],[Data do Caixa Previsto]], 0 ) ) -> 2151
B76: 43287 | C76: 43163 | D76: 43211 | E76: Vendas de mercadorias | F76: Livros | G76: NF4994 | H76: 1217 | I76: =IF(TbRegistroEntradas[[#This Row],[Data do Caixa Realizado]]="",0,MONTH(TbRegistroEntradas[[#This Row],[Data do Caixa Realizado]])) -> 7 | J76: =IF(TbRegistroEntradas[[#This Row],[Data do Caixa Realizado]]="",0,YEAR(TbRegistroEntradas[[#This Row],[Data do Caixa Realizado]])) -> 2018 | K76: =IF(TbRegistroEntradas[[#This Row],[Data da Competência]]="",0,MONTH(TbRegistroEntradas[[#This Row],[Data da Competência]])) -> 3 | L76: =IF(TbRegistroEntradas[[#This Row],[Data da Competência]]="",0,YEAR(TbRegistroEntradas[[#This Row],[Data da Competência]])) -> 2018 | M76: =IF(TbRegistroEntradas[[#This Row],[Data do Caixa Previsto]]="",0,MONTH(TbRegistroEntradas[[#This Row],[Data do Caixa Previsto]])) -> 4 | N76: =IF(TbRegistroEntradas[[#This Row],[Data do Caixa Previsto]]="",0,YEAR(TbRegistroEntradas[[#This Row],[Data do Caixa Previsto]])) -> 2018 | O76: =IF(AND(TbRegistroEntradas[[#This Row],[Data do Caixa Previsto]]<TODAY(),TbRegistroEntradas[[#This Row],[Data do Caixa Realizado]]=""),"Vencida","Não Vencida") -> Não Vencida | P76: =IF(TbRegistroEntradas[[#This Row],[Data da Competência]]=TbRegistroEntradas[[#This Row],[Data do Caixa Previsto]],"Vista","Prazo") -> Prazo | Q76: =IF(TbRegistroEntradas[[#This Row],[Data do Caixa Realizado]]<>"", IF(TbRegistroEntradas[[#This Row],[Data do Caixa Realizado]]>TbRegistroEntradas[[#This Row],[Data do Caixa Previsto]], TbRegistroEntradas[[#This Row],[Data do Caixa Realizado]]-TbRegistroEntradas[[#This Row],[Data do Caixa Previsto]], 0 ), IF(TODAY()>TbRegistroEntradas[[#This Row],[Data do Caixa Previsto]], TODAY()-TbRegistroEntradas[[#This Row],[Data do Caixa Previsto]], 0 ) ) -> 76
B77: 43203 | C77: 43166 | D77: 43203 | E77: Vendas de mercadorias | F77: Eletrodomésticos | G77: NF5720 | H77: 1660 | I77: =IF(TbRegistroEntradas[[#This Row],[Data do Caixa Realizado]]="",0,MONTH(TbRegistroEntradas[[#This Row],[Data do Caixa Realizado]])) -> 4 | J77: =IF(TbRegistroEntradas[[#This Row],[Data do Caixa Realizado]]="",0,YEAR(TbRegistroEntradas[[#This Row],[Data do Caixa Realizado]])) -> 2018 | K77: =IF(TbRegistroEntradas[[#This Row],[Data da Competência]]="",0,MONTH(TbRegistroEntradas[[#This Row],[Data da Competência]])) -> 3 | L77: =IF(TbRegistroEntradas[[#This Row],[Data da Competência]]="",0,YEAR(TbRegistroEntradas[[#This Row],[Data da Competência]])) -> 2018 | M77: =IF(TbRegistroEntradas[[#This Row],[Data do Caixa Previsto]]="",0,MONTH(TbRegistroEntradas[[#This Row],[Data do Caixa Previsto]])) -> 4 | N77: =IF(TbRegistroEntradas[[#This Row],[Data do Caixa Previsto]]="",0,YEAR(TbRegistroEntradas[[#This Row],[Data do Caixa Previsto]])) -> 2018 | O77: =IF(AND(TbRegistroEntradas[[#This Row],[Data do Caixa Previsto]]<TODAY(),TbRegistroEntradas[[#This Row],[Data do Caixa Realizado]]=""),"Vencida","Não Vencida") -> Não Vencida | P77: =IF(TbRegistroEntradas[[#This Row],[Data da Competência]]=TbRegistroEntradas[[#This Row],[Data do Caixa Previsto]],"Vista","Prazo") -> Prazo | Q77: =IF(TbRegistroEntradas[[#This Row],[Data do Caixa Realizado]]<>"", IF(TbRegistroEntradas[[#This Row],[Data do Caixa Realizado]]>TbRegistroEntradas[[#This Row],[Data do Caixa Previsto]], TbRegistroEntradas[[#This Row],[Data do Caixa Realizado]]-TbRegistroEntradas[[#This Row],[Data do Caixa Previsto]], 0 ), IF(TODAY()>TbRegistroEntradas[[#This Row],[Data do Caixa Previsto]], TODAY()-TbRegistroEntradas[[#This Row],[Data do Caixa Previsto]], 0 ) ) -> 0
B78: 43169 | C78: 43169 | D78: 43169 | E78: Vendas de mercadorias | F78: Eletrodomésticos | G78: NF6393 | H78: 837 | I78: =IF(TbRegistroEntradas[[#This Row],[Data do Caixa Realizado]]="",0,MONTH(TbRegistroEntradas[[#This Row],[Data do Caixa Realizado]])) -> 3 | J78: =IF(TbRegistroEntradas[[#This Row],[Data do Caixa Realizado]]="",0,YEAR(TbRegistroEntradas[[#This Row],[Data do Caixa Realizado]])) -> 2018 | K78: =IF(TbRegistroEntradas[[#This Row],[Data da Competência]]="",0,MONTH(TbRegistroEntradas[[#This Row],[Data da Competência]])) -> 3 | L78: =IF(TbRegistroEntradas[[#This Row],[Data da Competência]]="",0,YEAR(TbRegistroEntradas[[#This Row],[Data da Competência]])) -> 2018 | M78: =IF(TbRegistroEntradas[[#This Row],[Data do Caixa Previsto]]="",0,MONTH(TbRegistroEntradas[[#This Row],[Data do Caixa Previsto]])) -> 3 | N78: =IF(TbRegistroEntradas[[#This Row],[Data do Caixa Previsto]]="",0,YEAR(TbRegistroEntradas[[#This Row],[Data do Caixa Previsto]])) -> 2018 | O78: =IF(AND(TbRegistroEntradas[[#This Row],[Data do Caixa Previsto]]<TODAY(),TbRegistroEntradas[[#This Row],[Data do Caixa Realizado]]=""),"Vencida","Não Vencida") -> Não Vencida | P78: =IF(TbRegistroEntradas[[#This Row],[Data da Competência]]=TbRegistroEntradas[[#This Row],[Data do Caixa Previsto]],"Vista","Prazo") -> Vista | Q78: =IF(TbRegistroEntradas[[#This Row],[Data do Caixa Realizado]]<>"", IF(TbRegistroEntradas[[#This Row],[Data do Caixa Realizado]]>TbRegistroEntradas[[#This Row],[Data do Caixa Previsto]], TbRegistroEntradas[[#This Row],[Data do Caixa Realizado]]-TbRegistroEntradas[[#This Row],[Data do Caixa Previsto]], 0 ), IF(TODAY()>TbRegistroEntradas[[#This Row],[Data do Caixa Previsto]], TODAY()-TbRegistroEntradas[[#This Row],[Data do Caixa Previsto]], 0 ) ) -> 0
B79: 43274 | C79: 43171 | D79: 43200 | E79: Vendas de mercadorias | F79: Móveis | G79: NF9057 | H79: 1838 | I79: =IF(TbRegistroEntradas[[#This Row],[Data do Caixa Realizado]]="",0,MONTH(TbRegistroEntradas[[#This Row],[Data do Caixa Realizado]])) -> 6 | J79: =IF(TbRegistroEntradas[[#This Row],[Data do Caixa Realizado]]="",0,YEAR(TbRegistroEntradas[[#This Row],[Data do Caixa Realizado]])) -> 2018 | K79: =IF(TbRegistroEntradas[[#This Row],[Data da Competência]]="",0,MONTH(TbRegistroEntradas[[#This Row],[Data da Competência]])) -> 3 | L79: =IF(TbRegistroEntradas[[#This Row],[Data da Competência]]="",0,YEAR(TbRegistroEntradas[[#This Row],[Data da Competência]])) -> 2018 | M79: =IF(TbRegistroEntradas[[#This Row],[Data do Caixa Previsto]]="",0,MONTH(TbRegistroEntradas[[#This Row],[Data do Caixa Previsto]])) -> 4 | N79: =IF(TbRegistroEntradas[[#This Row],[Data do Caixa Previsto]]="",0,YEAR(TbRegistroEntradas[[#This Row],[Data do Caixa Previsto]])) -> 2018 | O79: =IF(AND(TbRegistroEntradas[[#This Row],[Data do Caixa Previsto]]<TODAY(),TbRegistroEntradas[[#This Row],[Data do Caixa Realizado]]=""),"Vencida","Não Vencida") -> Não Vencida | P79: =IF(TbRegistroEntradas[[#This Row],[Data da Competência]]=TbRegistroEntradas[[#This Row],[Data do Caixa Previsto]],"Vista","Prazo") -> Prazo | Q79: =IF(TbRegistroEntradas[[#This Row],[Data do Caixa Realizado]]<>"", IF(TbRegistroEntradas[[#This Row],[Data do Caixa Realizado]]>TbRegistroEntradas[[#This Row],[Data do Caixa Previsto]], TbRegistroEntradas[[#This Row],[Data do Caixa Realizado]]-TbRegistroEntradas[[#This Row],[Data do Caixa Previsto]], 0 ), IF(TODAY()>TbRegistroEntradas[[#This Row],[Data do Caixa Previsto]], TODAY()-TbRegistroEntradas[[#This Row],[Data do Caixa Previsto]], 0 ) ) -> 74
B80: 43176 | C80: 43176 | D80: 43176 | E80: Vendas de mercadorias | F80: Som e imagem | G80: NF7365 | H80: 4471 | I80: =IF(TbRegistroEntradas[[#This Row],[Data do Caixa Realizado]]="",0,MONTH(TbRegistroEntradas[[#This Row],[Data do Caixa Realizado]])) -> 3 | J80: =IF(TbRegistroEntradas[[#This Row],[Data do Caixa Realizado]]="",0,YEAR(TbRegistroEntradas[[#This Row],[Data do Caixa Realizado]])) -> 2018 | K80: =IF(TbRegistroEntradas[[#This Row],[Data da Competência]]="",0,MONTH(TbRegistroEntradas[[#This Row],[Data da Competência]])) -> 3 | L80: =IF(TbRegistroEntradas[[#This Row],[Data da Competência]]="",0,YEAR(TbRegistroEntradas[[#This Row],[Data da Competência]])) -> 2018 | M80: =IF(TbRegistroEntradas[[#This Row],[Data do Caixa Previsto]]="",0,MONTH(TbRegistroEntradas[[#This Row],[Data do Caixa Previsto]])) -> 3 | N80: =IF(TbRegistroEntradas[[#This Row],[Data do Caixa Previsto]]="",0,YEAR(TbRegistroEntradas[[#This Row],[Data do Caixa Previsto]])) -> 2018 | O80: =IF(AND(TbRegistroEntradas[[#This Row],[Data do Caixa Previsto]]<TODAY(),TbRegistroEntradas[[#This Row],[Data do Caixa Realizado]]=""),"Vencida","Não Vencida") -> Não Vencida | P80: =IF(TbRegistroEntradas[[#This Row],[Data da Competência]]=TbRegistroEntradas[[#This Row],[Data do Caixa Previsto]],"Vista","Prazo") -> Vista | Q80: =IF(TbRegistroEntradas[[#This Row],[Data do Caixa Realizado]]<>"", IF(TbRegistroEntradas[[#This Row],[Data do Caixa Realizado]]>TbRegistroEntradas[[#This Row],[Data do Caixa Previsto]], TbRegistroEntradas[[#This Row],[Data do Caixa Realizado]]-TbRegistroEntradas[[#This Row],[Data do Caixa Previsto]], 0 ), IF(TODAY()>TbRegistroEntradas[[#This Row],[Data do Caixa Previsto]], TODAY()-TbRegistroEntradas[[#This Row],[Data do Caixa Previsto]], 0 ) ) -> 0
B81: 43177 | C81: 43177 | D81: 43177 | E81: Vendas de mercadorias | F81: Móveis | G81: NF4559 | H81: 3540 | I81: =IF(TbRegistroEntradas[[#This Row],[Data do Caixa Realizado]]="",0,MONTH(TbRegistroEntradas[[#This Row],[Data do Caixa Realizado]])) -> 3 | J81: =IF(TbRegistroEntradas[[#This Row],[Data do Caixa Realizado]]="",0,YEAR(TbRegistroEntradas[[#This Row],[Data do Caixa Realizado]])) -> 2018 | K81: =IF(TbRegistroEntradas[[#This Row],[Data da Competência]]="",0,MONTH(TbRegistroEntradas[[#This Row],[Data da Competência]])) -> 3 | L81: =IF(TbRegistroEntradas[[#This Row],[Data da Competência]]="",0,YEAR(TbRegistroEntradas[[#This Row],[Data da Competência]])) -> 2018 | M81: =IF(TbRegistroEntradas[[#This Row],[Data do Caixa Previsto]]="",0,MONTH(TbRegistroEntradas[[#This Row],[Data do Caixa Previsto]])) -> 3 | N81: =IF(TbRegistroEntradas[[#This Row],[Data do Caixa Previsto]]="",0,YEAR(TbRegistroEntradas[[#This Row],[Data do Caixa Previsto]])) -> 2018 | O81: =IF(AND(TbRegistroEntradas[[#This Row],[Data do Caixa Previsto]]<TODAY(),TbRegistroEntradas[[#This Row],[Data do Caixa Realizado]]=""),"Vencida","Não Vencida") -> Não Vencida | P81: =IF(TbRegistroEntradas[[#This Row],[Data da Competência]]=TbRegistroEntradas[[#This Row],[Data do Caixa Previsto]],"Vista","Prazo") -> Vista | Q81: =IF(TbRegistroEntradas[[#This Row],[Data do Caixa Realizado]]<>"", IF(TbRegistroEntradas[[#This Row],[Data do Caixa Realizado]]>TbRegistroEntradas[[#This Row],[Data do Caixa Previsto]], TbRegistroEntradas[[#This Row],[Data do Caixa Realizado]]-TbRegistroEntradas[[#This Row],[Data do Caixa Previsto]], 0 ), IF(TODAY()>TbRegistroEntradas[[#This Row],[Data do Caixa Previsto]], TODAY()-TbRegistroEntradas[[#This Row],[Data do Caixa Previsto]], 0 ) ) -> 0
B82: 43225 | C82: 43180 | D82: 43180 | E82: Vendas de mercadorias | F82: Móveis | G82: NF7119 | H82: 4606 | I82: =IF(TbRegistroEntradas[[#This Row],[Data do Caixa Realizado]]="",0,MONTH(TbRegistroEntradas[[#This Row],[Data do Caixa Realizado]])) -> 5 | J82: =IF(TbRegistroEntradas[[#This Row],[Data do Caixa Realizado]]="",0,YEAR(TbRegistroEntradas[[#This Row],[Data do Caixa Realizado]])) -> 2018 | K82: =IF(TbRegistroEntradas[[#This Row],[Data da Competência]]="",0,MONTH(TbRegistroEntradas[[#This Row],[Data da Competência]])) -> 3 | L82: =IF(TbRegistroEntradas[[#This Row],[Data da Competência]]="",0,YEAR(TbRegistroEntradas[[#This Row],[Data da Competência]])) -> 2018 | M82: =IF(TbRegistroEntradas[[#This Row],[Data do Caixa Previsto]]="",0,MONTH(TbRegistroEntradas[[#This Row],[Data do Caixa Previsto]])) -> 3 | N82: =IF(TbRegistroEntradas[[#This Row],[Data do Caixa Previsto]]="",0,YEAR(TbRegistroEntradas[[#This Row],[Data do Caixa Previsto]])) -> 2018 | O82: =IF(AND(TbRegistroEntradas[[#This Row],[Data do Caixa Previsto]]<TODAY(),TbRegistroEntradas[[#This Row],[Data do Caixa Realizado]]=""),"Vencida","Não Vencida") -> Não Vencida | P82: =IF(TbRegistroEntradas[[#This Row],[Data da Competência]]=TbRegistroEntradas[[#This Row],[Data do Caixa Previsto]],"Vista","Prazo") -> Vista | Q82: =IF(TbRegistroEntradas[[#This Row],[Data do Caixa Realizado]]<>"", IF(TbRegistroEntradas[[#This Row],[Data do Caixa Realizado]]>TbRegistroEntradas[[#This Row],[Data do Caixa Previsto]], TbRegistroEntradas[[#This Row],[Data do Caixa Realizado]]-TbRegistroEntradas[[#This Row],[Data do Caixa Previsto]], 0 ), IF(TODAY()>TbRegistroEntradas[[#This Row],[Data do Caixa Previsto]], TODAY()-TbRegistroEntradas[[#This Row],[Data do Caixa Previsto]], 0 ) ) -> 45
B83: 43199 | C83: 43182 | D83: 43199 | E83: Vendas de mercadorias | F83: Informática | G83: NF2814 | H83: 2388 | I83: =IF(TbRegistroEntradas[[#This Row],[Data do Caixa Realizado]]="",0,MONTH(TbRegistroEntradas[[#This Row],[Data do Caixa Realizado]])) -> 4 | J83: =IF(TbRegistroEntradas[[#This Row],[Data do Caixa Realizado]]="",0,YEAR(TbRegistroEntradas[[#This Row],[Data do Caixa Realizado]])) -> 2018 | K83: =IF(TbRegistroEntradas[[#This Row],[Data da Competência]]="",0,MONTH(TbRegistroEntradas[[#This Row],[Data da Competência]])) -> 3 | L83: =IF(TbRegistroEntradas[[#This Row],[Data da Competência]]="",0,YEAR(TbRegistroEntradas[[#This Row],[Data da Competência]])) -> 2018 | M83: =IF(TbRegistroEntradas[[#This Row],[Data do Caixa Previsto]]="",0,MONTH(TbRegistroEntradas[[#This Row],[Data do Caixa Previsto]])) -> 4 | N83: =IF(TbRegistroEntradas[[#This Row],[Data do Caixa Previsto]]="",0,YEAR(TbRegistroEntradas[[#This Row],[Data do Caixa Previsto]])) -> 2018 | O83: =IF(AND(TbRegistroEntradas[[#This Row],[Data do Caixa Previsto]]<TODAY(),TbRegistroEntradas[[#This Row],[Data do Caixa Realizado]]=""),"Vencida","Não Vencida") -> Não Vencida | P83: =IF(TbRegistroEntradas[[#This Row],[Data da Competência]]=TbRegistroEntradas[[#This Row],[Data do Caixa Previsto]],"Vista","Prazo") -> Prazo | Q83: =IF(TbRegistroEntradas[[#This Row],[Data do Caixa Realizado]]<>"", IF(TbRegistroEntradas[[#This Row],[Data do Caixa Realizado]]>TbRegistroEntradas[[#This Row],[Data do Caixa Previsto]], TbRegistroEntradas[[#This Row],[Data do Caixa Realizado]]-TbRegistroEntradas[[#This Row],[Data do Caixa Previsto]], 0 ), IF(TODAY()>TbRegistroEntradas[[#This Row],[Data do Caixa Previsto]], TODAY()-TbRegistroEntradas[[#This Row],[Data do Caixa Previsto]], 0 ) ) -> 0
B84: 43187 | C84: 43184 | D84: 43187 | E84: Vendas de mercadorias | F84: Eletrodomésticos | G84: NF5963 | H84: 2303 | I84: =IF(TbRegistroEntradas[[#This Row],[Data do Caixa Realizado]]="",0,MONTH(TbRegistroEntradas[[#This Row],[Data do Caixa Realizado]])) -> 3 | J84: =IF(TbRegistroEntradas[[#This Row],[Data do Caixa Realizado]]="",0,YEAR(TbRegistroEntradas[[#This Row],[Data do Caixa Realizado]])) -> 2018 | K84: =IF(TbRegistroEntradas[[#This Row],[Data da Competência]]="",0,MONTH(TbRegistroEntradas[[#This Row],[Data da Competência]])) -> 3 | L84: =IF(TbRegistroEntradas[[#This Row],[Data da Competência]]="",0,YEAR(TbRegistroEntradas[[#This Row],[Data da Competência]])) -> 2018 | M84: =IF(TbRegistroEntradas[[#This Row],[Data do Caixa Previsto]]="",0,MONTH(TbRegistroEntradas[[#This Row],[Data do Caixa Previsto]])) -> 3 | N84: =IF(TbRegistroEntradas[[#This Row],[Data do Caixa Previsto]]="",0,YEAR(TbRegistroEntradas[[#This Row],[Data do Caixa Previsto]])) -> 2018 | O84: =IF(AND(TbRegistroEntradas[[#This Row],[Data do Caixa Previsto]]<TODAY(),TbRegistroEntradas[[#This Row],[Data do Caixa Realizado]]=""),"Vencida","Não Vencida") -> Não Vencida | P84: =IF(TbRegistroEntradas[[#This Row],[Data da Competência]]=TbRegistroEntradas[[#This Row],[Data do Caixa Previsto]],"Vista","Prazo") -> Prazo | Q84: =IF(TbRegistroEntradas[[#This Row],[Data do Caixa Realizado]]<>"", IF(TbRegistroEntradas[[#This Row],[Data do Caixa Realizado]]>TbRegistroEntradas[[#This Row],[Data do Caixa Previsto]], TbRegistroEntradas[[#This Row],[Data do Caixa Realizado]]-TbRegistroEntradas[[#This Row],[Data do Caixa Previsto]], 0 ), IF(TODAY()>TbRegistroEntradas[[#This Row],[Data do Caixa Previsto]], TODAY()-TbRegistroEntradas[[#This Row],[Data do Caixa Previsto]], 0 ) ) -> 0
B85: 43257 | C85: 43187 | D85: 43205 | E85: Vendas de mercadorias | F85: Som e imagem | G85: NF3293 | H85: 1662 | I85: =IF(TbRegistroEntradas[[#This Row],[Data do Caixa Realizado]]="",0,MONTH(TbRegistroEntradas[[#This Row],[Data do Caixa Realizado]])) -> 6 | J85: =IF(TbRegistroEntradas[[#This Row],[Data do Caixa Realizado]]="",0,YEAR(TbRegistroEntradas[[#This Row],[Data do Caixa Realizado]])) -> 2018 | K85: =IF(TbRegistroEntradas[[#This Row],[Data da Competência]]="",0,MONTH(TbRegistroEntradas[[#This Row],[Data da Competência]])) -> 3 | L85: =IF(TbRegistroEntradas[[#This Row],[Data da Competência]]="",0,YEAR(TbRegistroEntradas[[#This Row],[Data da Competência]])) -> 2018 | M85: =IF(TbRegistroEntradas[[#This Row],[Data do Caixa Previsto]]="",0,MONTH(TbRegistroEntradas[[#This Row],[Data do Caixa Previsto]])) -> 4 | N85: =IF(TbRegistroEntradas[[#This Row],[Data do Caixa Previsto]]="",0,YEAR(TbRegistroEntradas[[#This Row],[Data do Caixa Previsto]])) -> 2018 | O85: =IF(AND(TbRegistroEntradas[[#This Row],[Data do Caixa Previsto]]<TODAY(),TbRegistroEntradas[[#This Row],[Data do Caixa Realizado]]=""),"Vencida","Não Vencida") -> Não Vencida | P85: =IF(TbRegistroEntradas[[#This Row],[Data da Competência]]=TbRegistroEntradas[[#This Row],[Data do Caixa Previsto]],"Vista","Prazo") -> Prazo | Q85: =IF(TbRegistroEntradas[[#This Row],[Data do Caixa Realizado]]<>"", IF(TbRegistroEntradas[[#This Row],[Data do Caixa Realizado]]>TbRegistroEntradas[[#This Row],[Data do Caixa Previsto]], TbRegistroEntradas[[#This Row],[Data do Caixa Realizado]]-TbRegistroEntradas[[#This Row],[Data do Caixa Previsto]], 0 ), IF(TODAY()>TbRegistroEntradas[[#This Row],[Data do Caixa Previsto]], TODAY()-TbRegistroEntradas[[#This Row],[Data do Caixa Previsto]], 0 ) ) -> 52
B86: 43214 | C86: 43189 | D86: 43189 | E86: Vendas de mercadorias | F86: Informática | G86: NF8254 | H86: 3241 | I86: =IF(TbRegistroEntradas[[#This Row],[Data do Caixa Realizado]]="",0,MONTH(TbRegistroEntradas[[#This Row],[Data do Caixa Realizado]])) -> 4 | J86: =IF(TbRegistroEntradas[[#This Row],[Data do Caixa Realizado]]="",0,YEAR(TbRegistroEntradas[[#This Row],[Data do Caixa Realizado]])) -> 2018 | K86: =IF(TbRegistroEntradas[[#This Row],[Data da Competência]]="",0,MONTH(TbRegistroEntradas[[#This Row],[Data da Competência]])) -> 3 | L86: =IF(TbRegistroEntradas[[#This Row],[Data da Competência]]="",0,YEAR(TbRegistroEntradas[[#This Row],[Data da Competência]])) -> 2018 | M86: =IF(TbRegistroEntradas[[#This Row],[Data do Caixa Previsto]]="",0,MONTH(TbRegistroEntradas[[#This Row],[Data do Caixa Previsto]])) -> 3 | N86: =IF(TbRegistroEntradas[[#This Row],[Data do Caixa Previsto]]="",0,YEAR(TbRegistroEntradas[[#This Row],[Data do Caixa Previsto]])) -> 2018 | O86: =IF(AND(TbRegistroEntradas[[#This Row],[Data do Caixa Previsto]]<TODAY(),TbRegistroEntradas[[#This Row],[Data do Caixa Realizado]]=""),"Vencida","Não Vencida") -> Não Vencida | P86: =IF(TbRegistroEntradas[[#This Row],[Data da Competência]]=TbRegistroEntradas[[#This Row],[Data do Caixa Previsto]],"Vista","Prazo") -> Vista | Q86: =IF(TbRegistroEntradas[[#This Row],[Data do Caixa Realizado]]<>"", IF(TbRegistroEntradas[[#This Row],[Data do Caixa Realizado]]>TbRegistroEntradas[[#This Row],[Data do Caixa Previsto]], TbRegistroEntradas[[#This Row],[Data do Caixa Realizado]]-TbRegistroEntradas[[#This Row],[Data do Caixa Previsto]], 0 ), IF(TODAY()>TbRegistroEntradas[[#This Row],[Data do Caixa Previsto]], TODAY()-TbRegistroEntradas[[#This Row],[Data do Caixa Previsto]], 0 ) ) -> 25
B87: 43306 | C87: 43190 | D87: 43228 | E87: Vendas de mercadorias | F87: Som e imagem | G87: NF4303 | H87: 4017 | I87: =IF(TbRegistroEntradas[[#This Row],[Data do Caixa Realizado]]="",0,MONTH(TbRegistroEntradas[[#This Row],[Data do Caixa Realizado]])) -> 7 | J87: =IF(TbRegistroEntradas[[#This Row],[Data do Caixa Realizado]]="",0,YEAR(TbRegistroEntradas[[#This Row],[Data do Caixa Realizado]])) -> 2018 | K87: =IF(TbRegistroEntradas[[#This Row],[Data da Competência]]="",0,MONTH(TbRegistroEntradas[[#This Row],[Data da Competência]])) -> 3 | L87: =IF(TbRegistroEntradas[[#This Row],[Data da Competência]]="",0,YEAR(TbRegistroEntradas[[#This Row],[Data da Competência]])) -> 2018 | M87: =IF(TbRegistroEntradas[[#This Row],[Data do Caixa Previsto]]="",0,MONTH(TbRegistroEntradas[[#This Row],[Data do Caixa Previsto]])) -> 5 | N87: =IF(TbRegistroEntradas[[#This Row],[Data do Caixa Previsto]]="",0,YEAR(TbRegistroEntradas[[#This Row],[Data do Caixa Previsto]])) -> 2018 | O87: =IF(AND(TbRegistroEntradas[[#This Row],[Data do Caixa Previsto]]<TODAY(),TbRegistroEntradas[[#This Row],[Data do Caixa Realizado]]=""),"Vencida","Não Vencida") -> Não Vencida | P87: =IF(TbRegistroEntradas[[#This Row],[Data da Competência]]=TbRegistroEntradas[[#This Row],[Data do Caixa Previsto]],"Vista","Prazo") -> Prazo | Q87: =IF(TbRegistroEntradas[[#This Row],[Data do Caixa Realizado]]<>"", IF(TbRegistroEntradas[[#This Row],[Data do Caixa Realizado]]>TbRegistroEntradas[[#This Row],[Data do Caixa Previsto]], TbRegistroEntradas[[#This Row],[Data do Caixa Realizado]]-TbRegistroEntradas[[#This Row],[Data do Caixa Previsto]], 0 ), IF(TODAY()>TbRegistroEntradas[[#This Row],[Data do Caixa Previsto]], TODAY()-TbRegistroEntradas[[#This Row],[Data do Caixa Previsto]], 0 ) ) -> 78
... B90: 43251 | C90: 43199 | D90: 43251 | E90: Vendas de mercadorias | F90: Móveis | G90: NF6697 | H90: 4262 | I90: =IF(TbRegistroEntradas[[#This Row],[Data do Caixa Realizado]]="",0,MONTH(TbRegistroEntradas[[#This Row],[Data do Caixa Realizado]])) -> 5 | J90: =IF(TbRegistroEntradas[[#This Row],[Data do Caixa Realizado]]="",0,YEAR(TbRegistroEntradas[[#This Row],[Data do Caixa Realizado]])) -> 2018 | K90: =IF(TbRegistroEntradas[[#This Row],[Data da Competência]]="",0,MONTH(TbRegistroEntradas[[#This Row],[Data da Competência]])) -> 4 | L90: =IF(TbRegistroEntradas[[#This Row],[Data da Competência]]="",0,YEAR(TbRegistroEntradas[[#This Row],[Data da Competência]])) -> 2018 | M90: =IF(TbRegistroEntradas[[#This Row],[Data do Caixa Previsto]]="",0,MONTH(TbRegistroEntradas[[#This Row],[Data do Caixa Previsto]])) -> 5 | N90: =IF(TbRegistroEntradas[[#This Row],[Data do Caixa Previsto]]="",0,YEAR(TbRegistroEntradas[[#This Row],[Data do Caixa Previsto]])) -> 2018 | O90: =IF(AND(TbRegistroEntradas[[#This Row],[Data do Caixa Previsto]]<TODAY(),TbRegistroEntradas[[#This Row],[Data do Caixa Realizado]]=""),"Vencida","Não Vencida") -> Não Vencida | P90: =IF(TbRegistroEntradas[[#This Row],[Data da Competência]]=TbRegistroEntradas[[#This Row],[Data do Caixa Previsto]],"Vista","Prazo") -> Prazo | Q90: =IF(TbRegistroEntradas[[#This Row],[Data do Caixa Realizado]]<>"", IF(TbRegistroEntradas[[#This Row],[Data do Caixa Realizado]]>TbRegistroEntradas[[#This Row],[Data do Caixa Previsto]], TbRegistroEntradas[[#This Row],[Data do Caixa Realizado]]-TbRegistroEntradas[[#This Row],[Data do Caixa Previsto]], 0 ), IF(TODAY()>TbRegistroEntradas[[#This Row],[Data do Caixa Previsto]], TODAY()-TbRegistroEntradas[[#This Row],[Data do Caixa Previsto]], 0 ) ) -> 0
C91: 43201 | D91: 43260 | E91: Vendas de mercadorias | F91: Móveis | G91: NF5208 | H91: 2593 | I91: =IF(TbRegistroEntradas[[#This Row],[Data do Caixa Realizado]]="",0,MONTH(TbRegistroEntradas[[#This Row],[Data do Caixa Realizado]])) -> 0 | J91: =IF(TbRegistroEntradas[[#This Row],[Data do Caixa Realizado]]="",0,YEAR(TbRegistroEntradas[[#This Row],[Data do Caixa Realizado]])) -> 0 | K91: =IF(TbRegistroEntradas[[#This Row],[Data da Competência]]="",0,MONTH(TbRegistroEntradas[[#This Row],[Data da Competência]])) -> 4 | L91: =IF(TbRegistroEntradas[[#This Row],[Data da Competência]]="",0,YEAR(TbRegistroEntradas[[#This Row],[Data da Competência]])) -> 2018 | M91: =IF(TbRegistroEntradas[[#This Row],[Data do Caixa Previsto]]="",0,MONTH(TbRegistroEntradas[[#This Row],[Data do Caixa Previsto]])) -> 6 | N91: =IF(TbRegistroEntradas[[#This Row],[Data do Caixa Previsto]]="",0,YEAR(TbRegistroEntradas[[#This Row],[Data do Caixa Previsto]])) -> 2018 | O91: =IF(AND(TbRegistroEntradas[[#This Row],[Data do Caixa Previsto]]<TODAY(),TbRegistroEntradas[[#This Row],[Data do Caixa Realizado]]=""),"Vencida","Não Vencida") -> Vencida | P91: =IF(TbRegistroEntradas[[#This Row],[Data da Competência]]=TbRegistroEntradas[[#This Row],[Data do Caixa Previsto]],"Vista","Prazo") -> Prazo | Q91: =IF(TbRegistroEntradas[[#This Row],[Data do Caixa Realizado]]<>"", IF(TbRegistroEntradas[[#This Row],[Data do Caixa Realizado]]>TbRegistroEntradas[[#This Row],[Data do Caixa Previsto]], TbRegistroEntradas[[#This Row],[Data do Caixa Realizado]]-TbRegistroEntradas[[#This Row],[Data do Caixa Previsto]], 0 ), IF(TODAY()>TbRegistroEntradas[[#This Row],[Data do Caixa Previsto]], TODAY()-TbRegistroEntradas[[#This Row],[Data do Caixa Previsto]], 0 ) ) -> 2093
B92: 43224 | C92: 43204 | D92: 43224 | E92: Vendas de mercadorias | F92: Móveis | G92: NF2907 | H92: 1885 | I92: =IF(TbRegistroEntradas[[#This Row],[Data do Caixa Realizado]]="",0,MONTH(TbRegistroEntradas[[#This Row],[Data do Caixa Realizado]])) -> 5 | J92: =IF(TbRegistroEntradas[[#This Row],[Data do Caixa Realizado]]="",0,YEAR(TbRegistroEntradas[[#This Row],[Data do Caixa Realizado]])) -> 2018 | K92: =IF(TbRegistroEntradas[[#This Row],[Data da Competência]]="",0,MONTH(TbRegistroEntradas[[#This Row],[Data da Competência]])) -> 4 | L92: =IF(TbRegistroEntradas[[#This Row],[Data da Competência]]="",0,YEAR(TbRegistroEntradas[[#This Row],[Data da Competência]])) -> 2018 | M92: =IF(TbRegistroEntradas[[#This Row],[Data do Caixa Previsto]]="",0,MONTH(TbRegistroEntradas[[#This Row],[Data do Caixa Previsto]])) -> 5 | N92: =IF(TbRegistroEntradas[[#This Row],[Data do Caixa Previsto]]="",0,YEAR(TbRegistroEntradas[[#This Row],[Data do Caixa Previsto]])) -> 2018 | O92: =IF(AND(TbRegistroEntradas[[#This Row],[Data do Caixa Previsto]]<TODAY(),TbRegistroEntradas[[#This Row],[Data do Caixa Realizado]]=""),"Vencida","Não Vencida") -> Não Vencida | P92: =IF(TbRegistroEntradas[[#This Row],[Data da Competência]]=TbRegistroEntradas[[#This Row],[Data do Caixa Previsto]],"Vista","Prazo") -> Prazo | Q92: =IF(TbRegistroEntradas[[#This Row],[Data do Caixa Realizado]]<>"", IF(TbRegistroEntradas[[#This Row],[Data do Caixa Realizado]]>TbRegistroEntradas[[#This Row],[Data do Caixa Previsto]], TbRegistroEntradas[[#This Row],[Data do Caixa Realizado]]-TbRegistroEntradas[[#This Row],[Data do Caixa Previsto]], 0 ), IF(TODAY()>TbRegistroEntradas[[#This Row],[Data do Caixa Previsto]], TODAY()-TbRegistroEntradas[[#This Row],[Data do Caixa Previsto]], 0 ) ) -> 0
B93: 43295 | C93: 43209 | D93: 43209 | E93: Vendas de mercadorias | F93: Móveis | G93: NF9381 | H93: 2224 | I93: =IF(TbRegistroEntradas[[#This Row],[Data do Caixa Realizado]]="",0,MONTH(TbRegistroEntradas[[#This Row],[Data do Caixa Realizado]])) -> 7 | J93: =IF(TbRegistroEntradas[[#This Row],[Data do Caixa Realizado]]="",0,YEAR(TbRegistroEntradas[[#This Row],[Data do Caixa Realizado]])) -> 2018 | K93: =IF(TbRegistroEntradas[[#This Row],[Data da Competência]]="",0,MONTH(TbRegistroEntradas[[#This Row],[Data da Competência]])) -> 4 | L93: =IF(TbRegistroEntradas[[#This Row],[Data da Competência]]="",0,YEAR(TbRegistroEntradas[[#This Row],[Data da Competência]])) -> 2018 | M93: =IF(TbRegistroEntradas[[#This Row],[Data do Caixa Previsto]]="",0,MONTH(TbRegistroEntradas[[#This Row],[Data do Caixa Previsto]])) -> 4 | N93: =IF(TbRegistroEntradas[[#This Row],[Data do Caixa Previsto]]="",0,YEAR(TbRegistroEntradas[[#This Row],[Data do Caixa Previsto]])) -> 2018 | O93: =IF(AND(TbRegistroEntradas[[#This Row],[Data do Caixa Previsto]]<TODAY(),TbRegistroEntradas[[#This Row],[Data do Caixa Realizado]]=""),"Vencida","Não Vencida") -> Não Vencida | P93: =IF(TbRegistroEntradas[[#This Row],[Data da Competência]]=TbRegistroEntradas[[#This Row],[Data do Caixa Previsto]],"Vista","Prazo") -> Vista | Q93: =IF(TbRegistroEntradas[[#This Row],[Data do Caixa Realizado]]<>"", IF(TbRegistroEntradas[[#This Row],[Data do Caixa Realizado]]>TbRegistroEntradas[[#This Row],[Data do Caixa Previsto]], TbRegistroEntradas[[#This Row],[Data do Caixa Realizado]]-TbRegistroEntradas[[#This Row],[Data do Caixa Previsto]], 0 ), IF(TODAY()>TbRegistroEntradas[[#This Row],[Data do Caixa Previsto]], TODAY()-TbRegistroEntradas[[#This Row],[Data do Caixa Previsto]], 0 ) ) -> 86
B94: 43234 | C94: 43213 | D94: 43234 | E94: Vendas de mercadorias | F94: Móveis | G94: NF3247 | H94: 3223 | I94: =IF(TbRegistroEntradas[[#This Row],[Data do Caixa Realizado]]="",0,MONTH(TbRegistroEntradas[[#This Row],[Data do Caixa Realizado]])) -> 5 | J94: =IF(TbRegistroEntradas[[#This Row],[Data do Caixa Realizado]]="",0,YEAR(TbRegistroEntradas[[#This Row],[Data do Caixa Realizado]])) -> 2018 | K94: =IF(TbRegistroEntradas[[#This Row],[Data da Competência]]="",0,MONTH(TbRegistroEntradas[[#This Row],[Data da Competência]])) -> 4 | L94: =IF(TbRegistroEntradas[[#This Row],[Data da Competência]]="",0,YEAR(TbRegistroEntradas[[#This Row],[Data da Competência]])) -> 2018 | M94: =IF(TbRegistroEntradas[[#This Row],[Data do Caixa Previsto]]="",0,MONTH(TbRegistroEntradas[[#This Row],[Data do Caixa Previsto]])) -> 5 | N94: =IF(TbRegistroEntradas[[#This Row],[Data do Caixa Previsto]]="",0,YEAR(TbRegistroEntradas[[#This Row],[Data do Caixa Previsto]])) -> 2018 | O94: =IF(AND(TbRegistroEntradas[[#This Row],[Data do Caixa Previsto]]<TODAY(),TbRegistroEntradas[[#This Row],[Data do Caixa Realizado]]=""),"Vencida","Não Vencida") -> Não Vencida | P94: =IF(TbRegistroEntradas[[#This Row],[Data da Competência]]=TbRegistroEntradas[[#This Row],[Data do Caixa Previsto]],"Vista","Prazo") -> Prazo | Q94: =IF(TbRegistroEntradas[[#This Row],[Data do Caixa Realizado]]<>"", IF(TbRegistroEntradas[[#This Row],[Data do Caixa Realizado]]>TbRegistroEntradas[[#This Row],[Data do Caixa Previsto]], TbRegistroEntradas[[#This Row],[Data do Caixa Realizado]]-TbRegistroEntradas[[#This Row],[Data do Caixa Previsto]], 0 ), IF(TODAY()>TbRegistroEntradas[[#This Row],[Data do Caixa Previsto]], TODAY()-TbRegistroEntradas[[#This Row],[Data do Caixa Previsto]], 0 ) ) -> 0
B95: 43216 | C95: 43216 | D95: 43216 | E95: Vendas de mercadorias | F95: Livros | G95: NF4377 | H95: 3446 | I95: =IF(TbRegistroEntradas[[#This Row],[Data do Caixa Realizado]]="",0,MONTH(TbRegistroEntradas[[#This Row],[Data do Caixa Realizado]])) -> 4 | J95: =IF(TbRegistroEntradas[[#This Row],[Data do Caixa Realizado]]="",0,YEAR(TbRegistroEntradas[[#This Row],[Data do Caixa Realizado]])) -> 2018 | K95: =IF(TbRegistroEntradas[[#This Row],[Data da Competência]]="",0,MONTH(TbRegistroEntradas[[#This Row],[Data da Competência]])) -> 4 | L95: =IF(TbRegistroEntradas[[#This Row],[Data da Competência]]="",0,YEAR(TbRegistroEntradas[[#This Row],[Data da Competência]])) -> 2018 | M95: =IF(TbRegistroEntradas[[#This Row],[Data do Caixa Previsto]]="",0,MONTH(TbRegistroEntradas[[#This Row],[Data do Caixa Previsto]])) -> 4 | N95: =IF(TbRegistroEntradas[[#This Row],[Data do Caixa Previsto]]="",0,YEAR(TbRegistroEntradas[[#This Row],[Data do Caixa Previsto]])) -> 2018 | O95: =IF(AND(TbRegistroEntradas[[#This Row],[Data do Caixa Previsto]]<TODAY(),TbRegistroEntradas[[#This Row],[Data do Caixa Realizado]]=""),"Vencida","Não Vencida") -> Não Vencida | P95: =IF(TbRegistroEntradas[[#This Row],[Data da Competência]]=TbRegistroEntradas[[#This Row],[Data do Caixa Previsto]],"Vista","Prazo") -> Vista | Q95: =IF(TbRegistroEntradas[[#This Row],[Data do Caixa Realizado]]<>"", IF(TbRegistroEntradas[[#This Row],[Data do Caixa Realizado]]>TbRegistroEntradas[[#This Row],[Data do Caixa Previsto]], TbRegistroEntradas[[#This Row],[Data do Caixa Realizado]]-TbRegistroEntradas[[#This Row],[Data do Caixa Previsto]], 0 ), IF(TODAY()>TbRegistroEntradas[[#This Row],[Data do Caixa Previsto]], TODAY()-TbRegistroEntradas[[#This Row],[Data do Caixa Previsto]], 0 ) ) -> 0
B96: 43226 | C96: 43220 | D96: 43220 | E96: Vendas de mercadorias | F96: Móveis | G96: NF2988 | H96: 4540 | I96: =IF(TbRegistroEntradas[[#This Row],[Data do Caixa Realizado]]="",0,MONTH(TbRegistroEntradas[[#This Row],[Data do Caixa Realizado]])) -> 5 | J96: =IF(TbRegistroEntradas[[#This Row],[Data do Caixa Realizado]]="",0,YEAR(TbRegistroEntradas[[#This Row],[Data do Caixa Realizado]])) -> 2018 | K96: =IF(TbRegistroEntradas[[#This Row],[Data da Competência]]="",0,MONTH(TbRegistroEntradas[[#This Row],[Data da Competência]])) -> 4 | L96: =IF(TbRegistroEntradas[[#This Row],[Data da Competência]]="",0,YEAR(TbRegistroEntradas[[#This Row],[Data da Competência]])) -> 2018 | M96: =IF(TbRegistroEntradas[[#This Row],[Data do Caixa Previsto]]="",0,MONTH(TbRegistroEntradas[[#This Row],[Data do Caixa Previsto]])) -> 4 | N96: =IF(TbRegistroEntradas[[#This Row],[Data do Caixa Previsto]]="",0,YEAR(TbRegistroEntradas[[#This Row],[Data do Caixa Previsto]])) -> 2018 | O96: =IF(AND(TbRegistroEntradas[[#This Row],[Data do Caixa Previsto]]<TODAY(),TbRegistroEntradas[[#This Row],[Data do Caixa Realizado]]=""),"Vencida","Não Vencida") -> Não Vencida | P96: =IF(TbRegistroEntradas[[#This Row],[Data da Competência]]=TbRegistroEntradas[[#This Row],[Data do Caixa Previsto]],"Vista","Prazo") -> Vista | Q96: =IF(TbRegistroEntradas[[#This Row],[Data do Caixa Realizado]]<>"", IF(TbRegistroEntradas[[#This Row],[Data do Caixa Realizado]]>TbRegistroEntradas[[#This Row],[Data do Caixa Previsto]], TbRegistroEntradas[[#This Row],[Data do Caixa Realizado]]-TbRegistroEntradas[[#This Row],[Data do Caixa Previsto]], 0 ), IF(TODAY()>TbRegistroEntradas[[#This Row],[Data do Caixa Previsto]], TODAY()-TbRegistroEntradas[[#This Row],[Data do Caixa Previsto]], 0 ) ) -> 6
B97: 43283 | C97: 43228 | D97: 43283 | E97: Vendas de mercadorias | F97: Som e imagem | G97: NF4912 | H97: 3862 | I97: =IF(TbRegistroEntradas[[#This Row],[Data do Caixa Realizado]]="",0,MONTH(TbRegistroEntradas[[#This Row],[Data do Caixa Realizado]])) -> 7 | J97: =IF(TbRegistroEntradas[[#This Row],[Data do Caixa Realizado]]="",0,YEAR(TbRegistroEntradas[[#This Row],[Data do Caixa Realizado]])) -> 2018 | K97: =IF(TbRegistroEntradas[[#This Row],[Data da Competência]]="",0,MONTH(TbRegistroEntradas[[#This Row],[Data da Competência]])) -> 5 | L97: =IF(TbRegistroEntradas[[#This Row],[Data da Competência]]="",0,YEAR(TbRegistroEntradas[[#This Row],[Data da Competência]])) -> 2018 | M97: =IF(TbRegistroEntradas[[#This Row],[Data do Caixa Previsto]]="",0,MONTH(TbRegistroEntradas[[#This Row],[Data do Caixa Previsto]])) -> 7 | N97: =IF(TbRegistroEntradas[[#This Row],[Data do Caixa Previsto]]="",0,YEAR(TbRegistroEntradas[[#This Row],[Data do Caixa Previsto]])) -> 2018 | O97: =IF(AND(TbRegistroEntradas[[#This Row],[Data do Caixa Previsto]]<TODAY(),TbRegistroEntradas[[#This Row],[Data do Caixa Realizado]]=""),"Vencida","Não Vencida") -> Não Vencida | P97: =IF(TbRegistroEntradas[[#This Row],[Data da Competência]]=TbRegistroEntradas[[#This Row],[Data do Caixa Previsto]],"Vista","Prazo") -> Prazo | Q97: =IF(TbRegistroEntradas[[#This Row],[Data do Caixa Realizado]]<>"", IF(TbRegistroEntradas[[#This Row],[Data do Caixa Realizado]]>TbRegistroEntradas[[#This Row],[Data do Caixa Previsto]], TbRegistroEntradas[[#This Row],[Data do Caixa Realizado]]-TbRegistroEntradas[[#This Row],[Data do Caixa Previsto]], 0 ), IF(TODAY()>TbRegistroEntradas[[#This Row],[Data do Caixa Previsto]], TODAY()-TbRegistroEntradas[[#This Row],[Data do Caixa Previsto]], 0 ) ) -> 0
B98: 43311 | C98: 43231 | D98: 43279 | E98: Vendas de mercadorias | F98: Livros | G98: NF7104 | H98: 611 | I98: =IF(TbRegistroEntradas[[#This Row],[Data do Caixa Realizado]]="",0,MONTH(TbRegistroEntradas[[#This Row],[Data do Caixa Realizado]])) -> 7 | J98: =IF(TbRegistroEntradas[[#This Row],[Data do Caixa Realizado]]="",0,YEAR(TbRegistroEntradas[[#This Row],[Data do Caixa Realizado]])) -> 2018 | K98: =IF(TbRegistroEntradas[[#This Row],[Data da Competência]]="",0,MONTH(TbRegistroEntradas[[#This Row],[Data da Competência]])) -> 5 | L98: =IF(TbRegistroEntradas[[#This Row],[Data da Competência]]="",0,YEAR(TbRegistroEntradas[[#This Row],[Data da Competência]])) -> 2018 | M98: =IF(TbRegistroEntradas[[#This Row],[Data do Caixa Previsto]]="",0,MONTH(TbRegistroEntradas[[#This Row],[Data do Caixa Previsto]])) -> 6 | N98: =IF(TbRegistroEntradas[[#This Row],[Data do Caixa Previsto]]="",0,YEAR(TbRegistroEntradas[[#This Row],[Data do Caixa Previsto]])) -> 2018 | O98: =IF(AND(TbRegistroEntradas[[#This Row],[Data do Caixa Previsto]]<TODAY(),TbRegistroEntradas[[#This Row],[Data do Caixa Realizado]]=""),"Vencida","Não Vencida") -> Não Vencida | P98: =IF(TbRegistroEntradas[[#This Row],[Data da Competência]]=TbRegistroEntradas[[#This Row],[Data do Caixa Previsto]],"Vista","Prazo") -> Prazo | Q98: =IF(TbRegistroEntradas[[#This Row],[Data do Caixa Realizado]]<>"", IF(TbRegistroEntradas[[#This Row],[Data do Caixa Realizado]]>TbRegistroEntradas[[#This Row],[Data do Caixa Previsto]], TbRegistroEntradas[[#This Row],[Data do Caixa Realizado]]-TbRegistroEntradas[[#This Row],[Data do Caixa Previsto]], 0 ), IF(TODAY()>TbRegistroEntradas[[#This Row],[Data do Caixa Previsto]], TODAY()-TbRegistroEntradas[[#This Row],[Data do Caixa Previsto]], 0 ) ) -> 32
B99: 43233 | C99: 43233 | D99: 43233 | E99: Vendas de mercadorias | F99: Eletrodomésticos | G99: NF6700 | H99: 1486 | I99: =IF(TbRegistroEntradas[[#This Row],[Data do Caixa Realizado]]="",0,MONTH(TbRegistroEntradas[[#This Row],[Data do Caixa Realizado]])) -> 5 | J99: =IF(TbRegistroEntradas[[#This Row],[Data do Caixa Realizado]]="",0,YEAR(TbRegistroEntradas[[#This Row],[Data do Caixa Realizado]])) -> 2018 | K99: =IF(TbRegistroEntradas[[#This Row],[Data da Competência]]="",0,MONTH(TbRegistroEntradas[[#This Row],[Data da Competência]])) -> 5 | L99: =IF(TbRegistroEntradas[[#This Row],[Data da Competência]]="",0,YEAR(TbRegistroEntradas[[#This Row],[Data da Competência]])) -> 2018 | M99: =IF(TbRegistroEntradas[[#This Row],[Data do Caixa Previsto]]="",0,MONTH(TbRegistroEntradas[[#This Row],[Data do Caixa Previsto]])) -> 5 | N99: =IF(TbRegistroEntradas[[#This Row],[Data do Caixa Previsto]]="",0,YEAR(TbRegistroEntradas[[#This Row],[Data do Caixa Previsto]])) -> 2018 | O99: =IF(AND(TbRegistroEntradas[[#This Row],[Data do Caixa Previsto]]<TODAY(),TbRegistroEntradas[[#This Row],[Data do Caixa Realizado]]=""),"Vencida","Não Vencida") -> Não Vencida | P99: =IF(TbRegistroEntradas[[#This Row],[Data da Competência]]=TbRegistroEntradas[[#This Row],[Data do Caixa Previsto]],"Vista","Prazo") -> Vista | Q99: =IF(TbRegistroEntradas[[#This Row],[Data do Caixa Realizado]]<>"", IF(TbRegistroEntradas[[#This Row],[Data do Caixa Realizado]]>TbRegistroEntradas[[#This Row],[Data do Caixa Previsto]], TbRegistroEntradas[[#This Row],[Data do Caixa Realizado]]-TbRegistroEntradas[[#This Row],[Data do Caixa Previsto]], 0 ), IF(TODAY()>TbRegistroEntradas[[#This Row],[Data do Caixa Previsto]], TODAY()-TbRegistroEntradas[[#This Row],[Data do Caixa Previsto]], 0 ) ) -> 0
B100: 43252 | C100: 43241 | D100: 43252 | E100: Vendas de mercadorias | F100: Móveis | G100: NF7947 | H100: 4850 | I100: =IF(TbRegistroEntradas[[#This Row],[Data do Caixa Realizado]]="",0,MONTH(TbRegistroEntradas[[#This Row],[Data do Caixa Realizado]])) -> 6 | J100: =IF(TbRegistroEntradas[[#This Row],[Data do Caixa Realizado]]="",0,YEAR(TbRegistroEntradas[[#This Row],[Data do Caixa Realizado]])) -> 2018 | K100: =IF(TbRegistroEntradas[[#This Row],[Data da Competência]]="",0,MONTH(TbRegistroEntradas[[#This Row],[Data da Competência]])) -> 5 | L100: =IF(TbRegistroEntradas[[#This Row],[Data da Competência]]="",0,YEAR(TbRegistroEntradas[[#This Row],[Data da Competência]])) -> 2018 | M100: =IF(TbRegistroEntradas[[#This Row],[Data do Caixa Previsto]]="",0,MONTH(TbRegistroEntradas[[#This Row],[Data do Caixa Previsto]])) -> 6 | N100: =IF(TbRegistroEntradas[[#This Row],[Data do Caixa Previsto]]="",0,YEAR(TbRegistroEntradas[[#This Row],[Data do Caixa Previsto]])) -> 2018 | O100: =IF(AND(TbRegistroEntradas[[#This Row],[Data do Caixa Previsto]]<TODAY(),TbRegistroEntradas[[#This Row],[Data do Caixa Realizado]]=""),"Vencida","Não Vencida") -> Não Vencida | P100: =IF(TbRegistroEntradas[[#This Row],[Data da Competência]]=TbRegistroEntradas[[#This Row],[Data do Caixa Previsto]],"Vista","Prazo") -> Prazo | Q100: =IF(TbRegistroEntradas[[#This Row],[Data do Caixa Realizado]]<>"", IF(TbRegistroEntradas[[#This Row],[Data do Caixa Realizado]]>TbRegistroEntradas[[#This Row],[Data do Caixa Previsto]], TbRegistroEntradas[[#This Row],[Data do Caixa Realizado]]-TbRegistroEntradas[[#This Row],[Data do Caixa Previsto]], 0 ), IF(TODAY()>TbRegistroEntradas[[#This Row],[Data do Caixa Previsto]], TODAY()-TbRegistroEntradas[[#This Row],[Data do Caixa Previsto]], 0 ) ) -> 0
B101: 43275 | C101: 43244 | D101: 43275 | E101: Vendas de mercadorias | F101: Eletrodomésticos | G101: NF7741 | H101: 3878 | I101: =IF(TbRegistroEntradas[[#This Row],[Data do Caixa Realizado]]="",0,MONTH(TbRegistroEntradas[[#This Row],[Data do Caixa Realizado]])) -> 6 | J101: =IF(TbRegistroEntradas[[#This Row],[Data do Caixa Realizado]]="",0,YEAR(TbRegistroEntradas[[#This Row],[Data do Caixa Realizado]])) -> 2018 | K101: =IF(TbRegistroEntradas[[#This Row],[Data da Competência]]="",0,MONTH(TbRegistroEntradas[[#This Row],[Data da Competência]])) -> 5 | L101: =IF(TbRegistroEntradas[[#This Row],[Data da Competência]]="",0,YEAR(TbRegistroEntradas[[#This Row],[Data da Competência]])) -> 2018 | M101: =IF(TbRegistroEntradas[[#This Row],[Data do Caixa Previsto]]="",0,MONTH(TbRegistroEntradas[[#This Row],[Data do Caixa Previsto]])) -> 6 | N101: =IF(TbRegistroEntradas[[#This Row],[Data do Caixa Previsto]]="",0,YEAR(TbRegistroEntradas[[#This Row],[Data do Caixa Previsto]])) -> 2018 | O101: =IF(AND(TbRegistroEntradas[[#This Row],[Data do Caixa Previsto]]<TODAY(),TbRegistroEntradas[[#This Row],[Data do Caixa Realizado]]=""),"Vencida","Não Vencida") -> Não Vencida | P101: =IF(TbRegistroEntradas[[#This Row],[Data da Competência]]=TbRegistroEntradas[[#This Row],[Data do Caixa Previsto]],"Vista","Prazo") -> Prazo | Q101: =IF(TbRegistroEntradas[[#This Row],[Data do Caixa Realizado]]<>"", IF(TbRegistroEntradas[[#This Row],[Data do Caixa Realizado]]>TbRegistroEntradas[[#This Row],[Data do Caixa Previsto]], TbRegistroEntradas[[#This Row],[Data do Caixa Realizado]]-TbRegistroEntradas[[#This Row],[Data do Caixa Previsto]], 0 ), IF(TODAY()>TbRegistroEntradas[[#This Row],[Data do Caixa Previsto]], TODAY()-TbRegistroEntradas[[#This Row],[Data do Caixa Previsto]], 0 ) ) -> 0
B102: 43275 | C102: 43249 | D102: 43275 | E102: Vendas de mercadorias | F102: Eletrodomésticos | G102: NF3255 | H102: 976 | I102: =IF(TbRegistroEntradas[[#This Row],[Data do Caixa Realizado]]="",0,MONTH(TbRegistroEntradas[[#This Row],[Data do Caixa Realizado]])) -> 6 | J102: =IF(TbRegistroEntradas[[#This Row],[Data do Caixa Realizado]]="",0,YEAR(TbRegistroEntradas[[#This Row],[Data do Caixa Realizado]])) -> 2018 | K102: =IF(TbRegistroEntradas[[#This Row],[Data da Competência]]="",0,MONTH(TbRegistroEntradas[[#This Row],[Data da Competência]])) -> 5 | L102: =IF(TbRegistroEntradas[[#This Row],[Data da Competência]]="",0,YEAR(TbRegistroEntradas[[#This Row],[Data da Competência]])) -> 2018 | M102: =IF(TbRegistroEntradas[[#This Row],[Data do Caixa Previsto]]="",0,MONTH(TbRegistroEntradas[[#This Row],[Data do Caixa Previsto]])) -> 6 | N102: =IF(TbRegistroEntradas[[#This Row],[Data do Caixa Previsto]]="",0,YEAR(TbRegistroEntradas[[#This Row],[Data do Caixa Previsto]])) -> 2018 | O102: =IF(AND(TbRegistroEntradas[[#This Row],[Data do Caixa Previsto]]<TODAY(),TbRegistroEntradas[[#This Row],[Data do Caixa Realizado]]=""),"Vencida","Não Vencida") -> Não Vencida | P102: =IF(TbRegistroEntradas[[#This Row],[Data da Competência]]=TbRegistroEntradas[[#This Row],[Data do Caixa Previsto]],"Vista","Prazo") -> Prazo | Q102: =IF(TbRegistroEntradas[[#This Row],[Data do Caixa Realizado]]<>"", IF(TbRegistroEntradas[[#This Row],[Data do Caixa Realizado]]>TbRegistroEntradas[[#This Row],[Data do Caixa Previsto]], TbRegistroEntradas[[#This Row],[Data do Caixa Realizado]]-TbRegistroEntradas[[#This Row],[Data do Caixa Previsto]], 0 ), IF(TODAY()>TbRegistroEntradas[[#This Row],[Data do Caixa Previsto]], TODAY()-TbRegistroEntradas[[#This Row],[Data do Caixa Previsto]], 0 ) ) -> 0
B103: 43265 | C103: 43250 | D103: 43265 | E103: Vendas de mercadorias | F103: Som e imagem | G103: NF7106 | H103: 3346 | I103: =IF(TbRegistroEntradas[[#This Row],[Data do Caixa Realizado]]="",0,MONTH(TbRegistroEntradas[[#This Row],[Data do Caixa Realizado]])) -> 6 | J103: =IF(TbRegistroEntradas[[#This Row],[Data do Caixa Realizado]]="",0,YEAR(TbRegistroEntradas[[#This Row],[Data do Caixa Realizado]])) -> 2018 | K103: =IF(TbRegistroEntradas[[#This Row],[Data da Competência]]="",0,MONTH(TbRegistroEntradas[[#This Row],[Data da Competência]])) -> 5 | L103: =IF(TbRegistroEntradas[[#This Row],[Data da Competência]]="",0,YEAR(TbRegistroEntradas[[#This Row],[Data da Competência]])) -> 2018 | M103: =IF(TbRegistroEntradas[[#This Row],[Data do Caixa Previsto]]="",0,MONTH(TbRegistroEntradas[[#This Row],[Data do Caixa Previsto]])) -> 6 | N103: =IF(TbRegistroEntradas[[#This Row],[Data do Caixa Previsto]]="",0,YEAR(TbRegistroEntradas[[#This Row],[Data do Caixa Previsto]])) -> 2018 | O103: =IF(AND(TbRegistroEntradas[[#This Row],[Data do Caixa Previsto]]<TODAY(),TbRegistroEntradas[[#This Row],[Data do Caixa Realizado]]=""),"Vencida","Não Vencida") -> Não Vencida | P103: =IF(TbRegistroEntradas[[#This Row],[Data da Competência]]=TbRegistroEntradas[[#This Row],[Data do Caixa Previsto]],"Vista","Prazo") -> Prazo | Q103: =IF(TbRegistroEntradas[[#This Row],[Data do Caixa Realizado]]<>"", IF(TbRegistroEntradas[[#This Row],[Data do Caixa Realizado]]>TbRegistroEntradas[[#This Row],[Data do Caixa Previsto]], TbRegistroEntradas[[#This Row],[Data do Caixa Realizado]]-TbRegistroEntradas[[#This Row],[Data do Caixa Previsto]], 0 ), IF(TODAY()>TbRegistroEntradas[[#This Row],[Data do Caixa Previsto]], TODAY()-TbRegistroEntradas[[#This Row],[Data do Caixa Previsto]], 0 ) ) -> 0
... B123: 43302 | C123: 43297 | D123: 43302 | E123: Vendas de mercadorias | F123: Móveis | G123: NF7941 | H123: 3482 | I123: =IF(TbRegistroEntradas[[#This Row],[Data do Caixa Realizado]]="",0,MONTH(TbRegistroEntradas[[#This Row],[Data do Caixa Realizado]])) -> 7 | J123: =IF(TbRegistroEntradas[[#This Row],[Data do Caixa Realizado]]="",0,YEAR(TbRegistroEntradas[[#This Row],[Data do Caixa Realizado]])) -> 2018 | K123: =IF(TbRegistroEntradas[[#This Row],[Data da Competência]]="",0,MONTH(TbRegistroEntradas[[#This Row],[Data da Competência]])) -> 7 | L123: =IF(TbRegistroEntradas[[#This Row],[Data da Competência]]="",0,YEAR(TbRegistroEntradas[[#This Row],[Data da Competência]])) -> 2018 | M123: =IF(TbRegistroEntradas[[#This Row],[Data do Caixa Previsto]]="",0,MONTH(TbRegistroEntradas[[#This Row],[Data do Caixa Previsto]])) -> 7 | N123: =IF(TbRegistroEntradas[[#This Row],[Data do Caixa Previsto]]="",0,YEAR(TbRegistroEntradas[[#This Row],[Data do Caixa Previsto]])) -> 2018 | O123: =IF(AND(TbRegistroEntradas[[#This Row],[Data do Caixa Previsto]]<TODAY(),TbRegistroEntradas[[#This Row],[Data do Caixa Realizado]]=""),"Vencida","Não Vencida") -> Não Vencida | P123: =IF(TbRegistroEntradas[[#This Row],[Data da Competência]]=TbRegistroEntradas[[#This Row],[Data do Caixa Previsto]],"Vista","Prazo") -> Prazo | Q123: =IF(TbRegistroEntradas[[#This Row],[Data do Caixa Realizado]]<>"", IF(TbRegistroEntradas[[#This Row],[Data do Caixa Realizado]]>TbRegistroEntradas[[#This Row],[Data do Caixa Previsto]], TbRegistroEntradas[[#This Row],[Data do Caixa Realizado]]-TbRegistroEntradas[[#This Row],[Data do Caixa Previsto]], 0 ), IF(TODAY()>TbRegistroEntradas[[#This Row],[Data do Caixa Previsto]], TODAY()-TbRegistroEntradas[[#This Row],[Data do Caixa Previsto]], 0 ) ) -> 0
C124: 43299 | D124: 43346 | E124: Vendas de mercadorias | F124: Móveis | G124: NF3604 | H124: 2071 | I124: =IF(TbRegistroEntradas[[#This Row],[Data do Caixa Realizado]]="",0,MONTH(TbRegistroEntradas[[#This Row],[Data do Caixa Realizado]])) -> 0 | J124: =IF(TbRegistroEntradas[[#This Row],[Data do Caixa Realizado]]="",0,YEAR(TbRegistroEntradas[[#This Row],[Data do Caixa Realizado]])) -> 0 | K124: =IF(TbRegistroEntradas[[#This Row],[Data da Competência]]="",0,MONTH(TbRegistroEntradas[[#This Row],[Data da Competência]])) -> 7 | L124: =IF(TbRegistroEntradas[[#This Row],[Data da Competência]]="",0,YEAR(TbRegistroEntradas[[#This Row],[Data da Competência]])) -> 2018 | M124: =IF(TbRegistroEntradas[[#This Row],[Data do Caixa Previsto]]="",0,MONTH(TbRegistroEntradas[[#This Row],[Data do Caixa Previsto]])) -> 9 | N124: =IF(TbRegistroEntradas[[#This Row],[Data do Caixa Previsto]]="",0,YEAR(TbRegistroEntradas[[#This Row],[Data do Caixa Previsto]])) -> 2018 | O124: =IF(AND(TbRegistroEntradas[[#This Row],[Data do Caixa Previsto]]<TODAY(),TbRegistroEntradas[[#This Row],[Data do Caixa Realizado]]=""),"Vencida","Não Vencida") -> Vencida | P124: =IF(TbRegistroEntradas[[#This Row],[Data da Competência]]=TbRegistroEntradas[[#This Row],[Data do Caixa Previsto]],"Vista","Prazo") -> Prazo | Q124: =IF(TbRegistroEntradas[[#This Row],[Data do Caixa Realizado]]<>"", IF(TbRegistroEntradas[[#This Row],[Data do Caixa Realizado]]>TbRegistroEntradas[[#This Row],[Data do Caixa Previsto]], TbRegistroEntradas[[#This Row],[Data do Caixa Realizado]]-TbRegistroEntradas[[#This Row],[Data do Caixa Previsto]], 0 ), IF(TODAY()>TbRegistroEntradas[[#This Row],[Data do Caixa Previsto]], TODAY()-TbRegistroEntradas[[#This Row],[Data do Caixa Previsto]], 0 ) ) -> 2007
C125: 43304 | D125: 43304 | E125: Vendas de mercadorias | F125: Som e imagem | G125: NF4605 | H125: 4258 | I125: =IF(TbRegistroEntradas[[#This Row],[Data do Caixa Realizado]]="",0,MONTH(TbRegistroEntradas[[#This Row],[Data do Caixa Realizado]])) -> 0 | J125: =IF(TbRegistroEntradas[[#This Row],[Data do Caixa Realizado]]="",0,YEAR(TbRegistroEntradas[[#This Row],[Data do Caixa Realizado]])) -> 0 | K125: =IF(TbRegistroEntradas[[#This Row],[Data da Competência]]="",0,MONTH(TbRegistroEntradas[[#This Row],[Data da Competência]])) -> 7 | L125: =IF(TbRegistroEntradas[[#This Row],[Data da Competência]]="",0,YEAR(TbRegistroEntradas[[#This Row],[Data da Competência]])) -> 2018 | M125: =IF(TbRegistroEntradas[[#This Row],[Data do Caixa Previsto]]="",0,MONTH(TbRegistroEntradas[[#This Row],[Data do Caixa Previsto]])) -> 7 | N125: =IF(TbRegistroEntradas[[#This Row],[Data do Caixa Previsto]]="",0,YEAR(TbRegistroEntradas[[#This Row],[Data do Caixa Previsto]])) -> 2018 | O125: =IF(AND(TbRegistroEntradas[[#This Row],[Data do Caixa Previsto]]<TODAY(),TbRegistroEntradas[[#This Row],[Data do Caixa Realizado]]=""),"Vencida","Não Vencida") -> Vencida | P125: =IF(TbRegistroEntradas[[#This Row],[Data da Competência]]=TbRegistroEntradas[[#This Row],[Data do Caixa Previsto]],"Vista","Prazo") -> Vista | Q125: =IF(TbRegistroEntradas[[#This Row],[Data do Caixa Realizado]]<>"", IF(TbRegistroEntradas[[#This Row],[Data do Caixa Realizado]]>TbRegistroEntradas[[#This Row],[Data do Caixa Previsto]], TbRegistroEntradas[[#This Row],[Data do Caixa Realizado]]-TbRegistroEntradas[[#This Row],[Data do Caixa Previsto]], 0 ), IF(TODAY()>TbRegistroEntradas[[#This Row],[Data do Caixa Previsto]], TODAY()-TbRegistroEntradas[[#This Row],[Data do Caixa Previsto]], 0 ) ) -> 2049
B126: 43350 | C126: 43306 | D126: 43350 | E126: Vendas de mercadorias | F126: Informática | G126: NF1759 | H126: 4383 | I126: =IF(TbRegistroEntradas[[#This Row],[Data do Caixa Realizado]]="",0,MONTH(TbRegistroEntradas[[#This Row],[Data do Caixa Realizado]])) -> 9 | J126: =IF(TbRegistroEntradas[[#This Row],[Data do Caixa Realizado]]="",0,YEAR(TbRegistroEntradas[[#This Row],[Data do Caixa Realizado]])) -> 2018 | K126: =IF(TbRegistroEntradas[[#This Row],[Data da Competência]]="",0,MONTH(TbRegistroEntradas[[#This Row],[Data da Competência]])) -> 7 | L126: =IF(TbRegistroEntradas[[#This Row],[Data da Competência]]="",0,YEAR(TbRegistroEntradas[[#This Row],[Data da Competência]])) -> 2018 | M126: =IF(TbRegistroEntradas[[#This Row],[Data do Caixa Previsto]]="",0,MONTH(TbRegistroEntradas[[#This Row],[Data do Caixa Previsto]])) -> 9 | N126: =IF(TbRegistroEntradas[[#This Row],[Data do Caixa Previsto]]="",0,YEAR(TbRegistroEntradas[[#This Row],[Data do Caixa Previsto]])) -> 2018 | O126: =IF(AND(TbRegistroEntradas[[#This Row],[Data do Caixa Previsto]]<TODAY(),TbRegistroEntradas[[#This Row],[Data do Caixa Realizado]]=""),"Vencida","Não Vencida") -> Não Vencida | P126: =IF(TbRegistroEntradas[[#This Row],[Data da Competência]]=TbRegistroEntradas[[#This Row],[Data do Caixa Previsto]],"Vista","Prazo") -> Prazo | Q126: =IF(TbRegistroEntradas[[#This Row],[Data do Caixa Realizado]]<>"", IF(TbRegistroEntradas[[#This Row],[Data do Caixa Realizado]]>TbRegistroEntradas[[#This Row],[Data do Caixa Previsto]], TbRegistroEntradas[[#This Row],[Data do Caixa Realizado]]-TbRegistroEntradas[[#This Row],[Data do Caixa Previsto]], 0 ), IF(TODAY()>TbRegistroEntradas[[#This Row],[Data do Caixa Previsto]], TODAY()-TbRegistroEntradas[[#This Row],[Data do Caixa Previsto]], 0 ) ) -> 0
...

Sheet RegistroSaídas
B1: Educaçãoweb | H1: REGISTRO DAS SAÍDAS DE CAIXA
B3: Data do Caixa Realizado | C3: Data da Competência | D3: Data do Caixa Previsto | E3: Conta Nível 1 | F3: Conta Nível 2 | G3: Histórico | H3: Valor | I3: Mês Caixa | J3: Ano Caixa | K3: Mês Competência | L3: Ano Competência | M3: Mês Previsto | N3: Ano Previsto | O3: Dias de Atraso
B4: 43015.689 | C4: 42957 | D4: 43015.689 | E4: Compra de mercadorias | F4: Som e imagem | G4: NF4400 | H4: 4021 | I4: =IF([1]!TbRegistroSaídas[[#This Row],[Data do Caixa Realizado]]="",0,MONTH([1]!TbRegistroSaídas[[#This Row],[Data do Caixa Realizado]])) -> 10 | J4: =IF([1]!TbRegistroSaídas[[#This Row],[Data do Caixa Realizado]]="",0,YEAR([1]!TbRegistroSaídas[[#This Row],[Data do Caixa Realizado]])) -> 2017 | K4: =IF([1]!TbRegistroSaídas[[#This Row],[Data da Competência]]="",0,MONTH([1]!TbRegistroSaídas[[#This Row],[Data da Competência]])) -> 8 | L4: =IF([1]!TbRegistroSaídas[[#This Row],[Data da Competência]]="",0,YEAR([1]!TbRegistroSaídas[[#This Row],[Data da Competência]])) -> 2017 | M4: =IF([1]!TbRegistroSaídas[[#This Row],[Data do Caixa Previsto]]="",0,MONTH([1]!TbRegistroSaídas[[#This Row],[Data do Caixa Previsto]])) -> 10 | N4: =IF([1]!TbRegistroSaídas[[#This Row],[Data do Caixa Previsto]]="",0,YEAR([1]!TbRegistroSaídas[[#This Row],[Data do Caixa Previsto]])) -> 2017 | O4: =IF(TbRegistroSaídas[[#This Row],[Data do Caixa Realizado]]<>"", IF(TbRegistroSaídas[[#This Row],[Data do Caixa Realizado]]>TbRegistroSaídas[[#This Row],[Data do Caixa Previsto]], TbRegistroSaídas[[#This Row],[Data do Caixa Realizado]]-TbRegistroSaídas[[#This Row],[Data do Caixa Previsto]], 0 ), IF(TODAY()>TbRegistroSaídas[[#This Row],[Data do Caixa Previsto]], TODAY()-TbRegistroSaídas[[#This Row],[Data do Caixa Previsto]], 0 ) ) -> 0
B5: 42995.832 | C5: 42960 | D5: 42995.832 | E5: Compra de mercadorias | F5: Vestuário | G5: NF5356 | H5: 651 | I5: =IF([1]!TbRegistroSaídas[[#This Row],[Data do Caixa Realizado]]="",0,MONTH([1]!TbRegistroSaídas[[#This Row],[Data do Caixa Realizado]])) -> 9 | J5: =IF([1]!TbRegistroSaídas[[#This Row],[Data do Caixa Realizado]]="",0,YEAR([1]!TbRegistroSaídas[[#This Row],[Data do Caixa Realizado]])) -> 2017 | K5: =IF([1]!TbRegistroSaídas[[#This Row],[Data da Competência]]="",0,MONTH([1]!TbRegistroSaídas[[#This Row],[Data da Competência]])) -> 8 | L5: =IF([1]!TbRegistroSaídas[[#This Row],[Data da Competência]]="",0,YEAR([1]!TbRegistroSaídas[[#This Row],[Data da Competência]])) -> 2017 | M5: =IF([1]!TbRegistroSaídas[[#This Row],[Data do Caixa Previsto]]="",0,MONTH([1]!TbRegistroSaídas[[#This Row],[Data do Caixa Previsto]])) -> 9 | N5: =IF([1]!TbRegistroSaídas[[#This Row],[Data do Caixa Previsto]]="",0,YEAR([1]!TbRegistroSaídas[[#This Row],[Data do Caixa Previsto]])) -> 2017 | O5: =IF(TbRegistroSaídas[[#This Row],[Data do Caixa Realizado]]<>"", IF(TbRegistroSaídas[[#This Row],[Data do Caixa Realizado]]>TbRegistroSaídas[[#This Row],[Data do Caixa Previsto]], TbRegistroSaídas[[#This Row],[Data do Caixa Realizado]]-TbRegistroSaídas[[#This Row],[Data do Caixa Previsto]], 0 ), IF(TODAY()>TbRegistroSaídas[[#This Row],[Data do Caixa Previsto]], TODAY()-TbRegistroSaídas[[#This Row],[Data do Caixa Previsto]], 0 ) ) -> 0
B6: 42983.822 | C6: 42965 | D6: 42983.822 | E6: Compra de mercadorias | F6: Som e imagem | G6: NF1847 | H6: 131 | I6: =IF([1]!TbRegistroSaídas[[#This Row],[Data do Caixa Realizado]]="",0,MONTH([1]!TbRegistroSaídas[[#This Row],[Data do Caixa Realizado]])) -> 9 | J6: =IF([1]!TbRegistroSaídas[[#This Row],[Data do Caixa Realizado]]="",0,YEAR([1]!TbRegistroSaídas[[#This Row],[Data do Caixa Realizado]])) -> 2017 | K6: =IF([1]!TbRegistroSaídas[[#This Row],[Data da Competência]]="",0,MONTH([1]!TbRegistroSaídas[[#This Row],[Data da Competência]])) -> 8 | L6: =IF([1]!TbRegistroSaídas[[#This Row],[Data da Competência]]="",0,YEAR([1]!TbRegistroSaídas[[#This Row],[Data da Competência]])) -> 2017 | M6: =IF([1]!TbRegistroSaídas[[#This Row],[Data do Caixa Previsto]]="",0,MONTH([1]!TbRegistroSaídas[[#This Row],[Data do Caixa Previsto]])) -> 9 | N6: =IF([1]!TbRegistroSaídas[[#This Row],[Data do Caixa Previsto]]="",0,YEAR([1]!TbRegistroSaídas[[#This Row],[Data do Caixa Previsto]])) -> 2017 | O6: =IF(TbRegistroSaídas[[#This Row],[Data do Caixa Realizado]]<>"", IF(TbRegistroSaídas[[#This Row],[Data do Caixa Realizado]]>TbRegistroSaídas[[#This Row],[Data do Caixa Previsto]], TbRegistroSaídas[[#This Row],[Data do Caixa Realizado]]-TbRegistroSaídas[[#This Row],[Data do Caixa Previsto]], 0 ), IF(TODAY()>TbRegistroSaídas[[#This Row],[Data do Caixa Previsto]], TODAY()-TbRegistroSaídas[[#This Row],[Data do Caixa Previsto]], 0 ) ) -> 0
B7: 43004.4 | C7: 42970 | D7: 43004.4 | E7: Compra de mercadorias | F7: Som e imagem | G7: NF7011 | H7: 803 | I7: =IF([1]!TbRegistroSaídas[[#This Row],[Data do Caixa Realizado]]="",0,MONTH([1]!TbRegistroSaídas[[#This Row],[Data do Caixa Realizado]])) -> 9 | J7: =IF([1]!TbRegistroSaídas[[#This Row],[Data do Caixa Realizado]]="",0,YEAR([1]!TbRegistroSaídas[[#This Row],[Data do Caixa Realizado]])) -> 2017 | K7: =IF([1]!TbRegistroSaídas[[#This Row],[Data da Competência]]="",0,MONTH([1]!TbRegistroSaídas[[#This Row],[Data da Competência]])) -> 8 | L7: =IF([1]!TbRegistroSaídas[[#This Row],[Data da Competência]]="",0,YEAR([1]!TbRegistroSaídas[[#This Row],[Data da Competência]])) -> 2017 | M7: =IF([1]!TbRegistroSaídas[[#This Row],[Data do Caixa Previsto]]="",0,MONTH([1]!TbRegistroSaídas[[#This Row],[Data do Caixa Previsto]])) -> 9 | N7: =IF([1]!TbRegistroSaídas[[#This Row],[Data do Caixa Previsto]]="",0,YEAR([1]!TbRegistroSaídas[[#This Row],[Data do Caixa Previsto]])) -> 2017 | O7: =IF(TbRegistroSaídas[[#This Row],[Data do Caixa Realizado]]<>"", IF(TbRegistroSaídas[[#This Row],[Data do Caixa Realizado]]>TbRegistroSaídas[[#This Row],[Data do Caixa Previsto]], TbRegistroSaídas[[#This Row],[Data do Caixa Realizado]]-TbRegistroSaídas[[#This Row],[Data do Caixa Previsto]], 0 ), IF(TODAY()>TbRegistroSaídas[[#This Row],[Data do Caixa Previsto]], TODAY()-TbRegistroSaídas[[#This Row],[Data do Caixa Previsto]], 0 ) ) -> 0
B8: 43002.058 | C8: 42971 | D8: 43002.058 | E8: Compra de mercadorias | F8: Vestuário | G8: NF7746 | H8: 4460 | I8: =IF([1]!TbRegistroSaídas[[#This Row],[Data do Caixa Realizado]]="",0,MONTH([1]!TbRegistroSaídas[[#This Row],[Data do Caixa Realizado]])) -> 9 | J8: =IF([1]!TbRegistroSaídas[[#This Row],[Data do Caixa Realizado]]="",0,YEAR([1]!TbRegistroSaídas[[#This Row],[Data do Caixa Realizado]])) -> 2017 | K8: =IF([1]!TbRegistroSaídas[[#This Row],[Data da Competência]]="",0,MONTH([1]!TbRegistroSaídas[[#This Row],[Data da Competência]])) -> 8 | L8: =IF([1]!TbRegistroSaídas[[#This Row],[Data da Competência]]="",0,YEAR([1]!TbRegistroSaídas[[#This Row],[Data da Competência]])) -> 2017 | M8: =IF([1]!TbRegistroSaídas[[#This Row],[Data do Caixa Previsto]]="",0,MONTH([1]!TbRegistroSaídas[[#This Row],[Data do Caixa Previsto]])) -> 9 | N8: =IF([1]!TbRegistroSaídas[[#This Row],[Data do Caixa Previsto]]="",0,YEAR([1]!TbRegistroSaídas[[#This Row],[Data do Caixa Previsto]])) -> 2017 | O8: =IF(TbRegistroSaídas[[#This Row],[Data do Caixa Realizado]]<>"", IF(TbRegistroSaídas[[#This Row],[Data do Caixa Realizado]]>TbRegistroSaídas[[#This Row],[Data do Caixa Previsto]], TbRegistroSaídas[[#This Row],[Data do Caixa Realizado]]-TbRegistroSaídas[[#This Row],[Data do Caixa Previsto]], 0 ), IF(TODAY()>TbRegistroSaídas[[#This Row],[Data do Caixa Previsto]], TODAY()-TbRegistroSaídas[[#This Row],[Data do Caixa Previsto]], 0 ) ) -> 0
B9: 42980.359 | C9: 42972 | D9: 42980.359 | E9: Compra de mercadorias | F9: Informática | G9: NF1507 | H9: 299 | I9: =IF([1]!TbRegistroSaídas[[#This Row],[Data do Caixa Realizado]]="",0,MONTH([1]!TbRegistroSaídas[[#This Row],[Data do Caixa Realizado]])) -> 9 | J9: =IF([1]!TbRegistroSaídas[[#This Row],[Data do Caixa Realizado]]="",0,YEAR([1]!TbRegistroSaídas[[#This Row],[Data do Caixa Realizado]])) -> 2017 | K9: =IF([1]!TbRegistroSaídas[[#This Row],[Data da Competência]]="",0,MONTH([1]!TbRegistroSaídas[[#This Row],[Data da Competência]])) -> 8 | L9: =IF([1]!TbRegistroSaídas[[#This Row],[Data da Competência]]="",0,YEAR([1]!TbRegistroSaídas[[#This Row],[Data da Competência]])) -> 2017 | M9: =IF([1]!TbRegistroSaídas[[#This Row],[Data do Caixa Previsto]]="",0,MONTH([1]!TbRegistroSaídas[[#This Row],[Data do Caixa Previsto]])) -> 9 | N9: =IF([1]!TbRegistroSaídas[[#This Row],[Data do Caixa Previsto]]="",0,YEAR([1]!TbRegistroSaídas[[#This Row],[Data do Caixa Previsto]])) -> 2017 | O9: =IF(TbRegistroSaídas[[#This Row],[Data do Caixa Realizado]]<>"", IF(TbRegistroSaídas[[#This Row],[Data do Caixa Realizado]]>TbRegistroSaídas[[#This Row],[Data do Caixa Previsto]], TbRegistroSaídas[[#This Row],[Data do Caixa Realizado]]-TbRegistroSaídas[[#This Row],[Data do Caixa Previsto]], 0 ), IF(TODAY()>TbRegistroSaídas[[#This Row],[Data do Caixa Previsto]], TODAY()-TbRegistroSaídas[[#This Row],[Data do Caixa Previsto]], 0 ) ) -> 0
B10: 43014.597 | C10: 42976 | D10: 43014.597 | E10: Compra de mercadorias | F10: Vestuário | G10: NF5445 | H10: 618 | I10: =IF([1]!TbRegistroSaídas[[#This Row],[Data do Caixa Realizado]]="",0,MONTH([1]!TbRegistroSaídas[[#This Row],[Data do Caixa Realizado]])) -> 10 | J10: =IF([1]!TbRegistroSaídas[[#This Row],[Data do Caixa Realizado]]="",0,YEAR([1]!TbRegistroSaídas[[#This Row],[Data do Caixa Realizado]])) -> 2017 | K10: =IF([1]!TbRegistroSaídas[[#This Row],[Data da Competência]]="",0,MONTH([1]!TbRegistroSaídas[[#This Row],[Data da Competência]])) -> 8 | L10: =IF([1]!TbRegistroSaídas[[#This Row],[Data da Competência]]="",0,YEAR([1]!TbRegistroSaídas[[#This Row],[Data da Competência]])) -> 2017 | M10: =IF([1]!TbRegistroSaídas[[#This Row],[Data do Caixa Previsto]]="",0,MONTH([1]!TbRegistroSaídas[[#This Row],[Data do Caixa Previsto]])) -> 10 | N10: =IF([1]!TbRegistroSaídas[[#This Row],[Data do Caixa Previsto]]="",0,YEAR([1]!TbRegistroSaídas[[#This Row],[Data do Caixa Previsto]])) -> 2017 | O10: =IF(TbRegistroSaídas[[#This Row],[Data do Caixa Realizado]]<>"", IF(TbRegistroSaídas[[#This Row],[Data do Caixa Realizado]]>TbRegistroSaídas[[#This Row],[Data do Caixa Previsto]], TbRegistroSaídas[[#This Row],[Data do Caixa Realizado]]-TbRegistroSaídas[[#This Row],[Data do Caixa Previsto]], 0 ), IF(TODAY()>TbRegistroSaídas[[#This Row],[Data do Caixa Previsto]], TODAY()-TbRegistroSaídas[[#This Row],[Data do Caixa Previsto]], 0 ) ) -> 0
B11: 42990.112 | C11: 42979 | D11: 42980.557 | E11: Compra de mercadorias | F11: Vestuário | G11: NF7526 | H11: 2505 | I11: =IF([1]!TbRegistroSaídas[[#This Row],[Data do Caixa Realizado]]="",0,MONTH([1]!TbRegistroSaídas[[#This Row],[Data do Caixa Realizado]])) -> 9 | J11: =IF([1]!TbRegistroSaídas[[#This Row],[Data do Caixa Realizado]]="",0,YEAR([1]!TbRegistroSaídas[[#This Row],[Data do Caixa Realizado]])) -> 2017 | K11: =IF([1]!TbRegistroSaídas[[#This Row],[Data da Competência]]="",0,MONTH([1]!TbRegistroSaídas[[#This Row],[Data da Competência]])) -> 9 | L11: =IF([1]!TbRegistroSaídas[[#This Row],[Data da Competência]]="",0,YEAR([1]!TbRegistroSaídas[[#This Row],[Data da Competência]])) -> 2017 | M11: =IF([1]!TbRegistroSaídas[[#This Row],[Data do Caixa Previsto]]="",0,MONTH([1]!TbRegistroSaídas[[#This Row],[Data do Caixa Previsto]])) -> 9 | N11: =IF([1]!TbRegistroSaídas[[#This Row],[Data do Caixa Previsto]]="",0,YEAR([1]!TbRegistroSaídas[[#This Row],[Data do Caixa Previsto]])) -> 2017 | O11: =IF(TbRegistroSaídas[[#This Row],[Data do Caixa Realizado]]<>"", IF(TbRegistroSaídas[[#This Row],[Data do Caixa Realizado]]>TbRegistroSaídas[[#This Row],[Data do Caixa Previsto]], TbRegistroSaídas[[#This Row],[Data do Caixa Realizado]]-TbRegistroSaídas[[#This Row],[Data do Caixa Previsto]], 0 ), IF(TODAY()>TbRegistroSaídas[[#This Row],[Data do Caixa Previsto]], TODAY()-TbRegistroSaídas[[#This Row],[Data do Caixa Previsto]], 0 ) ) -> 9.5551237
B12: 42987.418 | C12: 42982 | D12: 42987.418 | E12: Compra de mercadorias | F12: Som e imagem | G12: NF7559 | H12: 817 | I12: =IF([1]!TbRegistroSaídas[[#This Row],[Data do Caixa Realizado]]="",0,MONTH([1]!TbRegistroSaídas[[#This Row],[Data do Caixa Realizado]])) -> 9 | J12: =IF([1]!TbRegistroSaídas[[#This Row],[Data do Caixa Realizado]]="",0,YEAR([1]!TbRegistroSaídas[[#This Row],[Data do Caixa Realizado]])) -> 2017 | K12: =IF([1]!TbRegistroSaídas[[#This Row],[Data da Competência]]="",0,MONTH([1]!TbRegistroSaídas[[#This Row],[Data da Competência]])) -> 9 | L12: =IF([1]!TbRegistroSaídas[[#This Row],[Data da Competência]]="",0,YEAR([1]!TbRegistroSaídas[[#This Row],[Data da Competência]])) -> 2017 | M12: =IF([1]!TbRegistroSaídas[[#This Row],[Data do Caixa Previsto]]="",0,MONTH([1]!TbRegistroSaídas[[#This Row],[Data do Caixa Previsto]])) -> 9 | N12: =IF([1]!TbRegistroSaídas[[#This Row],[Data do Caixa Previsto]]="",0,YEAR([1]!TbRegistroSaídas[[#This Row],[Data do Caixa Previsto]])) -> 2017 | O12: =IF(TbRegistroSaídas[[#This Row],[Data do Caixa Realizado]]<>"", IF(TbRegistroSaídas[[#This Row],[Data do Caixa Realizado]]>TbRegistroSaídas[[#This Row],[Data do Caixa Previsto]], TbRegistroSaídas[[#This Row],[Data do Caixa Realizado]]-TbRegistroSaídas[[#This Row],[Data do Caixa Previsto]], 0 ), IF(TODAY()>TbRegistroSaídas[[#This Row],[Data do Caixa Previsto]], TODAY()-TbRegistroSaídas[[#This Row],[Data do Caixa Previsto]], 0 ) ) -> 0
C13: 42984 | D13: 42984.703 | E13: Compra de mercadorias | F13: Informática | G13: NF9357 | H13: 1565 | I13: =IF([1]!TbRegistroSaídas[[#This Row],[Data do Caixa Realizado]]="",0,MONTH([1]!TbRegistroSaídas[[#This Row],[Data do Caixa Realizado]])) -> 0 | J13: =IF([1]!TbRegistroSaídas[[#This Row],[Data do Caixa Realizado]]="",0,YEAR([1]!TbRegistroSaídas[[#This Row],[Data do Caixa Realizado]])) -> 0 | K13: =IF([1]!TbRegistroSaídas[[#This Row],[Data da Competência]]="",0,MONTH([1]!TbRegistroSaídas[[#This Row],[Data da Competência]])) -> 9 | L13: =IF([1]!TbRegistroSaídas[[#This Row],[Data da Competência]]="",0,YEAR([1]!TbRegistroSaídas[[#This Row],[Data da Competência]])) -> 2017 | M13: =IF([1]!TbRegistroSaídas[[#This Row],[Data do Caixa Previsto]]="",0,MONTH([1]!TbRegistroSaídas[[#This Row],[Data do Caixa Previsto]])) -> 9 | N13: =IF([1]!TbRegistroSaídas[[#This Row],[Data do Caixa Previsto]]="",0,YEAR([1]!TbRegistroSaídas[[#This Row],[Data do Caixa Previsto]])) -> 2017 | O13: =IF(TbRegistroSaídas[[#This Row],[Data do Caixa Realizado]]<>"", IF(TbRegistroSaídas[[#This Row],[Data do Caixa Realizado]]>TbRegistroSaídas[[#This Row],[Data do Caixa Previsto]], TbRegistroSaídas[[#This Row],[Data do Caixa Realizado]]-TbRegistroSaídas[[#This Row],[Data do Caixa Previsto]], 0 ), IF(TODAY()>TbRegistroSaídas[[#This Row],[Data do Caixa Previsto]], TODAY()-TbRegistroSaídas[[#This Row],[Data do Caixa Previsto]], 0 ) ) -> 2368.297
C14: 42990 | D14: 43020.234 | E14: Compra de mercadorias | F14: Livros | G14: NF3898 | H14: 1357 | I14: =IF([1]!TbRegistroSaídas[[#This Row],[Data do Caixa Realizado]]="",0,MONTH([1]!TbRegistroSaídas[[#This Row],[Data do Caixa Realizado]])) -> 0 | J14: =IF([1]!TbRegistroSaídas[[#This Row],[Data do Caixa Realizado]]="",0,YEAR([1]!TbRegistroSaídas[[#This Row],[Data do Caixa Realizado]])) -> 0 | K14: =IF([1]!TbRegistroSaídas[[#This Row],[Data da Competência]]="",0,MONTH([1]!TbRegistroSaídas[[#This Row],[Data da Competência]])) -> 9 | L14: =IF([1]!TbRegistroSaídas[[#This Row],[Data da Competência]]="",0,YEAR([1]!TbRegistroSaídas[[#This Row],[Data da Competência]])) -> 2017 | M14: =IF([1]!TbRegistroSaídas[[#This Row],[Data do Caixa Previsto]]="",0,MONTH([1]!TbRegistroSaídas[[#This Row],[Data do Caixa Previsto]])) -> 10 | N14: =IF([1]!TbRegistroSaídas[[#This Row],[Data do Caixa Previsto]]="",0,YEAR([1]!TbRegistroSaídas[[#This Row],[Data do Caixa Previsto]])) -> 2017 | O14: =IF(TbRegistroSaídas[[#This Row],[Data do Caixa Realizado]]<>"", IF(TbRegistroSaídas[[#This Row],[Data do Caixa Realizado]]>TbRegistroSaídas[[#This Row],[Data do Caixa Previsto]], TbRegistroSaídas[[#This Row],[Data do Caixa Realizado]]-TbRegistroSaídas[[#This Row],[Data do Caixa Previsto]], 0 ), IF(TODAY()>TbRegistroSaídas[[#This Row],[Data do Caixa Previsto]], TODAY()-TbRegistroSaídas[[#This Row],[Data do Caixa Previsto]], 0 ) ) -> 2332.7664
B15: 42991 | C15: 42991 | D15: 42991 | E15: Compra de mercadorias | F15: Livros | G15: NF7275 | H15: 4739 | I15: =IF([1]!TbRegistroSaídas[[#This Row],[Data do Caixa Realizado]]="",0,MONTH([1]!TbRegistroSaídas[[#This Row],[Data do Caixa Realizado]])) -> 9 | J15: =IF([1]!TbRegistroSaídas[[#This Row],[Data do Caixa Realizado]]="",0,YEAR([1]!TbRegistroSaídas[[#This Row],[Data do Caixa Realizado]])) -> 2017 | K15: =IF([1]!TbRegistroSaídas[[#This Row],[Data da Competência]]="",0,MONTH([1]!TbRegistroSaídas[[#This Row],[Data da Competência]])) -> 9 | L15: =IF([1]!TbRegistroSaídas[[#This Row],[Data da Competência]]="",0,YEAR([1]!TbRegistroSaídas[[#This Row],[Data da Competência]])) -> 2017 | M15: =IF([1]!TbRegistroSaídas[[#This Row],[Data do Caixa Previsto]]="",0,MONTH([1]!TbRegistroSaídas[[#This Row],[Data do Caixa Previsto]])) -> 9 | N15: =IF([1]!TbRegistroSaídas[[#This Row],[Data do Caixa Previsto]]="",0,YEAR([1]!TbRegistroSaídas[[#This Row],[Data do Caixa Previsto]])) -> 2017 | O15: =IF(TbRegistroSaídas[[#This Row],[Data do Caixa Realizado]]<>"", IF(TbRegistroSaídas[[#This Row],[Data do Caixa Realizado]]>TbRegistroSaídas[[#This Row],[Data do Caixa Previsto]], TbRegistroSaídas[[#This Row],[Data do Caixa Realizado]]-TbRegistroSaídas[[#This Row],[Data do Caixa Previsto]], 0 ), IF(TODAY()>TbRegistroSaídas[[#This Row],[Data do Caixa Previsto]], TODAY()-TbRegistroSaídas[[#This Row],[Data do Caixa Previsto]], 0 ) ) -> 0
B16: 42992 | C16: 42992 | D16: 42992 | E16: Compra de mercadorias | F16: Som e imagem | G16: NF9591 | H16: 4675 | I16: =IF([1]!TbRegistroSaídas[[#This Row],[Data do Caixa Realizado]]="",0,MONTH([1]!TbRegistroSaídas[[#This Row],[Data do Caixa Realizado]])) -> 9 | J16: =IF([1]!TbRegistroSaídas[[#This Row],[Data do Caixa Realizado]]="",0,YEAR([1]!TbRegistroSaídas[[#This Row],[Data do Caixa Realizado]])) -> 2017 | K16: =IF([1]!TbRegistroSaídas[[#This Row],[Data da Competência]]="",0,MONTH([1]!TbRegistroSaídas[[#This Row],[Data da Competência]])) -> 9 | L16: =IF([1]!TbRegistroSaídas[[#This Row],[Data da Competência]]="",0,YEAR([1]!TbRegistroSaídas[[#This Row],[Data da Competência]])) -> 2017 | M16: =IF([1]!TbRegistroSaídas[[#This Row],[Data do Caixa Previsto]]="",0,MONTH([1]!TbRegistroSaídas[[#This Row],[Data do Caixa Previsto]])) -> 9 | N16: =IF([1]!TbRegistroSaídas[[#This Row],[Data do Caixa Previsto]]="",0,YEAR([1]!TbRegistroSaídas[[#This Row],[Data do Caixa Previsto]])) -> 2017 | O16: =IF(TbRegistroSaídas[[#This Row],[Data do Caixa Realizado]]<>"", IF(TbRegistroSaídas[[#This Row],[Data do Caixa Realizado]]>TbRegistroSaídas[[#This Row],[Data do Caixa Previsto]], TbRegistroSaídas[[#This Row],[Data do Caixa Realizado]]-TbRegistroSaídas[[#This Row],[Data do Caixa Previsto]], 0 ), IF(TODAY()>TbRegistroSaídas[[#This Row],[Data do Caixa Previsto]], TODAY()-TbRegistroSaídas[[#This Row],[Data do Caixa Previsto]], 0 ) ) -> 0
B17: 43004.132 | C17: 42997 | D17: 43004.132 | E17: Compra de mercadorias | F17: Vestuário | G17: NF3104 | H17: 1797 | I17: =IF([1]!TbRegistroSaídas[[#This Row],[Data do Caixa Realizado]]="",0,MONTH([1]!TbRegistroSaídas[[#This Row],[Data do Caixa Realizado]])) -> 9 | J17: =IF([1]!TbRegistroSaídas[[#This Row],[Data do Caixa Realizado]]="",0,YEAR([1]!TbRegistroSaídas[[#This Row],[Data do Caixa Realizado]])) -> 2017 | K17: =IF([1]!TbRegistroSaídas[[#This Row],[Data da Competência]]="",0,MONTH([1]!TbRegistroSaídas[[#This Row],[Data da Competência]])) -> 9 | L17: =IF([1]!TbRegistroSaídas[[#This Row],[Data da Competência]]="",0,YEAR([1]!TbRegistroSaídas[[#This Row],[Data da Competência]])) -> 2017 | M17: =IF([1]!TbRegistroSaídas[[#This Row],[Data do Caixa Previsto]]="",0,MONTH([1]!TbRegistroSaídas[[#This Row],[Data do Caixa Previsto]])) -> 9 | N17: =IF([1]!TbRegistroSaídas[[#This Row],[Data do Caixa Previsto]]="",0,YEAR([1]!TbRegistroSaídas[[#This Row],[Data do Caixa Previsto]])) -> 2017 | O17: =IF(TbRegistroSaídas[[#This Row],[Data do Caixa Realizado]]<>"", IF(TbRegistroSaídas[[#This Row],[Data do Caixa Realizado]]>TbRegistroSaídas[[#This Row],[Data do Caixa Previsto]], TbRegistroSaídas[[#This Row],[Data do Caixa Realizado]]-TbRegistroSaídas[[#This Row],[Data do Caixa Previsto]], 0 ), IF(TODAY()>TbRegistroSaídas[[#This Row],[Data do Caixa Previsto]], TODAY()-TbRegistroSaídas[[#This Row],[Data do Caixa Previsto]], 0 ) ) -> 0
B18: 43043.978 | C18: 43002 | D18: 43043.978 | E18: Compra de mercadorias | F18: Livros | G18: NF3440 | H18: 888 | I18: =IF([1]!TbRegistroSaídas[[#This Row],[Data do Caixa Realizado]]="",0,MONTH([1]!TbRegistroSaídas[[#This Row],[Data do Caixa Realizado]])) -> 11 | J18: =IF([1]!TbRegistroSaídas[[#This Row],[Data do Caixa Realizado]]="",0,YEAR([1]!TbRegistroSaídas[[#This Row],[Data do Caixa Realizado]])) -> 2017 | K18: =IF([1]!TbRegistroSaídas[[#This Row],[Data da Competência]]="",0,MONTH([1]!TbRegistroSaídas[[#This Row],[Data da Competência]])) -> 9 | L18: =IF([1]!TbRegistroSaídas[[#This Row],[Data da Competência]]="",0,YEAR([1]!TbRegistroSaídas[[#This Row],[Data da Competência]])) -> 2017 | M18: =IF([1]!TbRegistroSaídas[[#This Row],[Data do Caixa Previsto]]="",0,MONTH([1]!TbRegistroSaídas[[#This Row],[Data do Caixa Previsto]])) -> 11 | N18: =IF([1]!TbRegistroSaídas[[#This Row],[Data do Caixa Previsto]]="",0,YEAR([1]!TbRegistroSaídas[[#This Row],[Data do Caixa Previsto]])) -> 2017 | O18: =IF(TbRegistroSaídas[[#This Row],[Data do Caixa Realizado]]<>"", IF(TbRegistroSaídas[[#This Row],[Data do Caixa Realizado]]>TbRegistroSaídas[[#This Row],[Data do Caixa Previsto]], TbRegistroSaídas[[#This Row],[Data do Caixa Realizado]]-TbRegistroSaídas[[#This Row],[Data do Caixa Previsto]], 0 ), IF(TODAY()>TbRegistroSaídas[[#This Row],[Data do Caixa Previsto]], TODAY()-TbRegistroSaídas[[#This Row],[Data do Caixa Previsto]], 0 ) ) -> 0
C19: 43003 | D19: 43015.898 | E19: Compra de mercadorias | F19: Vestuário | G19: NF9195 | H19: 2784 | I19: =IF([1]!TbRegistroSaídas[[#This Row],[Data do Caixa Realizado]]="",0,MONTH([1]!TbRegistroSaídas[[#This Row],[Data do Caixa Realizado]])) -> 0 | J19: =IF([1]!TbRegistroSaídas[[#This Row],[Data do Caixa Realizado]]="",0,YEAR([1]!TbRegistroSaídas[[#This Row],[Data do Caixa Realizado]])) -> 0 | K19: =IF([1]!TbRegistroSaídas[[#This Row],[Data da Competência]]="",0,MONTH([1]!TbRegistroSaídas[[#This Row],[Data da Competência]])) -> 9 | L19: =IF([1]!TbRegistroSaídas[[#This Row],[Data da Competência]]="",0,YEAR([1]!TbRegistroSaídas[[#This Row],[Data da Competência]])) -> 2017 | M19: =IF([1]!TbRegistroSaídas[[#This Row],[Data do Caixa Previsto]]="",0,MONTH([1]!TbRegistroSaídas[[#This Row],[Data do Caixa Previsto]])) -> 10 | N19: =IF([1]!TbRegistroSaídas[[#This Row],[Data do Caixa Previsto]]="",0,YEAR([1]!TbRegistroSaídas[[#This Row],[Data do Caixa Previsto]])) -> 2017 | O19: =IF(TbRegistroSaídas[[#This Row],[Data do Caixa Realizado]]<>"", IF(TbRegistroSaídas[[#This Row],[Data do Caixa Realizado]]>TbRegistroSaídas[[#This Row],[Data do Caixa Previsto]], TbRegistroSaídas[[#This Row],[Data do Caixa Realizado]]-TbRegistroSaídas[[#This Row],[Data do Caixa Previsto]], 0 ), IF(TODAY()>TbRegistroSaídas[[#This Row],[Data do Caixa Previsto]], TODAY()-TbRegistroSaídas[[#This Row],[Data do Caixa Previsto]], 0 ) ) -> 2337.102
