Workbook

Sheet Dashboard
D1: Caixa: | E1: 20000 | G1: Até: | H1: =IF(ReCarteira!L1="",TODAY(),ReCarteira!L1) -> 43830
B4: Carteira atual
B5: =DashboardAux!C14 -> 8200.14
B7: Total aportado
B8: =DashboardAux!C13 -> 7113.23
B10: Valorização
B11: =DashboardAux!C15 -> 1086.91
B13: Valorização %
B14: =DashboardAux!C16 -> 0.15280119

Sheet DashboardAux
B2: Valores para caixa de combinação | E2: Matriz auxiliar: somatório por tipo de ativo | K2: Gráfico: composição do patrimônio | N2: Gráfico: maiores valores | R2: Maiores valores (tudo) | W2: Maiores valores (ações) | AB2: Maiores valores (FII)
G3: 1 | H3: 2 | I3: 3 | K3: Ações | L3: =H6 -> 27979 | N3: Ordem | O3: Ativo | P3: Valor | R3: Ordem | S3: Ativo | T3: Valor | U3: Corresp | W3: Ordem | X3: Ativo | Y3: Valor | Z3: Corresp | AB3: Ordem | AC3: Ativo | AD3: Valor | AE3: Corresp
B4: 1 | C4: Tudo | G4: Tudo | H4: Ações | I4: FII | K4: FII | L4: =I6 -> 8200.14 | N4: 10 | O4: =IF($C$9=1,S4,IF($C$9=2,X4,AC4)) -> - | P4: =IF($C$9=1,T4,IF($C$9=2,Y4,AD4)) -> - | R4: 10 | S4: {=IF(ISNA(INDEX(TbCarteira[],U4,1)),"-",INDEX(TbCarteira[],U4,1))} -> - | T4: =IF(ISNUMBER(LARGE(TbCarteira[Total Atual],R4)),LARGE(TbCarteira[Total Atual],R4),"-") -> - | U4: =MATCH(T4,TbCarteira[Total Atual],0) -> #N/A | W4: 10 | X4: {=IF(ISNA(INDEX(TbCarteiraAções[],Z4,1)),"-",INDEX(TbCarteiraAções[],Z4,1))} -> - | Y4: =IF(ISNUMBER(LARGE(TbCarteiraAções[Total Atual],W4)),LARGE(TbCarteiraAções[Total Atual],W4),"-") -> - | Z4: =MATCH(Y4,TbCarteiraAções[Total Atual],0) -> #N/A | AB4: 10 | AC4: {=IF(ISNA(INDEX(TbCarteiraFII[],AE4,1)),"-",INDEX(TbCarteiraFII[],AE4,1))} -> - | AD4: =IF(ISNUMBER(LARGE(TbCarteiraFII[Total Atual],AB4)),LARGE(TbCarteiraFII[Total Atual],AB4),"-") -> - | AE4: =MATCH(AD4,TbCarteiraFII[Total Atual],0) -> #N/A
B5: 2 | C5: Ações | E5: 1 | F5: Total aportado | G5: =SUM(TbCarteira[Total Aportado]) -> 24711.23 | H5: =SUMIF(TbCarteira[Tipo],"EMPRESA",TbCarteira[Total Aportado]) -> 17598 | I5: =SUMIF(TbCarteira[Tipo],"FII",TbCarteira[Total Aportado]) -> 7113.23 | K5: Caixa | L5: =C10 -> 20000 | N5: 9 | O5: =IF($C$9=1,S5,IF($C$9=2,X5,AC5)) -> - | P5: =IF($C$9=1,T5,IF($C$9=2,Y5,AD5)) -> - | R5: 9 | S5: {=IF(ISNA(INDEX(TbCarteira[],U5,1)),"-",INDEX(TbCarteira[],U5,1))} -> KNRI11 | T5: =IF(ISNUMBER(LARGE(TbCarteira[Total Atual],R5)),LARGE(TbCarteira[Total Atual],R5),0) -> 1318 | U5: =MATCH(T5,TbCarteira[Total Atual],0) -> 8 | W5: 9 | X5: {=IF(ISNA(INDEX(TbCarteiraAções[],Z5,1)),"-",INDEX(TbCarteiraAções[],Z5,1))} -> - | Y5: =IF(ISNUMBER(LARGE(TbCarteiraAções[Total Atual],W5)),LARGE(TbCarteiraAções[Total Atual],W5),"-") -> - | Z5: =MATCH(Y5,TbCarteiraAções[Total Atual],0) -> #N/A | AB5: 9 | AC5: {=IF(ISNA(INDEX(TbCarteiraFII[],AE5,1)),"-",INDEX(TbCarteiraFII[],AE5,1))} -> - | AD5: =IF(ISNUMBER(LARGE(TbCarteiraFII[Total Atual],AB5)),LARGE(TbCarteiraFII[Total Atual],AB5),"-") -> - | AE5: =MATCH(AD5,TbCarteiraFII[Total Atual],0) -> #N/A
B6: 3 | C6: Fundos Imobiliários | E6: 2 | F6: Carteira atual | G6: =SUM(TbCarteira[Total Atual]) -> 36179.14 | H6: =SUMIF(TbCarteira[Tipo],"EMPRESA",TbCarteira[Total Atual]) -> 27979 | I6: =SUMIF(TbCarteira[Tipo],"FII",TbCarteira[Total Atual]) -> 8200.14 | N6: 8 | O6: =IF($C$9=1,S6,IF($C$9=2,X6,AC6)) -> - | P6: =IF($C$9=1,T6,IF($C$9=2,Y6,AD6)) -> - | R6: 8 | S6: {=IF(ISNA(INDEX(TbCarteira[],U6,1)),"-",INDEX(TbCarteira[],U6,1))} -> HGRE11 | T6: =IF(ISNUMBER(LARGE(TbCarteira[Total Atual],R6)),LARGE(TbCarteira[Total Atual],R6),0) -> 1932.15 | U6: =MATCH(T6,TbCarteira[Total Atual],0) -> 7 | W6: 8 | X6: {=IF(ISNA(INDEX(TbCarteiraAções[],Z6,1)),"-",INDEX(TbCarteiraAções[],Z6,1))} -> - | Y6: =IF(ISNUMBER(LARGE(TbCarteiraAções[Total Atual],W6)),LARGE(TbCarteiraAções[Total Atual],W6),"-") -> - | Z6: =MATCH(Y6,TbCarteiraAções[Total Atual],0) -> #N/A | AB6: 8 | AC6: {=IF(ISNA(INDEX(TbCarteiraFII[],AE6,1)),"-",INDEX(TbCarteiraFII[],AE6,1))} -> - | AD6: =IF(ISNUMBER(LARGE(TbCarteiraFII[Total Atual],AB6)),LARGE(TbCarteiraFII[Total Atual],AB6),"-") -> - | AE6: =MATCH(AD6,TbCarteiraFII[Total Atual],0) -> #N/A
E7: 3 | F7: Valorização | G7: =SUM(TbCarteira[Valorização]) -> 11467.91 | H7: =SUMIF(TbCarteira[Tipo],"EMPRESA",TbCarteira[Valorização]) -> 10381 | I7: =SUMIF(TbCarteira[Tipo],"FII",TbCarteira[Valorização]) -> 1086.91 | N7: 7 | O7: =IF($C$9=1,S7,IF($C$9=2,X7,AC7)) -> - | P7: =IF($C$9=1,T7,IF($C$9=2,Y7,AD7)) -> - | R7: 7 | S7: {=IF(ISNA(INDEX(TbCarteira[],U7,1)),"-",INDEX(TbCarteira[],U7,1))} -> HGBS11 | T7: =IF(ISNUMBER(LARGE(TbCarteira[Total Atual],R7)),LARGE(TbCarteira[Total Atual],R7),0) -> 2065.77 | U7: =MATCH(T7,TbCarteira[Total Atual],0) -> 5 | W7: 7 | X7: {=IF(ISNA(INDEX(TbCarteiraAções[],Z7,1)),"-",INDEX(TbCarteiraAções[],Z7,1))} -> - | Y7: =IF(ISNUMBER(LARGE(TbCarteiraAções[Total Atual],W7)),LARGE(TbCarteiraAções[Total Atual],W7),"-") -> - | Z7: =MATCH(Y7,TbCarteiraAções[Total Atual],0) -> #N/A | AB7: 7 | AC7: {=IF(ISNA(INDEX(TbCarteiraFII[],AE7,1)),"-",INDEX(TbCarteiraFII[],AE7,1))} -> - | AD7: =IF(ISNUMBER(LARGE(TbCarteiraFII[Total Atual],AB7)),LARGE(TbCarteiraFII[Total Atual],AB7),"-") -> - | AE7: =MATCH(AD7,TbCarteiraFII[Total Atual],0) -> #N/A
B8: Entradas do usuário | E8: 4 | F8: Valorização % | G8: =G6/G5-1 -> 0.46407686 | H8: =H6/H5-1 -> 0.58989658 | I8: =I6/I5-1 -> 0.15280119 | N8: 6 | O8: =IF($C$9=1,S8,IF($C$9=2,X8,AC8)) -> - | P8: =IF($C$9=1,T8,IF($C$9=2,Y8,AD8)) -> - | R8: 6 | S8: {=IF(ISNA(INDEX(TbCarteira[],U8,1)),"-",INDEX(TbCarteira[],U8,1))} -> TAEE4 | T8: =IF(ISNUMBER(LARGE(TbCarteira[Total Atual],R8)),LARGE(TbCarteira[Total Atual],R8),0) -> 2384 | U8: =MATCH(T8,TbCarteira[Total Atual],0) -> 9 | W8: 6 | X8: {=IF(ISNA(INDEX(TbCarteiraAções[],Z8,1)),"-",INDEX(TbCarteiraAções[],Z8,1))} -> - | Y8: =IF(ISNUMBER(LARGE(TbCarteiraAções[Total Atual],W8)),LARGE(TbCarteiraAções[Total Atual],W8),"-") -> - | Z8: =MATCH(Y8,TbCarteiraAções[Total Atual],0) -> #N/A | AB8: 6 | AC8: {=IF(ISNA(INDEX(TbCarteiraFII[],AE8,1)),"-",INDEX(TbCarteiraFII[],AE8,1))} -> - | AD8: =IF(ISNUMBER(LARGE(TbCarteiraFII[Total Atual],AB8)),LARGE(TbCarteiraFII[Total Atual],AB8),"-") -> - | AE8: =MATCH(AD8,TbCarteiraFII[Total Atual],0) -> #N/A
B9: Caixa de combinação | C9: 3 | N9: 5 | O9: =IF($C$9=1,S9,IF($C$9=2,X9,AC9)) -> - | P9: =IF($C$9=1,T9,IF($C$9=2,Y9,AD9)) -> - | R9: 5 | S9: {=IF(ISNA(INDEX(TbCarteira[],U9,1)),"-",INDEX(TbCarteira[],U9,1))} -> HGLG11 | T9: =IF(ISNUMBER(LARGE(TbCarteira[Total Atual],R9)),LARGE(TbCarteira[Total Atual],R9),0) -> 2884.22 | U9: =MATCH(T9,TbCarteira[Total Atual],0) -> 6 | W9: 5 | X9: {=IF(ISNA(INDEX(TbCarteiraAções[],Z9,1)),"-",INDEX(TbCarteiraAções[],Z9,1))} -> TAEE4 | Y9: =IF(ISNUMBER(LARGE(TbCarteiraAções[Total Atual],W9)),LARGE(TbCarteiraAções[Total Atual],W9),"-") -> 2384 | Z9: =MATCH(Y9,TbCarteiraAções[Total Atual],0) -> 5 | AB9: 5 | AC9: {=IF(ISNA(INDEX(TbCarteiraFII[],AE9,1)),"-",INDEX(TbCarteiraFII[],AE9,1))} -> - | AD9: =IF(ISNUMBER(LARGE(TbCarteiraFII[Total Atual],AB9)),LARGE(TbCarteiraFII[Total Atual],AB9),"-") -> - | AE9: =MATCH(AD9,TbCarteiraFII[Total Atual],0) -> #N/A
B10: Valor em caixa | C10: =Dashboard!E1 -> 20000 | N10: 4 | O10: =IF($C$9=1,S10,IF($C$9=2,X10,AC10)) -> KNRI11 | P10: =IF($C$9=1,T10,IF($C$9=2,Y10,AD10)) -> 1318 | R10: 4 | S10: {=IF(ISNA(INDEX(TbCarteira[],U10,1)),"-",INDEX(TbCarteira[],U10,1))} -> FLRY3 | T10: =IF(ISNUMBER(LARGE(TbCarteira[Total Atual],R10)),LARGE(TbCarteira[Total Atual],R10),0) -> 3084 | U10: =MATCH(T10,TbCarteira[Total Atual],0) -> 2 | W10: 4 | X10: {=IF(ISNA(INDEX(TbCarteiraAções[],Z10,1)),"-",INDEX(TbCarteiraAções[],Z10,1))} -> FLRY3 | Y10: =IF(ISNUMBER(LARGE(TbCarteiraAções[Total Atual],W10)),LARGE(TbCarteiraAções[Total Atual],W10),"-") -> 3084 | Z10: =MATCH(Y10,TbCarteiraAções[Total Atual],0) -> 2 | AB10: 4 | AC10: {=IF(ISNA(INDEX(TbCarteiraFII[],AE10,1)),"-",INDEX(TbCarteiraFII[],AE10,1))} -> KNRI11 | AD10: =IF(ISNUMBER(LARGE(TbCarteiraFII[Total Atual],AB10)),LARGE(TbCarteiraFII[Total Atual],AB10),"-") -> 1318 | AE10: =MATCH(AD10,TbCarteiraFII[Total Atual],0) -> 4
N11: 3 | O11: =IF($C$9=1,S11,IF($C$9=2,X11,AC11)) -> HGRE11 | P11: =IF($C$9=1,T11,IF($C$9=2,Y11,AD11)) -> 1932.15 | R11: 3 | S11: {=IF(ISNA(INDEX(TbCarteira[],U11,1)),"-",INDEX(TbCarteira[],U11,1))} -> ITSA4 | T11: =IF(ISNUMBER(LARGE(TbCarteira[Total Atual],R11)),LARGE(TbCarteira[Total Atual],R11),0) -> 3090 | U11: =MATCH(T11,TbCarteira[Total Atual],0) -> 3 | W11: 3 | X11: {=IF(ISNA(INDEX(TbCarteiraAções[],Z11,1)),"-",INDEX(TbCarteiraAções[],Z11,1))} -> ITSA4 | Y11: =IF(ISNUMBER(LARGE(TbCarteiraAções[Total Atual],W11)),LARGE(TbCarteiraAções[Total Atual],W11),"-") -> 3090 | Z11: =MATCH(Y11,TbCarteiraAções[Total Atual],0) -> 3 | AB11: 3 | AC11: {=IF(ISNA(INDEX(TbCarteiraFII[],AE11,1)),"-",INDEX(TbCarteiraFII[],AE11,1))} -> HGRE11 | AD11: =IF(ISNUMBER(LARGE(TbCarteiraFII[Total Atual],AB11)),LARGE(TbCarteiraFII[Total Atual],AB11),"-") -> 1932.15 | AE11: =MATCH(AD11,TbCarteiraFII[Total Atual],0) -> 3
B12: Indicadores-chave de desempenho (KPI) | N12: 2 | O12: =IF($C$9=1,S12,IF($C$9=2,X12,AC12)) -> HGBS11 | P12: =IF($C$9=1,T12,IF($C$9=2,Y12,AD12)) -> 2065.77 | R12: 2 | S12: {=IF(ISNA(INDEX(TbCarteira[],U12,1)),"-",INDEX(TbCarteira[],U12,1))} -> CSNA3 | T12: =IF(ISNUMBER(LARGE(TbCarteira[Total Atual],R12)),LARGE(TbCarteira[Total Atual],R12),0) -> 4821 | U12: =MATCH(T12,TbCarteira[Total Atual],0) -> 1 | W12: 2 | X12: {=IF(ISNA(INDEX(TbCarteiraAções[],Z12,1)),"-",INDEX(TbCarteiraAções[],Z12,1))} -> CSNA3 | Y12: =IF(ISNUMBER(LARGE(TbCarteiraAções[Total Atual],W12)),LARGE(TbCarteiraAções[Total Atual],W12),"-") -> 4821 | Z12: =MATCH(Y12,TbCarteiraAções[Total Atual],0) -> 1 | AB12: 2 | AC12: {=IF(ISNA(INDEX(TbCarteiraFII[],AE12,1)),"-",INDEX(TbCarteiraFII[],AE12,1))} -> HGBS11 | AD12: =IF(ISNUMBER(LARGE(TbCarteiraFII[Total Atual],AB12)),LARGE(TbCarteiraFII[Total Atual],AB12),"-") -> 2065.77 | AE12: =MATCH(AD12,TbCarteiraFII[Total Atual],0) -> 1
B13: Total aportado | C13: {=INDEX($G$5:$I$8,E5,$C$9)} -> 7113.23 | N13: 1 | O13: =IF($C$9=1,S13,IF($C$9=2,X13,AC13)) -> HGLG11 | P13: =IF($C$9=1,T13,IF($C$9=2,Y13,AD13)) -> 2884.22 | R13: 1 | S13: {=IF(ISNA(INDEX(TbCarteira[],U13,1)),"-",INDEX(TbCarteira[],U13,1))} -> PETR4 | T13: =IF(ISNUMBER(LARGE(TbCarteira[Total Atual],R13)),LARGE(TbCarteira[Total Atual],R13),0) -> 14600 | U13: =MATCH(T13,TbCarteira[Total Atual],0) -> 4 | W13: 1 | X13: {=IF(ISNA(INDEX(TbCarteiraAções[],Z13,1)),"-",INDEX(TbCarteiraAções[],Z13,1))} -> PETR4 | Y13: =IF(ISNUMBER(LARGE(TbCarteiraAções[Total Atual],W13)),LARGE(TbCarteiraAções[Total Atual],W13),"-") -> 14600 | Z13: =MATCH(Y13,TbCarteiraAções[Total Atual],0) -> 4 | AB13: 1 | AC13: {=IF(ISNA(INDEX(TbCarteiraFII[],AE13,1)),"-",INDEX(TbCarteiraFII[],AE13,1))} -> HGLG11 | AD13: =IF(ISNUMBER(LARGE(TbCarteiraFII[Total Atual],AB13)),LARGE(TbCarteiraFII[Total Atual],AB13),"-") -> 2884.22 | AE13: =MATCH(AD13,TbCarteiraFII[Total Atual],0) -> 2
B14: Carteira atual | C14: {=INDEX($G$5:$I$8,E6,$C$9)} -> 8200.14
B15: Valorização | C15: {=INDEX($G$5:$I$8,E7,$C$9)} -> 1086.91 | N15: Gráfico: maiores valorizações | R15: Maiores valorizações (tudo) | W15: Maiores valorizações (ações) | AB15: Maiores valorizações (FII)
B16: Valorização % | C16: {=INDEX($G$5:$I$8,E8,$C$9)} -> 0.15280119 | N16: Ordem | O16: Ativo | P16: Valorização % | R16: Ordem | S16: Ativo | T16: Valorização % | U16: Corresp | W16: Ordem | X16: Ativo | Y16: Valorização % | Z16: Corresp | AB16: Ordem | AC16: Ativo | AD16: Valorização % | AE16: Corresp
N17: 10 | O17: =IF($C$9=1,S17,IF($C$9=2,X17,AC17)) -> - | P17: =IF($C$9=1,T17,IF($C$9=2,Y17,AD17)) -> - | R17: 10 | S17: {=IF(ISNA(INDEX(TbCarteira[],U17,1)),"-",INDEX(TbCarteira[],U17,1))} -> - | T17: =IF(ISNUMBER(LARGE(TbCarteira[Valorização %],R17)),LARGE(TbCarteira[Valorização %],R17),0) -> 0 | U17: =MATCH(T17,TbCarteira[Valorização %],0) -> #N/A | W17: 10 | X17: {=IF(ISNA(INDEX(TbCarteiraAções[],Z17,1)),"-",INDEX(TbCarteiraAções[],Z17,1))} -> - | Y17: =IF(ISNUMBER(LARGE(TbCarteiraAções[Valorização %],W17)),LARGE(TbCarteiraAções[Valorização %],W17),"-") -> - | Z17: =MATCH(Y17,TbCarteiraAções[Valorização %],0) -> #N/A | AB17: 10 | AC17: {=IF(ISNA(INDEX(TbCarteiraFII[],AE17,1)),"-",INDEX(TbCarteiraFII[],AE17,1))} -> - | AD17: =IF(ISNUMBER(LARGE(TbCarteiraFII[Valorização %],AB17)),LARGE(TbCarteiraFII[Valorização %],AB17),"-") -> - | AE17: =MATCH(AD17,TbCarteiraFII[Valorização %],0) -> #N/A
N18: 9 | O18: =IF($C$9=1,S18,IF($C$9=2,X18,AC18)) -> - | P18: =IF($C$9=1,T18,IF($C$9=2,Y18,AD18)) -> - | R18: 9 | S18: {=IF(ISNA(INDEX(TbCarteira[],U18,1)),"-",INDEX(TbCarteira[],U18,1))} -> FLRY3 | T18: =IF(ISNUMBER(LARGE(TbCarteira[Valorização %],R18)),LARGE(TbCarteira[Valorização %],R18),0) -> -0.23416936 | U18: =MATCH(T18,TbCarteira[Valorização %],0) -> 2 | W18: 9 | X18: {=IF(ISNA(INDEX(TbCarteiraAções[],Z18,1)),"-",INDEX(TbCarteiraAções[],Z18,1))} -> - | Y18: =IF(ISNUMBER(LARGE(TbCarteiraAções[Valorização %],W18)),LARGE(TbCarteiraAções[Valorização %],W18),"-") -> - | Z18: =MATCH(Y18,TbCarteiraAções[Valorização %],0) -> #N/A | AB18: 9 | AC18: {=IF(ISNA(INDEX(TbCarteiraFII[],AE18,1)),"-",INDEX(TbCarteiraFII[],AE18,1))} -> - | AD18: =IF(ISNUMBER(LARGE(TbCarteiraFII[Valorização %],AB18)),LARGE(TbCarteiraFII[Valorização %],AB18),"-") -> - | AE18: =MATCH(AD18,TbCarteiraFII[Valorização %],0) -> #N/A
N19: 8 | O19: =IF($C$9=1,S19,IF($C$9=2,X19,AC19)) -> - | P19: =IF($C$9=1,T19,IF($C$9=2,Y19,AD19)) -> - | R19: 8 | S19: {=IF(ISNA(INDEX(TbCarteira[],U19,1)),"-",INDEX(TbCarteira[],U19,1))} -> HGRE11 | T19: =IF(ISNUMBER(LARGE(TbCarteira[Valorização %],R19)),LARGE(TbCarteira[Valorização %],R19),0) -> -0.003414536 | U19: =MATCH(T19,TbCarteira[Valorização %],0) -> 7 | W19: 8 | X19: {=IF(ISNA(INDEX(TbCarteiraAções[],Z19,1)),"-",INDEX(TbCarteiraAções[],Z19,1))} -> - | Y19: =IF(ISNUMBER(LARGE(TbCarteiraAções[Valorização %],W19)),LARGE(TbCarteiraAções[Valorização %],W19),"-") -> - | Z19: =MATCH(Y19,TbCarteiraAções[Valorização %],0) -> #N/A | AB19: 8 | AC19: {=IF(ISNA(INDEX(TbCarteiraFII[],AE19,1)),"-",INDEX(TbCarteiraFII[],AE19,1))} -> - | AD19: =IF(ISNUMBER(LARGE(TbCarteiraFII[Valorização %],AB19)),LARGE(TbCarteiraFII[Valorização %],AB19),"-") -> - | AE19: =MATCH(AD19,TbCarteiraFII[Valorização %],0) -> #N/A
N20: 7 | O20: =IF($C$9=1,S20,IF($C$9=2,X20,AC20)) -> - | P20: =IF($C$9=1,T20,IF($C$9=2,Y20,AD20)) -> - | R20: 7 | S20: {=IF(ISNA(INDEX(TbCarteira[],U20,1)),"-",INDEX(TbCarteira[],U20,1))} -> KNRI11 | T20: =IF(ISNUMBER(LARGE(TbCarteira[Valorização %],R20)),LARGE(TbCarteira[Valorização %],R20),0) -> 0.18813666 | U20: =MATCH(T20,TbCarteira[Valorização %],0) -> 8 | W20: 7 | X20: {=IF(ISNA(INDEX(TbCarteiraAções[],Z20,1)),"-",INDEX(TbCarteiraAções[],Z20,1))} -> - | Y20: =IF(ISNUMBER(LARGE(TbCarteiraAções[Valorização %],W20)),LARGE(TbCarteiraAções[Valorização %],W20),"-") -> - | Z20: =MATCH(Y20,TbCarteiraAções[Valorização %],0) -> #N/A | AB20: 7 | AC20: {=IF(ISNA(INDEX(TbCarteiraFII[],AE20,1)),"-",INDEX(TbCarteiraFII[],AE20,1))} -> - | AD20: =IF(ISNUMBER(LARGE(TbCarteiraFII[Valorização %],AB20)),LARGE(TbCarteiraFII[Valorização %],AB20),"-") -> - | AE20: =MATCH(AD20,TbCarteiraFII[Valorização %],0) -> #N/A
N21: 6 | O21: =IF($C$9=1,S21,IF($C$9=2,X21,AC21)) -> - | P21: =IF($C$9=1,T21,IF($C$9=2,Y21,AD21)) -> - | R21: 6 | S21: {=IF(ISNA(INDEX(TbCarteira[],U21,1)),"-",INDEX(TbCarteira[],U21,1))} -> HGBS11 | T21: =IF(ISNUMBER(LARGE(TbCarteira[Valorização %],R21)),LARGE(TbCarteira[Valorização %],R21),0) -> 0.20498731 | U21: =MATCH(T21,TbCarteira[Valorização %],0) -> 5 | W21: 6 | X21: {=IF(ISNA(INDEX(TbCarteiraAções[],Z21,1)),"-",INDEX(TbCarteiraAções[],Z21,1))} -> - | Y21: =IF(ISNUMBER(LARGE(TbCarteiraAções[Valorização %],W21)),LARGE(TbCarteiraAções[Valorização %],W21),"-") -> - | Z21: =MATCH(Y21,TbCarteiraAções[Valorização %],0) -> #N/A | AB21: 6 | AC21: {=IF(ISNA(INDEX(TbCarteiraFII[],AE21,1)),"-",INDEX(TbCarteiraFII[],AE21,1))} -> - | AD21: =IF(ISNUMBER(LARGE(TbCarteiraFII[Valorização %],AB21)),LARGE(TbCarteiraFII[Valorização %],AB21),"-") -> - | AE21: =MATCH(AD21,TbCarteiraFII[Valorização %],0) -> #N/A
N22: 5 | O22: =IF($C$9=1,S22,IF($C$9=2,X22,AC22)) -> - | P22: =IF($C$9=1,T22,IF($C$9=2,Y22,AD22)) -> - | R22: 5 | S22: {=IF(ISNA(INDEX(TbCarteira[],U22,1)),"-",INDEX(TbCarteira[],U22,1))} -> HGLG11 | T22: =IF(ISNUMBER(LARGE(TbCarteira[Valorização %],R22)),LARGE(TbCarteira[Valorização %],R22),0) -> 0.22690477 | U22: =MATCH(T22,TbCarteira[Valorização %],0) -> 6 | W22: 5 | X22: {=IF(ISNA(INDEX(TbCarteiraAções[],Z22,1)),"-",INDEX(TbCarteiraAções[],Z22,1))} -> FLRY3 | Y22: =IF(ISNUMBER(LARGE(TbCarteiraAções[Valorização %],W22)),LARGE(TbCarteiraAções[Valorização %],W22),"-") -> -0.23416936 | Z22: =MATCH(Y22,TbCarteiraAções[Valorização %],0) -> 2 | AB22: 5 | AC22: {=IF(ISNA(INDEX(TbCarteiraFII[],AE22,1)),"-",INDEX(TbCarteiraFII[],AE22,1))} -> - | AD22: =IF(ISNUMBER(LARGE(TbCarteiraFII[Valorização %],AB22)),LARGE(TbCarteiraFII[Valorização %],AB22),"-") -> - | AE22: =MATCH(AD22,TbCarteiraFII[Valorização %],0) -> #N/A
N23: 4 | O23: =IF($C$9=1,S23,IF($C$9=2,X23,AC23)) -> HGRE11 | P23: =IF($C$9=1,T23,IF($C$9=2,Y23,AD23)) -> -0.003414536 | R23: 4 | S23: {=IF(ISNA(INDEX(TbCarteira[],U23,1)),"-",INDEX(TbCarteira[],U23,1))} -> ITSA4 | T23: =IF(ISNUMBER(LARGE(TbCarteira[Valorização %],R23)),LARGE(TbCarteira[Valorização %],R23),0) -> 0.23009554 | U23: =MATCH(T23,TbCarteira[Valorização %],0) -> 3 | W23: 4 | X23: {=IF(ISNA(INDEX(TbCarteiraAções[],Z23,1)),"-",INDEX(TbCarteiraAções[],Z23,1))} -> ITSA4 | Y23: =IF(ISNUMBER(LARGE(TbCarteiraAções[Valorização %],W23)),LARGE(TbCarteiraAções[Valorização %],W23),"-") -> 0.23009554 | Z23: =MATCH(Y23,TbCarteiraAções[Valorização %],0) -> 3 | AB23: 4 | AC23: {=IF(ISNA(INDEX(TbCarteiraFII[],AE23,1)),"-",INDEX(TbCarteiraFII[],AE23,1))} -> HGRE11 | AD23: =IF(ISNUMBER(LARGE(TbCarteiraFII[Valorização %],AB23)),LARGE(TbCarteiraFII[Valorização %],AB23),"-") -> -0.003414536 | AE23: =MATCH(AD23,TbCarteiraFII[Valorização %],0) -> 3
N24: 3 | O24: =IF($C$9=1,S24,IF($C$9=2,X24,AC24)) -> KNRI11 | P24: =IF($C$9=1,T24,IF($C$9=2,Y24,AD24)) -> 0.18813666 | R24: 3 | S24: {=IF(ISNA(INDEX(TbCarteira[],U24,1)),"-",INDEX(TbCarteira[],U24,1))} -> TAEE4 | T24: =IF(ISNUMBER(LARGE(TbCarteira[Valorização %],R24)),LARGE(TbCarteira[Valorização %],R24),0) -> 0.45810398 | U24: =MATCH(T24,TbCarteira[Valorização %],0) -> 9 | W24: 3 | X24: {=IF(ISNA(INDEX(TbCarteiraAções[],Z24,1)),"-",INDEX(TbCarteiraAções[],Z24,1))} -> TAEE4 | Y24: =IF(ISNUMBER(LARGE(TbCarteiraAções[Valorização %],W24)),LARGE(TbCarteiraAções[Valorização %],W24),"-") -> 0.45810398 | Z24: =MATCH(Y24,TbCarteiraAções[Valorização %],0) -> 5 | AB24: 3 | AC24: {=IF(ISNA(INDEX(TbCarteiraFII[],AE24,1)),"-",INDEX(TbCarteiraFII[],AE24,1))} -> KNRI11 | AD24: =IF(ISNUMBER(LARGE(TbCarteiraFII[Valorização %],AB24)),LARGE(TbCarteiraFII[Valorização %],AB24),"-") -> 0.18813666 | AE24: =MATCH(AD24,TbCarteiraFII[Valorização %],0) -> 4
N25: 2 | O25: =IF($C$9=1,S25,IF($C$9=2,X25,AC25)) -> HGBS11 | P25: =IF($C$9=1,T25,IF($C$9=2,Y25,AD25)) -> 0.20498731 | R25: 2 | S25: {=IF(ISNA(INDEX(TbCarteira[],U25,1)),"-",INDEX(TbCarteira[],U25,1))} -> CSNA3 | T25: =IF(ISNUMBER(LARGE(TbCarteira[Valorização %],R25)),LARGE(TbCarteira[Valorização %],R25),0) -> 0.71565836 | U25: =MATCH(T25,TbCarteira[Valorização %],0) -> 1 | W25: 2 | X25: {=IF(ISNA(INDEX(TbCarteiraAções[],Z25,1)),"-",INDEX(TbCarteiraAções[],Z25,1))} -> CSNA3 | Y25: =IF(ISNUMBER(LARGE(TbCarteiraAções[Valorização %],W25)),LARGE(TbCarteiraAções[Valorização %],W25),"-") -> 0.71565836 | Z25: =MATCH(Y25,TbCarteiraAções[Valorização %],0) -> 1 | AB25: 2 | AC25: {=IF(ISNA(INDEX(TbCarteiraFII[],AE25,1)),"-",INDEX(TbCarteiraFII[],AE25,1))} -> HGBS11 | AD25: =IF(ISNUMBER(LARGE(TbCarteiraFII[Valorização %],AB25)),LARGE(TbCarteiraFII[Valorização %],AB25),"-") -> 0.20498731 | AE25: =MATCH(AD25,TbCarteiraFII[Valorização %],0) -> 1
N26: 1 | O26: =IF($C$9=1,S26,IF($C$9=2,X26,AC26)) -> HGLG11 | P26: =IF($C$9=1,T26,IF($C$9=2,Y26,AD26)) -> 0.22690477 | R26: 1 | S26: {=IF(ISNA(INDEX(TbCarteira[],U26,1)),"-",INDEX(TbCarteira[],U26,1))} -> PETR4 | T26: =IF(ISNUMBER(LARGE(TbCarteira[Valorização %],R26)),LARGE(TbCarteira[Valorização %],R26),0) -> 1.2074388 | U26: =MATCH(T26,TbCarteira[Valorização %],0) -> 4 | W26: 1 | X26: {=IF(ISNA(INDEX(TbCarteiraAções[],Z26,1)),"-",INDEX(TbCarteiraAções[],Z26,1))} -> PETR4 | Y26: =IF(ISNUMBER(LARGE(TbCarteiraAções[Valorização %],W26)),LARGE(TbCarteiraAções[Valorização %],W26),"-") -> 1.2074388 | Z26: =MATCH(Y26,TbCarteiraAções[Valorização %],0) -> 4 | AB26: 1 | AC26: {=IF(ISNA(INDEX(TbCarteiraFII[],AE26,1)),"-",INDEX(TbCarteiraFII[],AE26,1))} -> HGLG11 | AD26: =IF(ISNUMBER(LARGE(TbCarteiraFII[Valorização %],AB26)),LARGE(TbCarteiraFII[Valorização %],AB26),"-") -> 0.22690477 | AE26: =MATCH(AD26,TbCarteiraFII[Valorização %],0) -> 2

Sheet ReCarteira
A1: Ativo | B1: Tipo | C1: Cotação | D1: Total Aportado | E1: Total Qte | F1: PM | G1: Total Atual | H1: Valorização | I1: Valorização % | K1: Até qual data? | L1: 43830
A2: CSNA3 | B2: =VLOOKUP(TbCarteira[[#This Row],[Ativo]],TbAtivos[],2,FALSE) -> EMPRESA | C2: =VLOOKUP(TbCarteira[[#This Row],[Ativo]],TbAtivos[],3,FALSE) -> 16.07 | D2: =SUMIFS(TbAportes[Total],TbAportes[Ativo],TbCarteira[[#This Row],[Ativo]],TbAportes[Data],"<="&IF($L$1="",TODAY(),$L$1)) -> 2810 | E2: =SUMIFS(TbAportes[Qte],TbAportes[Ativo],TbCarteira[[#This Row],[Ativo]],TbAportes[Data],"<="&IF($L$1="",TODAY(),$L$1)) -> 300 | F2: =TbCarteira[[#This Row],[Total Aportado]]/E2 -> 9.3666667 | G2: =TbCarteira[[#This Row],[Cotação]]*TbCarteira[[#This Row],[Total Qte]] -> 4821 | H2: =TbCarteira[[#This Row],[Total Atual]]-TbCarteira[[#This Row],[Total Aportado]] -> 2011 | I2: =(TbCarteira[[#This Row],[Total Atual]]/TbCarteira[[#This Row],[Total Aportado]])-1 -> 0.71565836
A3: FLRY3 | B3: =VLOOKUP(TbCarteira[[#This Row],[Ativo]],TbAtivos[],2,FALSE) -> EMPRESA | C3: =VLOOKUP(TbCarteira[[#This Row],[Ativo]],TbAtivos[],3,FALSE) -> 15.42 | D3: =SUMIFS(TbAportes[Total],TbAportes[Ativo],TbCarteira[[#This Row],[Ativo]],TbAportes[Data],"<="&IF($L$1="",TODAY(),$L$1)) -> 4027 | E3: =SUMIFS(TbAportes[Qte],TbAportes[Ativo],TbCarteira[[#This Row],[Ativo]],TbAportes[Data],"<="&IF($L$1="",TODAY(),$L$1)) -> 200 | F3: =TbCarteira[[#This Row],[Total Aportado]]/E3 -> 20.135 | G3: =TbCarteira[[#This Row],[Cotação]]*TbCarteira[[#This Row],[Total Qte]] -> 3084 | H3: =TbCarteira[[#This Row],[Total Atual]]-TbCarteira[[#This Row],[Total Aportado]] -> -943 | I3: =(TbCarteira[[#This Row],[Total Atual]]/TbCarteira[[#This Row],[Total Aportado]])-1 -> -0.23416936
A4: ITSA4 | B4: =VLOOKUP(TbCarteira[[#This Row],[Ativo]],TbAtivos[],2,FALSE) -> EMPRESA | C4: =VLOOKUP(TbCarteira[[#This Row],[Ativo]],TbAtivos[],3,FALSE) -> 10.3 | D4: =SUMIFS(TbAportes[Total],TbAportes[Ativo],TbCarteira[[#This Row],[Ativo]],TbAportes[Data],"<="&IF($L$1="",TODAY(),$L$1)) -> 2512 | E4: =SUMIFS(TbAportes[Qte],TbAportes[Ativo],TbCarteira[[#This Row],[Ativo]],TbAportes[Data],"<="&IF($L$1="",TODAY(),$L$1)) -> 300 | F4: =TbCarteira[[#This Row],[Total Aportado]]/E4 -> 8.3733333 | G4: =TbCarteira[[#This Row],[Cotação]]*TbCarteira[[#This Row],[Total Qte]] -> 3090 | H4: =TbCarteira[[#This Row],[Total Atual]]-TbCarteira[[#This Row],[Total Aportado]] -> 578 | I4: =(TbCarteira[[#This Row],[Total Atual]]/TbCarteira[[#This Row],[Total Aportado]])-1 -> 0.23009554
A5: PETR4 | B5: =VLOOKUP(TbCarteira[[#This Row],[Ativo]],TbAtivos[],2,FALSE) -> EMPRESA | C5: =VLOOKUP(TbCarteira[[#This Row],[Ativo]],TbAtivos[],3,FALSE) -> 36.5 | D5: =SUMIFS(TbAportes[Total],TbAportes[Ativo],TbCarteira[[#This Row],[Ativo]],TbAportes[Data],"<="&IF($L$1="",TODAY(),$L$1)) -> 6614 | E5: =SUMIFS(TbAportes[Qte],TbAportes[Ativo],TbCarteira[[#This Row],[Ativo]],TbAportes[Data],"<="&IF($L$1="",TODAY(),$L$1)) -> 400 | F5: =TbCarteira[[#This Row],[Total Aportado]]/E5 -> 16.535 | G5: =TbCarteira[[#This Row],[Cotação]]*TbCarteira[[#This Row],[Total Qte]] -> 14600 | H5: =TbCarteira[[#This Row],[Total Atual]]-TbCarteira[[#This Row],[Total Aportado]] -> 7986 | I5: =(TbCarteira[[#This Row],[Total Atual]]/TbCarteira[[#This Row],[Total Aportado]])-1 -> 1.2074388
A6: HGBS11 | B6: =VLOOKUP(TbCarteira[[#This Row],[Ativo]],TbAtivos[],2,FALSE) -> FII | C6: =VLOOKUP(TbCarteira[[#This Row],[Ativo]],TbAtivos[],3,FALSE) -> 229.53 | D6: =SUMIFS(TbAportes[Total],TbAportes[Ativo],TbCarteira[[#This Row],[Ativo]],TbAportes[Data],"<="&IF($L$1="",TODAY(),$L$1)) -> 1714.35 | E6: =SUMIFS(TbAportes[Qte],TbAportes[Ativo],TbCarteira[[#This Row],[Ativo]],TbAportes[Data],"<="&IF($L$1="",TODAY(),$L$1)) -> 9 | F6: =TbCarteira[[#This Row],[Total Aportado]]/E6 -> 190.48333 | G6: =TbCarteira[[#This Row],[Cotação]]*TbCarteira[[#This Row],[Total Qte]] -> 2065.77 | H6: =TbCarteira[[#This Row],[Total Atual]]-TbCarteira[[#This Row],[Total Aportado]] -> 351.42 | I6: =(TbCarteira[[#This Row],[Total Atual]]/TbCarteira[[#This Row],[Total Aportado]])-1 -> 0.20498731
A7: HGLG11 | B7: =VLOOKUP(TbCarteira[[#This Row],[Ativo]],TbAtivos[],2,FALSE) -> FII | C7: =VLOOKUP(TbCarteira[[#This Row],[Ativo]],TbAtivos[],3,FALSE) -> 169.66 | D7: =SUMIFS(TbAportes[Total],TbAportes[Ativo],TbCarteira[[#This Row],[Ativo]],TbAportes[Data],"<="&IF($L$1="",TODAY(),$L$1)) -> 2350.81 | E7: =SUMIFS(TbAportes[Qte],TbAportes[Ativo],TbCarteira[[#This Row],[Ativo]],TbAportes[Data],"<="&IF($L$1="",TODAY(),$L$1)) -> 17 | F7: =TbCarteira[[#This Row],[Total Aportado]]/E7 -> 138.28294 | G7: =TbCarteira[[#This Row],[Cotação]]*TbCarteira[[#This Row],[Total Qte]] -> 2884.22 | H7: =TbCarteira[[#This Row],[Total Atual]]-TbCarteira[[#This Row],[Total Aportado]] -> 533.41 | I7: =(TbCarteira[[#This Row],[Total Atual]]/TbCarteira[[#This Row],[Total Aportado]])-1 -> 0.22690477
A8: HGRE11 | B8: =VLOOKUP(TbCarteira[[#This Row],[Ativo]],TbAtivos[],2,FALSE) -> FII | C8: =VLOOKUP(TbCarteira[[#This Row],[Ativo]],TbAtivos[],3,FALSE) -> 128.81 | D8: =SUMIFS(TbAportes[Total],TbAportes[Ativo],TbCarteira[[#This Row],[Ativo]],TbAportes[Data],"<="&IF($L$1="",TODAY(),$L$1)) -> 1938.77 | E8: =SUMIFS(TbAportes[Qte],TbAportes[Ativo],TbCarteira[[#This Row],[Ativo]],TbAportes[Data],"<="&IF($L$1="",TODAY(),$L$1)) -> 15 | F8: =TbCarteira[[#This Row],[Total Aportado]]/E8 -> 129.25133 | G8: =TbCarteira[[#This Row],[Cotação]]*TbCarteira[[#This Row],[Total Qte]] -> 1932.15 | H8: =TbCarteira[[#This Row],[Total Atual]]-TbCarteira[[#This Row],[Total Aportado]] -> -6.62 | I8: =(TbCarteira[[#This Row],[Total Atual]]/TbCarteira[[#This Row],[Total Aportado]])-1 -> -0.003414536
A9: KNRI11 | B9: =VLOOKUP(TbCarteira[[#This Row],[Ativo]],TbAtivos[],2,FALSE) -> FII | C9: =VLOOKUP(TbCarteira[[#This Row],[Ativo]],TbAtivos[],3,FALSE) -> 164.75 | D9: =SUMIFS(TbAportes[Total],TbAportes[Ativo],TbCarteira[[#This Row],[Ativo]],TbAportes[Data],"<="&IF($L$1="",TODAY(),$L$1)) -> 1109.3 | E9: =SUMIFS(TbAportes[Qte],TbAportes[Ativo],TbCarteira[[#This Row],[Ativo]],TbAportes[Data],"<="&IF($L$1="",TODAY(),$L$1)) -> 8 | F9: =TbCarteira[[#This Row],[Total Aportado]]/E9 -> 138.6625 | G9: =TbCarteira[[#This Row],[Cotação]]*TbCarteira[[#This Row],[Total Qte]] -> 1318 | H9: =TbCarteira[[#This Row],[Total Atual]]-TbCarteira[[#This Row],[Total Aportado]] -> 208.7 | I9: =(TbCarteira[[#This Row],[Total Atual]]/TbCarteira[[#This Row],[Total Aportado]])-1 -> 0.18813666
A10: TAEE4 | B10: =VLOOKUP(TbCarteira[[#This Row],[Ativo]],TbAtivos[],2,FALSE) -> EMPRESA | C10: =VLOOKUP(TbCarteira[[#This Row],[Ativo]],TbAtivos[],3,FALSE) -> 11.92 | D10: =SUMIFS(TbAportes[Total],TbAportes[Ativo],TbCarteira[[#This Row],[Ativo]],TbAportes[Data],"<="&IF($L$1="",TODAY(),$L$1)) -> 1635 | E10: =SUMIFS(TbAportes[Qte],TbAportes[Ativo],TbCarteira[[#This Row],[Ativo]],TbAportes[Data],"<="&IF($L$1="",TODAY(),$L$1)) -> 200 | F10: =TbCarteira[[#This Row],[Total Aportado]]/E10 -> 8.175 | G10: =TbCarteira[[#This Row],[Cotação]]*TbCarteira[[#This Row],[Total Qte]] -> 2384 | H10: =TbCarteira[[#This Row],[Total Atual]]-TbCarteira[[#This Row],[Total Aportado]] -> 749 | I10: =(TbCarteira[[#This Row],[Total Atual]]/TbCarteira[[#This Row],[Total Aportado]])-1 -> 0.45810398
A11: Total | D11: =SUBTOTAL(109,TbCarteira[Total Aportado]) -> 24711.23 | G11: =SUBTOTAL(109,TbCarteira[Total Atual]) -> 36179.14 | H11: =SUBTOTAL(109,TbCarteira[Valorização]) -> 11467.91

Sheet ReCarteiraAções
A1: Ativo | B1: Tipo | C1: Cotação | D1: Total Aportado | E1: Total Qte | F1: PM | G1: Total Atual | H1: Valorização | I1: Valorização % | K1: Até qual data? | L1: 43830
A2: CSNA3 | B2: =VLOOKUP(TbCarteiraAções[[#This Row],[Ativo]],TbAtivos[],2,FALSE) -> EMPRESA | C2: =VLOOKUP(TbCarteiraAções[[#This Row],[Ativo]],TbAtivos[],3,FALSE) -> 16.07 | D2: =SUMIFS(TbAportes[Total],TbAportes[Ativo],TbCarteiraAções[[#This Row],[Ativo]],TbAportes[Data],"<="&IF($L$1="",TODAY(),$L$1)) -> 2810 | E2: =SUMIFS(TbAportes[Qte],TbAportes[Ativo],TbCarteiraAções[[#This Row],[Ativo]],TbAportes[Data],"<="&IF($L$1="",TODAY(),$L$1)) -> 300 | F2: =TbCarteiraAções[[#This Row],[Total Aportado]]/E2 -> 9.3666667 | G2: =TbCarteiraAções[[#This Row],[Cotação]]*TbCarteiraAções[[#This Row],[Total Qte]] -> 4821 | H2: =TbCarteiraAções[[#This Row],[Total Atual]]-TbCarteiraAções[[#This Row],[Total Aportado]] -> 2011 | I2: =(TbCarteiraAções[[#This Row],[Total Atual]]/TbCarteiraAções[[#This Row],[Total Aportado]])-1 -> 0.71565836
A3: FLRY3 | B3: =VLOOKUP(TbCarteiraAções[[#This Row],[Ativo]],TbAtivos[],2,FALSE) -> EMPRESA | C3: =VLOOKUP(TbCarteiraAções[[#This Row],[Ativo]],TbAtivos[],3,FALSE) -> 15.42 | D3: =SUMIFS(TbAportes[Total],TbAportes[Ativo],TbCarteiraAções[[#This Row],[Ativo]],TbAportes[Data],"<="&IF($L$1="",TODAY(),$L$1)) -> 4027 | E3: =SUMIFS(TbAportes[Qte],TbAportes[Ativo],TbCarteiraAções[[#This Row],[Ativo]],TbAportes[Data],"<="&IF($L$1="",TODAY(),$L$1)) -> 200 | F3: =TbCarteiraAções[[#This Row],[Total Aportado]]/E3 -> 20.135 | G3: =TbCarteiraAções[[#This Row],[Cotação]]*TbCarteiraAções[[#This Row],[Total Qte]] -> 3084 | H3: =TbCarteiraAções[[#This Row],[Total Atual]]-TbCarteiraAções[[#This Row],[Total Aportado]] -> -943 | I3: =(TbCarteiraAções[[#This Row],[Total Atual]]/TbCarteiraAções[[#This Row],[Total Aportado]])-1 -> -0.23416936
A4: ITSA4 | B4: =VLOOKUP(TbCarteiraAções[[#This Row],[Ativo]],TbAtivos[],2,FALSE) -> EMPRESA | C4: =VLOOKUP(TbCarteiraAções[[#This Row],[Ativo]],TbAtivos[],3,FALSE) -> 10.3 | D4: =SUMIFS(TbAportes[Total],TbAportes[Ativo],TbCarteiraAções[[#This Row],[Ativo]],TbAportes[Data],"<="&IF($L$1="",TODAY(),$L$1)) -> 2512 | E4: =SUMIFS(TbAportes[Qte],TbAportes[Ativo],TbCarteiraAções[[#This Row],[Ativo]],TbAportes[Data],"<="&IF($L$1="",TODAY(),$L$1)) -> 300 | F4: =TbCarteiraAções[[#This Row],[Total Aportado]]/E4 -> 8.3733333 | G4: =TbCarteiraAções[[#This Row],[Cotação]]*TbCarteiraAções[[#This Row],[Total Qte]] -> 3090 | H4: =TbCarteiraAções[[#This Row],[Total Atual]]-TbCarteiraAções[[#This Row],[Total Aportado]] -> 578 | I4: =(TbCarteiraAções[[#This Row],[Total Atual]]/TbCarteiraAções[[#This Row],[Total Aportado]])-1 -> 0.23009554
A5: PETR4 | B5: =VLOOKUP(TbCarteiraAções[[#This Row],[Ativo]],TbAtivos[],2,FALSE) -> EMPRESA | C5: =VLOOKUP(TbCarteiraAções[[#This Row],[Ativo]],TbAtivos[],3,FALSE) -> 36.5 | D5: =SUMIFS(TbAportes[Total],TbAportes[Ativo],TbCarteiraAções[[#This Row],[Ativo]],TbAportes[Data],"<="&IF($L$1="",TODAY(),$L$1)) -> 6614 | E5: =SUMIFS(TbAportes[Qte],TbAportes[Ativo],TbCarteiraAções[[#This Row],[Ativo]],TbAportes[Data],"<="&IF($L$1="",TODAY(),$L$1)) -> 400 | F5: =TbCarteiraAções[[#This Row],[Total Aportado]]/E5 -> 16.535 | G5: =TbCarteiraAções[[#This Row],[Cotação]]*TbCarteiraAções[[#This Row],[Total Qte]] -> 14600 | H5: =TbCarteiraAções[[#This Row],[Total Atual]]-TbCarteiraAções[[#This Row],[Total Aportado]] -> 7986 | I5: =(TbCarteiraAções[[#This Row],[Total Atual]]/TbCarteiraAções[[#This Row],[Total Aportado]])-1 -> 1.2074388
A6: TAEE4 | B6: =VLOOKUP(TbCarteiraAções[[#This Row],[Ativo]],TbAtivos[],2,FALSE) -> EMPRESA | C6: =VLOOKUP(TbCarteiraAções[[#This Row],[Ativo]],TbAtivos[],3,FALSE) -> 11.92 | D6: =SUMIFS(TbAportes[Total],TbAportes[Ativo],TbCarteiraAções[[#This Row],[Ativo]],TbAportes[Data],"<="&IF($L$1="",TODAY(),$L$1)) -> 1635 | E6: =SUMIFS(TbAportes[Qte],TbAportes[Ativo],TbCarteiraAções[[#This Row],[Ativo]],TbAportes[Data],"<="&IF($L$1="",TODAY(),$L$1)) -> 200 | F6: =TbCarteiraAções[[#This Row],[Total Aportado]]/E6 -> 8.175 | G6: =TbCarteiraAções[[#This Row],[Cotação]]*TbCarteiraAções[[#This Row],[Total Qte]] -> 2384 | H6: =TbCarteiraAções[[#This Row],[Total Atual]]-TbCarteiraAções[[#This Row],[Total Aportado]] -> 749 | I6: =(TbCarteiraAções[[#This Row],[Total Atual]]/TbCarteiraAções[[#This Row],[Total Aportado]])-1 -> 0.45810398
A7: Total | D7: =SUBTOTAL(109,TbCarteiraAções[Total Aportado]) -> 17598 | G7: =SUBTOTAL(109,TbCarteiraAções[Total Atual]) -> 27979 | H7: =SUBTOTAL(109,TbCarteiraAções[Valorização]) -> 10381

Sheet ReCarteiraFII
A1: Ativo | B1: Tipo | C1: Cotação | D1: Total Aportado | E1: Total Qte | F1: PM | G1: Total Atual | H1: Valorização | I1: Valorização % | K1: Até qual data? | L1: 43830
A2: HGBS11 | B2: =VLOOKUP(TbCarteiraFII[[#This Row],[Ativo]],TbAtivos[],2,FALSE) -> FII | C2: =VLOOKUP(TbCarteiraFII[[#This Row],[Ativo]],TbAtivos[],3,FALSE) -> 229.53 | D2: =SUMIFS(TbAportes[Total],TbAportes[Ativo],TbCarteiraFII[[#This Row],[Ativo]],TbAportes[Data],"<="&IF($L$1="",TODAY(),$L$1)) -> 1714.35 | E2: =SUMIFS(TbAportes[Qte],TbAportes[Ativo],TbCarteiraFII[[#This Row],[Ativo]],TbAportes[Data],"<="&IF($L$1="",TODAY(),$L$1)) -> 9 | F2: =TbCarteiraFII[[#This Row],[Total Aportado]]/E2 -> 190.48333 | G2: =TbCarteiraFII[[#This Row],[Cotação]]*TbCarteiraFII[[#This Row],[Total Qte]] -> 2065.77 | H2: =TbCarteiraFII[[#This Row],[Total Atual]]-TbCarteiraFII[[#This Row],[Total Aportado]] -> 351.42 | I2: =(TbCarteiraFII[[#This Row],[Total Atual]]/TbCarteiraFII[[#This Row],[Total Aportado]])-1 -> 0.20498731
A3: HGLG11 | B3: =VLOOKUP(TbCarteiraFII[[#This Row],[Ativo]],TbAtivos[],2,FALSE) -> FII | C3: =VLOOKUP(TbCarteiraFII[[#This Row],[Ativo]],TbAtivos[],3,FALSE) -> 169.66 | D3: =SUMIFS(TbAportes[Total],TbAportes[Ativo],TbCarteiraFII[[#This Row],[Ativo]],TbAportes[Data],"<="&IF($L$1="",TODAY(),$L$1)) -> 2350.81 | E3: =SUMIFS(TbAportes[Qte],TbAportes[Ativo],TbCarteiraFII[[#This Row],[Ativo]],TbAportes[Data],"<="&IF($L$1="",TODAY(),$L$1)) -> 17 | F3: =TbCarteiraFII[[#This Row],[Total Aportado]]/E3 -> 138.28294 | G3: =TbCarteiraFII[[#This Row],[Cotação]]*TbCarteiraFII[[#This Row],[Total Qte]] -> 2884.22 | H3: =TbCarteiraFII[[#This Row],[Total Atual]]-TbCarteiraFII[[#This Row],[Total Aportado]] -> 533.41 | I3: =(TbCarteiraFII[[#This Row],[Total Atual]]/TbCarteiraFII[[#This Row],[Total Aportado]])-1 -> 0.22690477
A4: HGRE11 | B4: =VLOOKUP(TbCarteiraFII[[#This Row],[Ativo]],TbAtivos[],2,FALSE) -> FII | C4: =VLOOKUP(TbCarteiraFII[[#This Row],[Ativo]],TbAtivos[],3,FALSE) -> 128.81 | D4: =SUMIFS(TbAportes[Total],TbAportes[Ativo],TbCarteiraFII[[#This Row],[Ativo]],TbAportes[Data],"<="&IF($L$1="",TODAY(),$L$1)) -> 1938.77 | E4: =SUMIFS(TbAportes[Qte],TbAportes[Ativo],TbCarteiraFII[[#This Row],[Ativo]],TbAportes[Data],"<="&IF($L$1="",TODAY(),$L$1)) -> 15 | F4: =TbCarteiraFII[[#This Row],[Total Aportado]]/E4 -> 129.25133 | G4: =TbCarteiraFII[[#This Row],[Cotação]]*TbCarteiraFII[[#This Row],[Total Qte]] -> 1932.15 | H4: =TbCarteiraFII[[#This Row],[Total Atual]]-TbCarteiraFII[[#This Row],[Total Aportado]] -> -6.62 | I4: =(TbCarteiraFII[[#This Row],[Total Atual]]/TbCarteiraFII[[#This Row],[Total Aportado]])-1 -> -0.003414536
A5: KNRI11 | B5: =VLOOKUP(TbCarteiraFII[[#This Row],[Ativo]],TbAtivos[],2,FALSE) -> FII | C5: =VLOOKUP(TbCarteiraFII[[#This Row],[Ativo]],TbAtivos[],3,FALSE) -> 164.75 | D5: =SUMIFS(TbAportes[Total],TbAportes[Ativo],TbCarteiraFII[[#This Row],[Ativo]],TbAportes[Data],"<="&IF($L$1="",TODAY(),$L$1)) -> 1109.3 | E5: =SUMIFS(TbAportes[Qte],TbAportes[Ativo],TbCarteiraFII[[#This Row],[Ativo]],TbAportes[Data],"<="&IF($L$1="",TODAY(),$L$1)) -> 8 | F5: =TbCarteiraFII[[#This Row],[Total Aportado]]/E5 -> 138.6625 | G5: =TbCarteiraFII[[#This Row],[Cotação]]*TbCarteiraFII[[#This Row],[Total Qte]] -> 1318 | H5: =TbCarteiraFII[[#This Row],[Total Atual]]-TbCarteiraFII[[#This Row],[Total Aportado]] -> 208.7 | I5: =(TbCarteiraFII[[#This Row],[Total Atual]]/TbCarteiraFII[[#This Row],[Total Aportado]])-1 -> 0.18813666
A6: Total | D6: =SUBTOTAL(109,TbCarteiraFII[Total Aportado]) -> 7113.23 | G6: =SUBTOTAL(109,TbCarteiraFII[Total Atual]) -> 8200.14 | H6: =SUBTOTAL(109,TbCarteiraFII[Valorização]) -> 1086.91

Sheet ReProventos
A3: Sum of Valor Líquido | B3: Column Labels
A4: Row Labels | B4: 2018/12 | C4: 2019/01 | D4: 2019/02 | E4: 2019/03 | F4: 2019/04 | G4: 2019/05 | H4: 2019/06 | I4: 2019/07 | J4: 2019/08 | K4: 2019/09 | L4: 2019/10 | M4: 2020/01 | N4: Grand Total
A5: EMPRESA | B5: 39.48 | C5: 61 | D5: 65.43 | E5: 163.66 | F5: 162.75 | G5: 156.14 | H5: 166 | I5: 162.75 | J5: 156.14 | K5: 166 | L5: 484.89 | M5: 162.75 | N5: 1946.99
A6: CSNA3 | K6: 166 | N6: 166
A7: FLRY3 | E7: 163.66 | J7: 156.14 | N7: 319.8
A8: ITSA4 | B8: 39.48 | D8: 65.43 | F8: 162.75 | H8: 166 | L8: 328.75 | N8: 762.41
A9: PETR4 | C9: 61 | I9: 162.75 | N9: 223.75
A10: TAEE4 | G10: 156.14 | L10: 156.14 | M10: 162.75 | N10: 475.03
A11: FII | B11: 217.66 | C11: 228.62 | D11: 358.32 | E11: 308.72 | F11: 433.18 | G11: 358.32 | H11: 308.72 | I11: 433.18 | J11: 357.29 | K11: 308.72 | L11: 1100.22 | M11: 433.18 | N11: 4846.13
A12: HGBS11 | B12: 63 | C12: 75.71 | D12: 61 | E12: 37.44 | F12: 61 | G12: 61 | H12: 37.44 | I12: 61 | J12: 59.97 | K12: 37.44 | L12: 159.44 | M12: 61 | N12: 775.44
A13: HGLG11 | B13: 81 | C13: 39.36 | D13: 99 | E13: 52.02 | F13: 180.6 | G13: 99 | H13: 52.02 | I13: 180.6 | J13: 99 | K13: 52.02 | L13: 331.62 | M13: 180.6 | N13: 1446.84
A14: HGRE11 | B14: 38.89 | C14: 51.8 | D14: 99.9 | E14: 42.14 | F14: 38.4 | G14: 99.9 | H14: 42.14 | I14: 38.4 | J14: 99.9 | K14: 42.14 | L14: 180.44 | M14: 38.4 | N14: 812.45
A15: KNRI11 | B15: 34.77 | C15: 61.75 | D15: 98.42 | E15: 177.12 | F15: 153.18 | G15: 98.42 | H15: 177.12 | I15: 153.18 | J15: 98.42 | K15: 177.12 | L15: 428.72 | M15: 153.18 | N15: 1811.4
A16: #N/A | D16: 0 | N16: 0
A17: HGBS12 | D17: 0 | N17: 0
A18: Grand Total | B18: 257.14 | C18: 289.62 | D18: 423.75 | E18: 472.38 | F18: 595.93 | G18: 514.46 | H18: 474.72 | I18: 595.93 | J18: 513.43 | K18: 474.72 | L18: 1585.11 | M18: 595.93 | N18: 6793.12

Sheet ReAportes
A3: Sum of Total | B3: Column Labels
A4: Row Labels | B4: 2018/12 | C4: 2019/01 | D4: 2019/02 | E4: 2019/03 | F4: 2019/04 | G4: 2019/05 | H4: 2019/06 | I4: 2019/07 | J4: 2019/08 | K4: 2019/09 | L4: 2019/10 | M4: 2019/11 | N4: 2019/12 | O4: 2020/01 | P4: Grand Total
A5: EMPRESA | B5: 1594 | C5: 1644 | D5: 788 | E5: 1985 | G5: 1721 | H5: 1591 | I5: 2042 | J5: 1766 | K5: 1022 | L5: 1613 | M5: 963 | N5: 869 | P5: 17598
A6: CSNA3 | B6: 833 | G6: 955 | K6: 1022 | P6: 2810
A7: FLRY3 | E7: 1985 | I7: 2042 | P7: 4027
A8: ITSA4 | B8: 761 | D8: 788 | M8: 963 | P8: 2512
A9: PETR4 | C9: 1644 | H9: 1591 | J9: 1766 | L9: 1613 | P9: 6614
A10: TAEE4 | G10: 766 | N10: 869 | P10: 1635
A11: FII | C11: 704.9 | D11: 991.52 | E11: 551.46 | F11: 635.83 | H11: 679.05 | I11: 191.74 | J11: 972.58 | K11: 268.2 | L11: 971.15 | M11: 430.65 | N11: 716.15 | O11: 2079.8 | P11: 9193.03
A12: HGBS11 | E12: 551.46 | I12: 191.74 | L12: 971.15 | P12: 1714.35
A13: HGLG11 | C13: 704.9 | F13: 242.68 | J13: 972.58 | M13: 430.65 | P13: 2350.81
A14: HGRE11 | D14: 991.52 | H14: 679.05 | K14: 268.2 | O14: 553.8 | P14: 2492.57
A15: KNRI11 | F15: 393.15 | N15: 716.15 | O15: 1526 | P15: 2635.3
A16: Grand Total | B16: 1594 | C16: 2348.9 | D16: 1779.52 | E16: 2536.46 | F16: 635.83 | G16: 1721 | H16: 2270.05 | I16: 2233.74 | J16: 2738.58 | K16: 1290.2 | L16: 2584.15 | M16: 1393.65 | N16: 1585.15 | O16: 2079.8 | P16: 26791.03

Sheet TbAportes
A1: Data | B1: Ativo | C1: Qte | D1: Valor unitário | E1: Custo | F1: Total | G1: Tipo | H1: Ano | I1: Mês | J1: Ano/Mês
A2: 43444 | B2: ITSA4 | C2: 100 | D2: 7.51 | E2: 10 | F2: =TbAportes[[#This Row],[Qte]]*TbAportes[[#This Row],[Valor unitário]]+TbAportes[[#This Row],[Custo]] -> 761 | G2: =VLOOKUP(TbAportes[[#This Row],[Ativo]],TbAtivos[],2,FALSE) -> EMPRESA | H2: =YEAR(TbAportes[[#This Row],[Data]]) -> 2018 | I2: =MONTH(TbAportes[[#This Row],[Data]]) -> 12 | J2: =_xlfn.CONCAT(TbAportes[[#This Row],[Ano]],"/",IF(TbAportes[[#This Row],[Mês]]<10,_xlfn.CONCAT(0,TbAportes[[#This Row],[Mês]]),TbAportes[[#This Row],[Mês]])) -> 2018/12
A3: 43444 | B3: CSNA3 | C3: 100 | D3: 8.23 | E3: 10 | F3: =TbAportes[[#This Row],[Qte]]*TbAportes[[#This Row],[Valor unitário]]+TbAportes[[#This Row],[Custo]] -> 833 | G3: =VLOOKUP(TbAportes[[#This Row],[Ativo]],TbAtivos[],2,FALSE) -> EMPRESA | H3: =YEAR(TbAportes[[#This Row],[Data]]) -> 2018 | I3: =MONTH(TbAportes[[#This Row],[Data]]) -> 12 | J3: =_xlfn.CONCAT(TbAportes[[#This Row],[Ano]],"/",IF(TbAportes[[#This Row],[Mês]]<10,_xlfn.CONCAT(0,TbAportes[[#This Row],[Mês]]),TbAportes[[#This Row],[Mês]])) -> 2018/12
A4: 43475 | B4: PETR4 | C4: 100 | D4: 16.34 | E4: 10 | F4: =TbAportes[[#This Row],[Qte]]*TbAportes[[#This Row],[Valor unitário]]+TbAportes[[#This Row],[Custo]] -> 1644 | G4: =VLOOKUP(TbAportes[[#This Row],[Ativo]],TbAtivos[],2,FALSE) -> EMPRESA | H4: =YEAR(TbAportes[[#This Row],[Data]]) -> 2019 | I4: =MONTH(TbAportes[[#This Row],[Data]]) -> 1 | J4: =_xlfn.CONCAT(TbAportes[[#This Row],[Ano]],"/",IF(TbAportes[[#This Row],[Mês]]<10,_xlfn.CONCAT(0,TbAportes[[#This Row],[Mês]]),TbAportes[[#This Row],[Mês]])) -> 2019/01
A5: 43475 | B5: HGLG11 | C5: 5 | D5: 140.98 | E5: 0 | F5: =TbAportes[[#This Row],[Qte]]*TbAportes[[#This Row],[Valor unitário]]+TbAportes[[#This Row],[Custo]] -> 704.9 | G5: =VLOOKUP(TbAportes[[#This Row],[Ativo]],TbAtivos[],2,FALSE) -> FII | H5: =YEAR(TbAportes[[#This Row],[Data]]) -> 2019 | I5: =MONTH(TbAportes[[#This Row],[Data]]) -> 1 | J5: =_xlfn.CONCAT(TbAportes[[#This Row],[Ano]],"/",IF(TbAportes[[#This Row],[Mês]]<10,_xlfn.CONCAT(0,TbAportes[[#This Row],[Mês]]),TbAportes[[#This Row],[Mês]])) -> 2019/01
A6: 43506 | B6: ITSA4 | C6: 100 | D6: 7.78 | E6: 10 | F6: =TbAportes[[#This Row],[Qte]]*TbAportes[[#This Row],[Valor unitário]]+TbAportes[[#This Row],[Custo]] -> 788 | G6: =VLOOKUP(TbAportes[[#This Row],[Ativo]],TbAtivos[],2,FALSE) -> EMPRESA | H6: =YEAR(TbAportes[[#This Row],[Data]]) -> 2019 | I6: =MONTH(TbAportes[[#This Row],[Data]]) -> 2 | J6: =_xlfn.CONCAT(TbAportes[[#This Row],[Ano]],"/",IF(TbAportes[[#This Row],[Mês]]<10,_xlfn.CONCAT(0,TbAportes[[#This Row],[Mês]]),TbAportes[[#This Row],[Mês]])) -> 2019/02
A7: 43506 | B7: HGRE11 | C7: 8 | D7: 123.94 | E7: 0 | F7: =TbAportes[[#This Row],[Qte]]*TbAportes[[#This Row],[Valor unitário]]+TbAportes[[#This Row],[Custo]] -> 991.52 | G7: =VLOOKUP(TbAportes[[#This Row],[Ativo]],TbAtivos[],2,FALSE) -> FII | H7: =YEAR(TbAportes[[#This Row],[Data]]) -> 2019 | I7: =MONTH(TbAportes[[#This Row],[Data]]) -> 2 | J7: =_xlfn.CONCAT(TbAportes[[#This Row],[Ano]],"/",IF(TbAportes[[#This Row],[Mês]]<10,_xlfn.CONCAT(0,TbAportes[[#This Row],[Mês]]),TbAportes[[#This Row],[Mês]])) -> 2019/02
A8: 43534 | B8: FLRY3 | C8: 100 | D8: 19.75 | E8: 10 | F8: =TbAportes[[#This Row],[Qte]]*TbAportes[[#This Row],[Valor unitário]]+TbAportes[[#This Row],[Custo]] -> 1985 | G8: =VLOOKUP(TbAportes[[#This Row],[Ativo]],TbAtivos[],2,FALSE) -> EMPRESA | H8: =YEAR(TbAportes[[#This Row],[Data]]) -> 2019 | I8: =MONTH(TbAportes[[#This Row],[Data]]) -> 3 | J8: =_xlfn.CONCAT(TbAportes[[#This Row],[Ano]],"/",IF(TbAportes[[#This Row],[Mês]]<10,_xlfn.CONCAT(0,TbAportes[[#This Row],[Mês]]),TbAportes[[#This Row],[Mês]])) -> 2019/03
A9: 43534 | B9: HGBS11 | C9: 3 | D9: 183.82 | E9: 0 | F9: =TbAportes[[#This Row],[Qte]]*TbAportes[[#This Row],[Valor unitário]]+TbAportes[[#This Row],[Custo]] -> 551.46 | G9: =VLOOKUP(TbAportes[[#This Row],[Ativo]],TbAtivos[],2,FALSE) -> FII | H9: =YEAR(TbAportes[[#This Row],[Data]]) -> 2019 | I9: =MONTH(TbAportes[[#This Row],[Data]]) -> 3 | J9: =_xlfn.CONCAT(TbAportes[[#This Row],[Ano]],"/",IF(TbAportes[[#This Row],[Mês]]<10,_xlfn.CONCAT(0,TbAportes[[#This Row],[Mês]]),TbAportes[[#This Row],[Mês]])) -> 2019/03
A10: 43565 | B10: HGLG11 | C10: 2 | D10: 121.34 | E10: 0 | F10: =TbAportes[[#This Row],[Qte]]*TbAportes[[#This Row],[Valor unitário]]+TbAportes[[#This Row],[Custo]] -> 242.68 | G10: =VLOOKUP(TbAportes[[#This Row],[Ativo]],TbAtivos[],2,FALSE) -> FII | H10: =YEAR(TbAportes[[#This Row],[Data]]) -> 2019 | I10: =MONTH(TbAportes[[#This Row],[Data]]) -> 4 | J10: =_xlfn.CONCAT(TbAportes[[#This Row],[Ano]],"/",IF(TbAportes[[#This Row],[Mês]]<10,_xlfn.CONCAT(0,TbAportes[[#This Row],[Mês]]),TbAportes[[#This Row],[Mês]])) -> 2019/04
A11: 43565 | B11: KNRI11 | C11: 3 | D11: 131.05 | E11: 0 | F11: =TbAportes[[#This Row],[Qte]]*TbAportes[[#This Row],[Valor unitário]]+TbAportes[[#This Row],[Custo]] -> 393.15 | G11: =VLOOKUP(TbAportes[[#This Row],[Ativo]],TbAtivos[],2,FALSE) -> FII | H11: =YEAR(TbAportes[[#This Row],[Data]]) -> 2019 | I11: =MONTH(TbAportes[[#This Row],[Data]]) -> 4 | J11: =_xlfn.CONCAT(TbAportes[[#This Row],[Ano]],"/",IF(TbAportes[[#This Row],[Mês]]<10,_xlfn.CONCAT(0,TbAportes[[#This Row],[Mês]]),TbAportes[[#This Row],[Mês]])) -> 2019/04
A12: 43595 | B12: CSNA3 | C12: 100 | D12: 9.45 | E12: 10 | F12: =TbAportes[[#This Row],[Qte]]*TbAportes[[#This Row],[Valor unitário]]+TbAportes[[#This Row],[Custo]] -> 955 | G12: =VLOOKUP(TbAportes[[#This Row],[Ativo]],TbAtivos[],2,FALSE) -> EMPRESA | H12: =YEAR(TbAportes[[#This Row],[Data]]) -> 2019 | I12: =MONTH(TbAportes[[#This Row],[Data]]) -> 5 | J12: =_xlfn.CONCAT(TbAportes[[#This Row],[Ano]],"/",IF(TbAportes[[#This Row],[Mês]]<10,_xlfn.CONCAT(0,TbAportes[[#This Row],[Mês]]),TbAportes[[#This Row],[Mês]])) -> 2019/05
A13: 43595 | B13: TAEE4 | C13: 100 | D13: 7.56 | E13: 10 | F13: =TbAportes[[#This Row],[Qte]]*TbAportes[[#This Row],[Valor unitário]]+TbAportes[[#This Row],[Custo]] -> 766 | G13: =VLOOKUP(TbAportes[[#This Row],[Ativo]],TbAtivos[],2,FALSE) -> EMPRESA | H13: =YEAR(TbAportes[[#This Row],[Data]]) -> 2019 | I13: =MONTH(TbAportes[[#This Row],[Data]]) -> 5 | J13: =_xlfn.CONCAT(TbAportes[[#This Row],[Ano]],"/",IF(TbAportes[[#This Row],[Mês]]<10,_xlfn.CONCAT(0,TbAportes[[#This Row],[Mês]]),TbAportes[[#This Row],[Mês]])) -> 2019/05
... A29: 43840 | B29: HGRE11 | C29: 4 | D29: 138.45 | E29: 0 | F29: =TbAportes[[#This Row],[Qte]]*TbAportes[[#This Row],[Valor unitário]]+TbAportes[[#This Row],[Custo]] -> 553.8 | G29: =VLOOKUP(TbAportes[[#This Row],[Ativo]],TbAtivos[],2,FALSE) -> FII | H29: =YEAR(TbAportes[[#This Row],[Data]]) -> 2020 | I29: =MONTH(TbAportes[[#This Row],[Data]]) -> 1 | J29: =_xlfn.CONCAT(TbAportes[[#This Row],[Ano]],"/",IF(TbAportes[[#This Row],[Mês]]<10,_xlfn.CONCAT(0,TbAportes[[#This Row],[Mês]]),TbAportes[[#This Row],[Mês]])) -> 2020/01

Sheet TbProventos
A1: Cod | B1: Ativo | C1: Qte | D1: Valor Bruto | E1: IR | F1: Valor Líquido | G1: Data | H1: Ano/Mês | I1: Tipo
A2: 13 | B2: ITSA4 | C2: 100 | D2: 39.48 | E2: 0 | F2: 39.48 | G2: 43449 | H2: =_xlfn.CONCAT(YEAR(TbProventos[[#This Row],[Data]]),"/",IF(MONTH(TbProventos[[#This Row],[Data]])<10,_xlfn.CONCAT(0,MONTH(TbProventos[[#This Row],[Data]])),MONTH(TbProventos[[#This Row],[Data]]))) -> 2018/12 | I2: =VLOOKUP(TbProventos[[#This Row],[Ativo]],TbAtivos[],2,FALSE) -> EMPRESA
A3: 14 | B3: HGBS11 | C3: 100 | D3: 63 | E3: 0 | F3: 63 | G3: 43451 | H3: =_xlfn.CONCAT(YEAR(TbProventos[[#This Row],[Data]]),"/",IF(MONTH(TbProventos[[#This Row],[Data]])<10,_xlfn.CONCAT(0,MONTH(TbProventos[[#This Row],[Data]])),MONTH(TbProventos[[#This Row],[Data]]))) -> 2018/12 | I3: =VLOOKUP(TbProventos[[#This Row],[Ativo]],TbAtivos[],2,FALSE) -> FII
A4: 14 | B4: HGLG11 | C4: 100 | D4: 81 | E4: 0 | F4: 81 | G4: 43451 | H4: =_xlfn.CONCAT(YEAR(TbProventos[[#This Row],[Data]]),"/",IF(MONTH(TbProventos[[#This Row],[Data]])<10,_xlfn.CONCAT(0,MONTH(TbProventos[[#This Row],[Data]])),MONTH(TbProventos[[#This Row],[Data]]))) -> 2018/12 | I4: =VLOOKUP(TbProventos[[#This Row],[Ativo]],TbAtivos[],2,FALSE) -> FII
A5: 14 | B5: HGRE11 | C5: 100 | D5: 38.89 | E5: 0 | F5: 38.89 | G5: 43451 | H5: =_xlfn.CONCAT(YEAR(TbProventos[[#This Row],[Data]]),"/",IF(MONTH(TbProventos[[#This Row],[Data]])<10,_xlfn.CONCAT(0,MONTH(TbProventos[[#This Row],[Data]])),MONTH(TbProventos[[#This Row],[Data]]))) -> 2018/12 | I5: =VLOOKUP(TbProventos[[#This Row],[Ativo]],TbAtivos[],2,FALSE) -> FII
A6: 14 | B6: KNRI11 | C6: 100 | D6: 34.77 | E6: 0 | F6: 34.77 | G6: 43451 | H6: =_xlfn.CONCAT(YEAR(TbProventos[[#This Row],[Data]]),"/",IF(MONTH(TbProventos[[#This Row],[Data]])<10,_xlfn.CONCAT(0,MONTH(TbProventos[[#This Row],[Data]])),MONTH(TbProventos[[#This Row],[Data]]))) -> 2018/12 | I6: =VLOOKUP(TbProventos[[#This Row],[Ativo]],TbAtivos[],2,FALSE) -> FII
A7: 13 | B7: PETR4 | C7: 100 | D7: 67 | E7: 6 | F7: 61 | G7: 43480 | H7: =_xlfn.CONCAT(YEAR(TbProventos[[#This Row],[Data]]),"/",IF(MONTH(TbProventos[[#This Row],[Data]])<10,_xlfn.CONCAT(0,MONTH(TbProventos[[#This Row],[Data]])),MONTH(TbProventos[[#This Row],[Data]]))) -> 2019/01 | I7: =VLOOKUP(TbProventos[[#This Row],[Ativo]],TbAtivos[],2,FALSE) -> EMPRESA
A8: 14 | B8: HGBS11 | C8: 100 | D8: 75.71 | E8: 0 | F8: 75.71 | G8: 43482 | H8: =_xlfn.CONCAT(YEAR(TbProventos[[#This Row],[Data]]),"/",IF(MONTH(TbProventos[[#This Row],[Data]])<10,_xlfn.CONCAT(0,MONTH(TbProventos[[#This Row],[Data]])),MONTH(TbProventos[[#This Row],[Data]]))) -> 2019/01 | I8: =VLOOKUP(TbProventos[[#This Row],[Ativo]],TbAtivos[],2,FALSE) -> FII
A9: 14 | B9: HGLG11 | C9: 100 | D9: 39.36 | E9: 0 | F9: 39.36 | G9: 43482 | H9: =_xlfn.CONCAT(YEAR(TbProventos[[#This Row],[Data]]),"/",IF(MONTH(TbProventos[[#This Row],[Data]])<10,_xlfn.CONCAT(0,MONTH(TbProventos[[#This Row],[Data]])),MONTH(TbProventos[[#This Row],[Data]]))) -> 2019/01 | I9: =VLOOKUP(TbProventos[[#This Row],[Ativo]],TbAtivos[],2,FALSE) -> FII
A10: 14 | B10: HGRE11 | C10: 100 | D10: 51.8 | E10: 0 | F10: 51.8 | G10: 43482 | H10: =_xlfn.CONCAT(YEAR(TbProventos[[#This Row],[Data]]),"/",IF(MONTH(TbProventos[[#This Row],[Data]])<10,_xlfn.CONCAT(0,MONTH(TbProventos[[#This Row],[Data]])),MONTH(TbProventos[[#This Row],[Data]]))) -> 2019/01 | I10: =VLOOKUP(TbProventos[[#This Row],[Ativo]],TbAtivos[],2,FALSE) -> FII
A11: 14 | B11: KNRI11 | C11: 100 | D11: 61.75 | E11: 0 | F11: 61.75 | G11: 43482 | H11: =_xlfn.CONCAT(YEAR(TbProventos[[#This Row],[Data]]),"/",IF(MONTH(TbProventos[[#This Row],[Data]])<10,_xlfn.CONCAT(0,MONTH(TbProventos[[#This Row],[Data]])),MONTH(TbProventos[[#This Row],[Data]]))) -> 2019/01 | I11: =VLOOKUP(TbProventos[[#This Row],[Ativo]],TbAtivos[],2,FALSE) -> FII
A12: 13 | B12: ITSA4 | C12: 100 | D12: 65.43 | E12: 0 | F12: 65.43 | G12: 43511 | H12: =_xlfn.CONCAT(YEAR(TbProventos[[#This Row],[Data]]),"/",IF(MONTH(TbProventos[[#This Row],[Data]])<10,_xlfn.CONCAT(0,MONTH(TbProventos[[#This Row],[Data]])),MONTH(TbProventos[[#This Row],[Data]]))) -> 2019/02 | I12: =VLOOKUP(TbProventos[[#This Row],[Ativo]],TbAtivos[],2,FALSE) -> EMPRESA
A13: 50 | B13: HGBS12 | C13: 100 | D13: 0 | E13: 0 | F13: 0 | G13: 43511 | H13: =_xlfn.CONCAT(YEAR(TbProventos[[#This Row],[Data]]),"/",IF(MONTH(TbProventos[[#This Row],[Data]])<10,_xlfn.CONCAT(0,MONTH(TbProventos[[#This Row],[Data]])),MONTH(TbProventos[[#This Row],[Data]]))) -> 2019/02 | I13: =VLOOKUP(TbProventos[[#This Row],[Ativo]],TbAtivos[],2,FALSE) -> #N/A
... A72: 14 | B72: KNRI11 | C72: 100 | D72: 153.18 | E72: 0 | F72: 153.18 | G72: 43847 | H72: =_xlfn.CONCAT(YEAR(TbProventos[[#This Row],[Data]]),"/",IF(MONTH(TbProventos[[#This Row],[Data]])<10,_xlfn.CONCAT(0,MONTH(TbProventos[[#This Row],[Data]])),MONTH(TbProventos[[#This Row],[Data]]))) -> 2020/01 | I72: =VLOOKUP(TbProventos[[#This Row],[Ativo]],TbAtivos[],2,FALSE) -> FII

Sheet TbAtivos
A1: ATIVO | B1: TIPO | C1: COTAÇÃO
A2: CSNA3 | B2: EMPRESA | C2: 16.07
A3: FLRY3 | B3: EMPRESA | C3: 15.42
A4: ITSA4 | B4: EMPRESA | C4: 10.3
A5: PETR4 | B5: EMPRESA | C5: 36.5
A6: HGBS11 | B6: FII | C6: 229.53
A7: HGLG11 | B7: FII | C7: 169.66
A8: HGRE11 | B8: FII | C8: 128.81
A9: KNRI11 | B9: FII | C9: 164.75
A10: TAEE4 | B10: EMPRESA | C10: 11.92
